Workbook

Sheet Registre de reserves
A1: ANY | B1: MES | C1: DATA | D1: DIA | E1: FESTIU | F1: ESPECIAL | G1: HORA ENTRADA | H1: HORA SORTIDA | I1: HORARI | J1: TORNS | K1: NOM CLIENT | L1: CODI POSTAL | M1: MUNICIPI | N1: DIRECCIÓ | O1: DNI | P1: TARIFA | Q1: HORAS EXTRAS | R1: IMPORTE EXTRAS | S1: IMPORTE TOTAL | T1: COBRAT | U1: RES-A | V1: RES-B | W1: EXTR-A | X1: EXTR-B | Y1: OBSERVACIONS | Z1: Columna1 | AA1: Columna2
A2: 2020 | B2: GENER | C2: 43831 | D2: DIMECRES | E2: SI | F2: NO | G2: 0.52083333 | H2: 0.85416667 | I2: DINAR | J2: 2 | P2: 200 | Q2: 0 | R2: 0 | S2: =Tabla1[[#This Row],[TARIFA]]+Tabla1[[#This Row],[IMPORTE EXTRAS]] -> 200 | T2: SI | U2: 0 | V2: 200 | W2: 0 | X2: 0 | Y2: ANUAL | Z2: =SUM(Tabla1[[#This Row],[RES-A]:[EXTR-B]]) -> 200 | AA2: =Tabla1[[#This Row],[Columna1]]-Tabla1[[#This Row],[IMPORTE TOTAL]] -> 0
A3: 2020 | B3: GENER | C3: 43832 | D3: DIJOUS | E3: NO | F3: NO | G3: 0.64583333 | H3: 0.85416667 | I3: TARDA | J3: 2 | P3: 95 | Q3: 0 | R3: 0 | S3: =Tabla1[[#This Row],[TARIFA]]+Tabla1[[#This Row],[IMPORTE EXTRAS]] -> 95 | T3: SI | U3: 5 | V3: 90 | W3: 0 | X3: 0 | Z3: =SUM(Tabla1[[#This Row],[RES-A]:[EXTR-B]]) -> 95 | AA3: =Tabla1[[#This Row],[Columna1]]-Tabla1[[#This Row],[IMPORTE TOTAL]] -> 0
A4: 2020 | B4: GENER | C4: 43833 | D4: DIVENDRES | E4: NO | F4: NO | G4: 0.64583333 | H4: 0.85416667 | I4: TARDA | J4: 1 | P4: 135 | Q4: 0 | R4: 0 | S4: =Tabla1[[#This Row],[TARIFA]]+Tabla1[[#This Row],[IMPORTE EXTRAS]] -> 135 | T4: SI | U4: 135 | V4: 0 | W4: 0 | X4: 0 | Z4: =SUM(Tabla1[[#This Row],[RES-A]:[EXTR-B]]) -> 135 | AA4: =Tabla1[[#This Row],[Columna1]]-Tabla1[[#This Row],[IMPORTE TOTAL]] -> 0
A5: 2020 | B5: GENER | C5: 43833 | D5: DIVENDRES | E5: NO | F5: NO | G5: 0.89583333 | H5: 0.10416667 | I5: NIT | J5: 1 | P5: 195 | Q5: 0 | R5: 0 | S5: =Tabla1[[#This Row],[TARIFA]]+Tabla1[[#This Row],[IMPORTE EXTRAS]] -> 195 | T5: SI | U5: 0 | V5: 195 | W5: 0 | X5: 0 | Z5: =SUM(Tabla1[[#This Row],[RES-A]:[EXTR-B]]) -> 195 | AA5: =Tabla1[[#This Row],[Columna1]]-Tabla1[[#This Row],[IMPORTE TOTAL]] -> 0
A6: 2020 | B6: GENER | C6: 43834 | D6: DISSABTE | E6: NO | F6: NO | G6: 0.39583333 | H6: 0.60416667 | I6: MATI | J6: 1 | P6: 145 | Q6: 0 | R6: 0 | S6: =Tabla1[[#This Row],[TARIFA]]+Tabla1[[#This Row],[IMPORTE EXTRAS]] -> 145 | T6: SI | U6: 0 | V6: 145 | W6: 0 | X6: 0 | Z6: =SUM(Tabla1[[#This Row],[RES-A]:[EXTR-B]]) -> 145 | AA6: =Tabla1[[#This Row],[Columna1]]-Tabla1[[#This Row],[IMPORTE TOTAL]] -> 0
A7: 2020 | B7: GENER | C7: 43834 | D7: DISSABTE | E7: NO | F7: NO | G7: 0.64583333 | H7: 0.85416667 | I7: TARDA | J7: 1 | P7: 145 | Q7: 0 | R7: 0 | S7: =Tabla1[[#This Row],[TARIFA]]+Tabla1[[#This Row],[IMPORTE EXTRAS]] -> 145 | T7: SI | U7: 145 | V7: 0 | W7: 0 | X7: 0 | Z7: =SUM(Tabla1[[#This Row],[RES-A]:[EXTR-B]]) -> 145 | AA7: =Tabla1[[#This Row],[Columna1]]-Tabla1[[#This Row],[IMPORTE TOTAL]] -> 0
A8: 2020 | B8: GENER | C8: 43834 | D8: DISSABTE | E8: NO | F8: NO | G8: 0.89583333 | H8: 0.10416667 | I8: NIT | J8: 1 | P8: 195 | Q8: 0 | R8: 0 | S8: =Tabla1[[#This Row],[TARIFA]]+Tabla1[[#This Row],[IMPORTE EXTRAS]] -> 195 | T8: SI | U8: 195 | V8: 0 | W8: 0 | X8: 0 | Z8: =SUM(Tabla1[[#This Row],[RES-A]:[EXTR-B]]) -> 195 | AA8: =Tabla1[[#This Row],[Columna1]]-Tabla1[[#This Row],[IMPORTE TOTAL]] -> 0
A9: 2020 | B9: GENER | C9: 43835 | D9: DIUMENGE | E9: NO | F9: SI | G9: 0.39583333 | H9: 0.60416667 | I9: MATI | J9: 1 | P9: 145 | Q9: 0 | R9: 0 | S9: =Tabla1[[#This Row],[TARIFA]]+Tabla1[[#This Row],[IMPORTE EXTRAS]] -> 145 | T9: SI | U9: 145 | V9: 0 | W9: 0 | X9: 0 | Z9: =SUM(Tabla1[[#This Row],[RES-A]:[EXTR-B]]) -> 145 | AA9: =Tabla1[[#This Row],[Columna1]]-Tabla1[[#This Row],[IMPORTE TOTAL]] -> 0
A10: 2020 | B10: GENER | C10: 43836 | D10: DILLUNS | E10: SI | F10: NO | G10: 0.625 | H10: 0.83333333 | I10: DINAR | J10: 1 | P10: 145 | Q10: 0 | R10: 0 | S10: =Tabla1[[#This Row],[TARIFA]]+Tabla1[[#This Row],[IMPORTE EXTRAS]] -> 145 | T10: SI | U10: 145 | V10: 0 | W10: 0 | X10: 0 | Y10: ANUAL | Z10: =SUM(Tabla1[[#This Row],[RES-A]:[EXTR-B]]) -> 145 | AA10: =Tabla1[[#This Row],[Columna1]]-Tabla1[[#This Row],[IMPORTE TOTAL]] -> 0
A11: 2020 | B11: GENER | C11: 43838 | D11: DIMECRES | E11: NO | F11: NO | G11: 0.64583333 | H11: 0.85416667 | I11: TARDA | J11: 1 | P11: 95 | Q11: 0 | R11: 0 | S11: =Tabla1[[#This Row],[TARIFA]]+Tabla1[[#This Row],[IMPORTE EXTRAS]] -> 95 | T11: SI | U11: 0 | V11: 95 | W11: 0 | X11: 0 | Z11: =SUM(Tabla1[[#This Row],[RES-A]:[EXTR-B]]) -> 95 | AA11: =Tabla1[[#This Row],[Columna1]]-Tabla1[[#This Row],[IMPORTE TOTAL]] -> 0
A12: 2020 | B12: GENER | C12: 43841 | D12: DISSABTE | E12: NO | F12: NO | G12: 0.64583333 | H12: 0.10416667 | I12: TARDA+NIT | J12: 2 | P12: 300 | Q12: 0 | R12: 0 | S12: =Tabla1[[#This Row],[TARIFA]]+Tabla1[[#This Row],[IMPORTE EXTRAS]] -> 300 | T12: SI | U12: 300 | V12: 0 | W12: 0 | X12: 0 | Z12: =SUM(Tabla1[[#This Row],[RES-A]:[EXTR-B]]) -> 300 | AA12: =Tabla1[[#This Row],[Columna1]]-Tabla1[[#This Row],[IMPORTE TOTAL]] -> 0
A13: 2020 | B13: GENER | C13: 43842 | D13: DIUMENGE | E13: NO | F13: NO | G13: 0.39583333 | H13: 0.85416667 | I13: DIA SENCER | J13: 2 | P13: 200 | Q13: 0 | R13: 0 | S13: =Tabla1[[#This Row],[TARIFA]]+Tabla1[[#This Row],[IMPORTE EXTRAS]] -> 200 | T13: SI | U13: 200 | V13: 0 | W13: 0 | X13: 0 | Z13: =SUM(Tabla1[[#This Row],[RES-A]:[EXTR-B]]) -> 200 | AA13: =Tabla1[[#This Row],[Columna1]]-Tabla1[[#This Row],[IMPORTE TOTAL]] -> 0
A14: 2020 | B14: GENER | C14: 43847 | D14: DIVENDRES | E14: NO | F14: NO | G14: 0.89583333 | H14: 0.10416667 | I14: NIT | J14: 1 | P14: 195 | Q14: 1 | R14: 50 | S14: =Tabla1[[#This Row],[TARIFA]]+Tabla1[[#This Row],[IMPORTE EXTRAS]] -> 245 | T14: SI | U14: 195 | V14: 0 | W14: 0 | X14: 50 | Z14: =SUM(Tabla1[[#This Row],[RES-A]:[EXTR-B]]) -> 245 | AA14: =Tabla1[[#This Row],[Columna1]]-Tabla1[[#This Row],[IMPORTE TOTAL]] -> 0
A15: 2020 | B15: GENER | C15: 43848 | D15: DISSABTE | E15: NO | F15: NO | G15: 0.64583333 | H15: 0.85416667 | I15: TARDA | J15: 1 | P15: 145 | Q15: 0 | R15: 0 | S15: =Tabla1[[#This Row],[TARIFA]]+Tabla1[[#This Row],[IMPORTE EXTRAS]] -> 145 | T15: SI | U15: 100 | V15: 45 | W15: 0 | X15: 0 | Z15: =SUM(Tabla1[[#This Row],[RES-A]:[EXTR-B]]) -> 145 | AA15: =Tabla1[[#This Row],[Columna1]]-Tabla1[[#This Row],[IMPORTE TOTAL]] -> 0
A16: 2020 | B16: GENER | C16: 43848 | D16: DISSABTE | E16: NO | F16: NO | G16: 0.89583333 | H16: 0.10416667 | I16: NIT | J16: 1 | P16: 195 | Q16: 0 | R16: 0 | S16: =Tabla1[[#This Row],[TARIFA]]+Tabla1[[#This Row],[IMPORTE EXTRAS]] -> 195 | T16: SI | U16: 0 | V16: 195 | W16: 0 | X16: 0 | Z16: =SUM(Tabla1[[#This Row],[RES-A]:[EXTR-B]]) -> 195 | AA16: =Tabla1[[#This Row],[Columna1]]-Tabla1[[#This Row],[IMPORTE TOTAL]] -> 0
A17: 2020 | B17: GENER | C17: 43849 | D17: DIUMENGE | E17: NO | F17: NO | G17: 0.64583333 | H17: 0.85416667 | I17: TARDA | J17: 1 | P17: 145 | Q17: 0 | R17: 0 | S17: =Tabla1[[#This Row],[TARIFA]]+Tabla1[[#This Row],[IMPORTE EXTRAS]] -> 145 | T17: SI | U17: 0 | V17: 145 | W17: 0 | X17: 0 | Z17: =SUM(Tabla1[[#This Row],[RES-A]:[EXTR-B]]) -> 145 | AA17: =Tabla1[[#This Row],[Columna1]]-Tabla1[[#This Row],[IMPORTE TOTAL]] -> 0
A18: 2020 | B18: GENER | C18: 43855 | D18: DISSABTE | E18: NO | F18: NO | G18: 0.39583333 | H18: 0.60416667 | I18: MATI | J18: 1 | P18: 145 | Q18: 0 | R18: 0 | S18: =Tabla1[[#This Row],[TARIFA]]+Tabla1[[#This Row],[IMPORTE EXTRAS]] -> 145 | T18: SI | U18: 50 | V18: 95 | W18: 0 | X18: 0 | Z18: =SUM(Tabla1[[#This Row],[RES-A]:[EXTR-B]]) -> 145 | AA18: =Tabla1[[#This Row],[Columna1]]-Tabla1[[#This Row],[IMPORTE TOTAL]] -> 0
A19: 2020 | B19: GENER | C19: 43855 | D19: DISSABTE | E19: NO | F19: NO | G19: 0.89583333 | H19: 0.10416667 | I19: NIT | J19: 1 | P19: 195 | Q19: 0 | R19: 0 | S19: =Tabla1[[#This Row],[TARIFA]]+Tabla1[[#This Row],[IMPORTE EXTRAS]] -> 195 | T19: SI | U19: 0 | V19: 195 | W19: 0 | X19: 0 | Z19: =SUM(Tabla1[[#This Row],[RES-A]:[EXTR-B]]) -> 195 | AA19: =Tabla1[[#This Row],[Columna1]]-Tabla1[[#This Row],[IMPORTE TOTAL]] -> 0
A20: 2020 | B20: GENER | C20: 43856 | D20: DIUMENGE | E20: NO | F20: NO | G20: 0.64583333 | H20: 0.85416667 | I20: TARDA | J20: 1 | P20: 145 | Q20: 0 | R20: 0 | S20: =Tabla1[[#This Row],[TARIFA]]+Tabla1[[#This Row],[IMPORTE EXTRAS]] -> 145 | T20: SI | U20: 50 | V20: 95 | W20: 0 | X20: 0 | Z20: =SUM(Tabla1[[#This Row],[RES-A]:[EXTR-B]]) -> 145 | AA20: =Tabla1[[#This Row],[Columna1]]-Tabla1[[#This Row],[IMPORTE TOTAL]] -> 0
A21: 2020 | B21: GENER | C21: 43861 | D21: DIVENDRES | E21: NO | F21: NO | G21: 0.64583333 | H21: 0.85416667 | I21: TARDA | J21: 1 | P21: 135 | Q21: 0 | R21: 0 | S21: =Tabla1[[#This Row],[TARIFA]]+Tabla1[[#This Row],[IMPORTE EXTRAS]] -> 135 | T21: SI | U21: 0 | V21: 135 | W21: 0 | X21: 0 | Z21: =SUM(Tabla1[[#This Row],[RES-A]:[EXTR-B]]) -> 135 | AA21: =Tabla1[[#This Row],[Columna1]]-Tabla1[[#This Row],[IMPORTE TOTAL]] -> 0
A22: 2020 | B22: GENER | C22: 43861 | D22: DIVENDRES | E22: NO | F22: NO | G22: 0.89583333 | H22: 0.10416667 | I22: NIT | J22: 1 | P22: 195 | Q22: 0 | R22: 0 | S22: =Tabla1[[#This Row],[TARIFA]]+Tabla1[[#This Row],[IMPORTE EXTRAS]] -> 195 | T22: SI | U22: 50 | V22: 145 | W22: 0 | X22: 0 | Z22: =SUM(Tabla1[[#This Row],[RES-A]:[EXTR-B]]) -> 195 | AA22: =Tabla1[[#This Row],[Columna1]]-Tabla1[[#This Row],[IMPORTE TOTAL]] -> 0
... A34: 2020 | B34: FEBRER | C34: 43883 | D34: DISSABTE | E34: NO | F34: NO | G34: 0.64583333 | H34: 0.85416667 | I34: TARDA | J34: 1 | P34: 145 | Q34: 1 | R34: 5 | S34: =Tabla1[[#This Row],[TARIFA]]+Tabla1[[#This Row],[IMPORTE EXTRAS]] -> 150 | T34: SI | U34: 0 | V34: 145 | W34: 0 | X34: 5 | Z34: =SUM(Tabla1[[#This Row],[RES-A]:[EXTR-B]]) -> 150 | AA34: =Tabla1[[#This Row],[Columna1]]-Tabla1[[#This Row],[IMPORTE TOTAL]] -> 0
A35: 2020 | B35: FEBRER | C35: 43883 | D35: DISSABTE | E35: NO | F35: NO | G35: 0.89583333 | H35: 0.10416667 | I35: NIT | J35: 1 | P35: 195 | Q35: 1 | R35: 5 | S35: =Tabla1[[#This Row],[TARIFA]]+Tabla1[[#This Row],[IMPORTE EXTRAS]] -> 200 | T35: SI | U35: 0 | V35: 195 | W35: 0 | X35: 5 | Y35: ANUAL | Z35: =SUM(Tabla1[[#This Row],[RES-A]:[EXTR-B]]) -> 200 | AA35: =Tabla1[[#This Row],[Columna1]]-Tabla1[[#This Row],[IMPORTE TOTAL]] -> 0
A36: 2020 | B36: FEBRER | C36: 43884 | D36: DIUMENGE | E36: NO | F36: NO | G36: 0.39583333 | H36: 0.60416667 | I36: MATI | J36: 1 | P36: 145 | Q36: 0 | R36: 0 | S36: =Tabla1[[#This Row],[TARIFA]]+Tabla1[[#This Row],[IMPORTE EXTRAS]] -> 145 | T36: SI | U36: 145 | V36: 0 | W36: 0 | X36: 0 | Z36: =SUM(Tabla1[[#This Row],[RES-A]:[EXTR-B]]) -> 145 | AA36: =Tabla1[[#This Row],[Columna1]]-Tabla1[[#This Row],[IMPORTE TOTAL]] -> 0
A37: 2020 | B37: FEBRER | C37: 43884 | D37: DIUMENGE | E37: NO | F37: NO | G37: 0.85416667 | H37: 0.10416667 | I37: NIT | J37: 1 | P37: 195 | Q37: 0 | R37: 0 | S37: =Tabla1[[#This Row],[TARIFA]]+Tabla1[[#This Row],[IMPORTE EXTRAS]] -> 195 | T37: SI | U37: 100 | V37: 95 | W37: 0 | X37: 0 | Z37: =SUM(Tabla1[[#This Row],[RES-A]:[EXTR-B]]) -> 195 | AA37: =Tabla1[[#This Row],[Columna1]]-Tabla1[[#This Row],[IMPORTE TOTAL]] -> 0
A38: 2020 | B38: FEBRER | C38: 43885 | D38: DILLUNS | E38: NO | F38: NO | G38: 0.64583333 | H38: 0.85416667 | I38: TARDA | J38: 1 | P38: 95 | Q38: 0 | R38: 0 | S38: =Tabla1[[#This Row],[TARIFA]]+Tabla1[[#This Row],[IMPORTE EXTRAS]] -> 95 | T38: SI | U38: 50 | V38: 45 | W38: 0 | X38: 0 | Z38: =SUM(Tabla1[[#This Row],[RES-A]:[EXTR-B]]) -> 95 | AA38: =Tabla1[[#This Row],[Columna1]]-Tabla1[[#This Row],[IMPORTE TOTAL]] -> 0
A39: 2020 | B39: FEBRER | C39: 43890 | D39: DISSABTE | E39: NO | F39: NO | G39: 0.39583333 | H39: 0.60416667 | I39: MATI | J39: 1 | P39: 145 | Q39: 0 | R39: 0 | S39: =Tabla1[[#This Row],[TARIFA]]+Tabla1[[#This Row],[IMPORTE EXTRAS]] -> 145 | T39: SI | U39: 50 | V39: 95 | W39: 0 | X39: 0 | Z39: =SUM(Tabla1[[#This Row],[RES-A]:[EXTR-B]]) -> 145 | AA39: =Tabla1[[#This Row],[Columna1]]-Tabla1[[#This Row],[IMPORTE TOTAL]] -> 0
A40: 2020 | B40: FEBRER | C40: 43890 | D40: DISSABTE | E40: NO | F40: NO | G40: 0.64583333 | H40: 0.85416667 | I40: TARDA | J40: 1 | P40: 145 | Q40: 0 | R40: 0 | S40: =Tabla1[[#This Row],[TARIFA]]+Tabla1[[#This Row],[IMPORTE EXTRAS]] -> 145 | T40: SI | U40: 50 | V40: 95 | W40: 0 | X40: 0 | Z40: =SUM(Tabla1[[#This Row],[RES-A]:[EXTR-B]]) -> 145 | AA40: =Tabla1[[#This Row],[Columna1]]-Tabla1[[#This Row],[IMPORTE TOTAL]] -> 0
A41: 2020 | B41: FEBRER | C41: 43890 | D41: DISSABTE | E41: NO | F41: NO | G41: 0.89583333 | H41: 0.10416667 | I41: NIT | J41: 1 | P41: 195 | Q41: 0 | R41: 0 | S41: =Tabla1[[#This Row],[TARIFA]]+Tabla1[[#This Row],[IMPORTE EXTRAS]] -> 195 | T41: SI | U41: 195 | V41: 0 | W41: 0 | X41: 0 | Z41: =SUM(Tabla1[[#This Row],[RES-A]:[EXTR-B]]) -> 195 | AA41: =Tabla1[[#This Row],[Columna1]]-Tabla1[[#This Row],[IMPORTE TOTAL]] -> 0
A42: 2020 | B42: MARÇ | C42: 43896 | D42: DIVENDRES | E42: NO | F42: NO | G42: 0.89583333 | H42: 0.10416667 | I42: NIT | J42: 1 | P42: 195 | Q42: 1 | R42: 50 | S42: =Tabla1[[#This Row],[TARIFA]]+Tabla1[[#This Row],[IMPORTE EXTRAS]] -> 245 | T42: SI | U42: 50 | V42: 145 | W42: 0 | X42: 50 | Z42: =SUM(Tabla1[[#This Row],[RES-A]:[EXTR-B]]) -> 245 | AA42: =Tabla1[[#This Row],[Columna1]]-Tabla1[[#This Row],[IMPORTE TOTAL]] -> 0
A43: 2020 | B43: MARÇ | C43: 43897 | D43: DISSABTE | E43: NO | F43: NO | G43: 0.625 | H43: 0.85416667 | I43: TARDA | J43: 1 | P43: 145 | Q43: 0 | R43: 0 | S43: =Tabla1[[#This Row],[TARIFA]]+Tabla1[[#This Row],[IMPORTE EXTRAS]] -> 145 | T43: SI | U43: 50 | V43: 95 | W43: 0 | X43: 0 | Z43: =SUM(Tabla1[[#This Row],[RES-A]:[EXTR-B]]) -> 145 | AA43: =Tabla1[[#This Row],[Columna1]]-Tabla1[[#This Row],[IMPORTE TOTAL]] -> 0
A44: 2020 | B44: MARÇ | C44: 43898 | D44: DIUMENGE | E44: NO | F44: NO | G44: 0.39583333 | H44: 0.60416667 | I44: MATI | J44: 1 | P44: 145 | Q44: 0 | R44: 0 | S44: =Tabla1[[#This Row],[TARIFA]]+Tabla1[[#This Row],[IMPORTE EXTRAS]] -> 145 | T44: SI | U44: 50 | V44: 95 | W44: 0 | X44: 0 | Z44: =SUM(Tabla1[[#This Row],[RES-A]:[EXTR-B]]) -> 145 | AA44: =Tabla1[[#This Row],[Columna1]]-Tabla1[[#This Row],[IMPORTE TOTAL]] -> 0
A45: 2020 | B45: MARÇ | C45: 43898 | D45: DIUMENGE | E45: NO | F45: NO | G45: 0.625 | H45: 0.85416667 | I45: TARDA | J45: 1 | P45: 145 | Q45: 1 | R45: 20 | S45: =Tabla1[[#This Row],[TARIFA]]+Tabla1[[#This Row],[IMPORTE EXTRAS]] -> 165 | T45: SI | U45: 50 | V45: 95 | W45: 0 | X45: 20 | Z45: =SUM(Tabla1[[#This Row],[RES-A]:[EXTR-B]]) -> 165 | AA45: =Tabla1[[#This Row],[Columna1]]-Tabla1[[#This Row],[IMPORTE TOTAL]] -> 0
A46: 2020 | B46: MARÇ | C46: 43903 | D46: DIVENDRES | E46: NO | F46: NO | G46: 0.625 | H46: 0.85416667 | I46: TARDA | J46: 1 | P46: 135 | Q46: 0 | R46: 0 | S46: =Tabla1[[#This Row],[TARIFA]]+Tabla1[[#This Row],[IMPORTE EXTRAS]] -> 135 | T46: RESERVA | U46: 0 | V46: 0 | W46: 0 | X46: 0 | Y46: ANULAT | Z46: =SUM(Tabla1[[#This Row],[RES-A]:[EXTR-B]]) -> 0 | AA46: =Tabla1[[#This Row],[Columna1]]-Tabla1[[#This Row],[IMPORTE TOTAL]] -> -135
A47: 2020 | B47: MARÇ | C47: 43903 | D47: DIVENDRES | E47: NO | F47: NO | G47: 0.89583333 | H47: 0.10416667 | I47: NIT | J47: 1 | P47: 195 | Q47: 0 | R47: 0 | S47: =Tabla1[[#This Row],[TARIFA]]+Tabla1[[#This Row],[IMPORTE EXTRAS]] -> 195 | T47: RESERVA | U47: 0 | V47: 0 | W47: 0 | X47: 0 | Y47: ANULAT | Z47: =SUM(Tabla1[[#This Row],[RES-A]:[EXTR-B]]) -> 0 | AA47: =Tabla1[[#This Row],[Columna1]]-Tabla1[[#This Row],[IMPORTE TOTAL]] -> -195
A48: 2020 | B48: MARÇ | C48: 43904 | D48: DISSABTE | E48: NO | F48: NO | G48: 0.39583333 | H48: 0.85416667 | I48: DIA SENCER | J48: 2 | P48: 270 | Q48: 0 | R48: 0 | S48: =Tabla1[[#This Row],[TARIFA]]+Tabla1[[#This Row],[IMPORTE EXTRAS]] -> 270 | T48: RESERVA | U48: 0 | V48: 0 | W48: 0 | X48: 0 | Y48: ANULAT | Z48: =SUM(Tabla1[[#This Row],[RES-A]:[EXTR-B]]) -> 0 | AA48: =Tabla1[[#This Row],[Columna1]]-Tabla1[[#This Row],[IMPORTE TOTAL]] -> -270
A49: 2020 | B49: MARÇ | C49: 43904 | D49: DISSABTE | E49: NO | F49: NO | G49: 0.89583333 | H49: 0.10416667 | I49: NIT | J49: 1 | P49: 195 | Q49: 0 | R49: 0 | S49: =Tabla1[[#This Row],[TARIFA]]+Tabla1[[#This Row],[IMPORTE EXTRAS]] -> 195 | T49: RESERVA | U49: 0 | V49: 0 | W49: 0 | X49: 0 | Y49: APLAÇAT | Z49: =SUM(Tabla1[[#This Row],[RES-A]:[EXTR-B]]) -> 0 | AA49: =Tabla1[[#This Row],[Columna1]]-Tabla1[[#This Row],[IMPORTE TOTAL]] -> -195
A50: 2020 | B50: MARÇ | C50: 43905 | D50: DIUMENGE | E50: NO | F50: NO | G50: 0.39583333 | H50: 0.85416667 | I50: DIA SENCER | J50: 2 | P50: 270 | Q50: 0 | R50: 0 | S50: =Tabla1[[#This Row],[TARIFA]]+Tabla1[[#This Row],[IMPORTE EXTRAS]] -> 270 | T50: RESERVA | U50: 0 | V50: 0 | W50: 0 | X50: 0 | Y50: ANULAT | Z50: =SUM(Tabla1[[#This Row],[RES-A]:[EXTR-B]]) -> 0 | AA50: =Tabla1[[#This Row],[Columna1]]-Tabla1[[#This Row],[IMPORTE TOTAL]] -> -270
A51: 2020 | B51: MARÇ | C51: 43910 | D51: DIVENDRES | E51: NO | F51: NO | G51: 0.89583333 | H51: 0.10416667 | I51: NIT | J51: 1 | P51: 195 | Q51: 0 | R51: 0 | S51: =Tabla1[[#This Row],[TARIFA]]+Tabla1[[#This Row],[IMPORTE EXTRAS]] -> 195 | T51: RESERVA | U51: 0 | V51: 0 | W51: 0 | X51: 0 | Y51: APLAÇAT | Z51: =SUM(Tabla1[[#This Row],[RES-A]:[EXTR-B]]) -> 0 | AA51: =Tabla1[[#This Row],[Columna1]]-Tabla1[[#This Row],[IMPORTE TOTAL]] -> -195
A52: 2020 | B52: MARÇ | C52: 43911 | D52: DISSABTE | E52: NO | F52: NO | G52: 0.64583333 | H52: 0.10416667 | I52: SOPAR | J52: 2 | P52: 300 | Q52: 0 | R52: 0 | S52: =Tabla1[[#This Row],[TARIFA]]+Tabla1[[#This Row],[IMPORTE EXTRAS]] -> 300 | T52: RESERVA | U52: 0 | V52: 0 | W52: 0 | X52: 0 | Y52: ANULAT | Z52: =SUM(Tabla1[[#This Row],[RES-A]:[EXTR-B]]) -> 0 | AA52: =Tabla1[[#This Row],[Columna1]]-Tabla1[[#This Row],[IMPORTE TOTAL]] -> -300
A53: 2020 | B53: MARÇ | C53: 43912 | D53: DIUMENGE | E53: NO | F53: NO | G53: 0.39583333 | H53: 0.60416667 | I53: MATI | J53: 1 | P53: 145 | Q53: 0 | R53: 0 | S53: =Tabla1[[#This Row],[TARIFA]]+Tabla1[[#This Row],[IMPORTE EXTRAS]] -> 145 | T53: RESERVA | U53: 0 | V53: 0 | W53: 0 | X53: 0 | Y53: ANULAT | Z53: =SUM(Tabla1[[#This Row],[RES-A]:[EXTR-B]]) -> 0 | AA53: =Tabla1[[#This Row],[Columna1]]-Tabla1[[#This Row],[IMPORTE TOTAL]] -> -145
A54: 2020 | B54: MARÇ | C54: 43912 | D54: DIUMENGE | E54: NO | F54: NO | G54: 0.64583333 | H54: 0.85416667 | I54: TARDA | J54: 1 | P54: 145 | Q54: 0 | R54: 0 | S54: =Tabla1[[#This Row],[TARIFA]]+Tabla1[[#This Row],[IMPORTE EXTRAS]] -> 145 | T54: RESERVA | U54: 0 | V54: 0 | W54: 0 | X54: 0 | Y54: APLAÇAT | Z54: =SUM(Tabla1[[#This Row],[RES-A]:[EXTR-B]]) -> 0 | AA54: =Tabla1[[#This Row],[Columna1]]-Tabla1[[#This Row],[IMPORTE TOTAL]] -> -145
A55: 2020 | B55: MARÇ | C55: 43917 | D55: DIVENDRES | E55: NO | F55: NO | G55: 0.89583333 | H55: 0.10416667 | I55: NIT | J55: 1 | P55: 195 | Q55: 0 | R55: 0 | S55: =Tabla1[[#This Row],[TARIFA]]+Tabla1[[#This Row],[IMPORTE EXTRAS]] -> 195 | T55: RESERVA | U55: 0 | V55: 0 | W55: 0 | X55: 0 | Y55: ANULAT | Z55: =SUM(Tabla1[[#This Row],[RES-A]:[EXTR-B]]) -> 0 | AA55: =Tabla1[[#This Row],[Columna1]]-Tabla1[[#This Row],[IMPORTE TOTAL]] -> -195
A56: 2020 | B56: MARÇ | C56: 43918 | D56: DISSABTE | E56: NO | F56: NO | G56: 0.64583333 | H56: 0.85416667 | I56: TARDA | J56: 1 | P56: 145 | Q56: 0 | R56: 0 | S56: =Tabla1[[#This Row],[TARIFA]]+Tabla1[[#This Row],[IMPORTE EXTRAS]] -> 145 | T56: RESERVA | U56: 0 | V56: 0 | W56: 0 | X56: 0 | Y56: ANULAT | Z56: =SUM(Tabla1[[#This Row],[RES-A]:[EXTR-B]]) -> 0 | AA56: =Tabla1[[#This Row],[Columna1]]-Tabla1[[#This Row],[IMPORTE TOTAL]] -> -145
A57: 2020 | B57: MARÇ | C57: 43918 | D57: DISSABTE | E57: NO | F57: NO | G57: 0.89583333 | H57: 0.10416667 | I57: NIT | J57: 1 | P57: 195 | Q57: 1 | R57: 50 | S57: =Tabla1[[#This Row],[TARIFA]]+Tabla1[[#This Row],[IMPORTE EXTRAS]] -> 245 | T57: RESERVA | U57: 0 | V57: 0 | W57: 0 | X57: 0 | Y57: ANULAT | Z57: =SUM(Tabla1[[#This Row],[RES-A]:[EXTR-B]]) -> 0 | AA57: =Tabla1[[#This Row],[Columna1]]-Tabla1[[#This Row],[IMPORTE TOTAL]] -> -245
... A64: 2020 | B64: ABRIL | C64: 43931 | D64: DIVENDRES | E64: SI | F64: NO | G64: 0.89583333 | H64: 0.10416667 | I64: NIT | J64: 1 | P64: 195 | Q64: 0 | R64: 0 | S64: =Tabla1[[#This Row],[TARIFA]]+Tabla1[[#This Row],[IMPORTE EXTRAS]] -> 195 | T64: RESERVA | U64: 0 | V64: 0 | W64: 0 | X64: 0 | Y64: ANULAT | Z64: =SUM(Tabla1[[#This Row],[RES-A]:[EXTR-B]]) -> 0 | AA64: =Tabla1[[#This Row],[Columna1]]-Tabla1[[#This Row],[IMPORTE TOTAL]] -> -195
A65: 2020 | B65: ABRIL | C65: 43938 | D65: DIVENDRES | E65: NO | F65: NO | I65: ESPECIAL | P65: 661.2 | Q65: 0 | R65: 0 | S65: =Tabla1[[#This Row],[TARIFA]]+Tabla1[[#This Row],[IMPORTE EXTRAS]] -> 661.2 | T65: SI | U65: 661.2 | V65: 0 | W65: 0 | X65: 0 | Z65: =SUM(Tabla1[[#This Row],[RES-A]:[EXTR-B]]) -> 661.2 | AA65: =Tabla1[[#This Row],[Columna1]]-Tabla1[[#This Row],[IMPORTE TOTAL]] -> 0
A66: 2020 | B66: ABRIL | C66: 43938 | D66: DIVENDRES | E66: NO | F66: NO | G66: 0.89583333 | H66: 0.10416667 | I66: NIT | J66: 1 | P66: 195 | Q66: 0 | R66: 0 | S66: =Tabla1[[#This Row],[TARIFA]]+Tabla1[[#This Row],[IMPORTE EXTRAS]] -> 195 | T66: RESERVA | U66: 0 | V66: 0 | W66: 0 | X66: 0 | Y66: APLAÇAT | Z66: =SUM(Tabla1[[#This Row],[RES-A]:[EXTR-B]]) -> 0 | AA66: =Tabla1[[#This Row],[Columna1]]-Tabla1[[#This Row],[IMPORTE TOTAL]] -> -195
A67: 2020 | B67: ABRIL | C67: 43939 | D67: DISSABTE | E67: NO | F67: NO | G67: 0.39583333 | H67: 0.60416667 | I67: MATI | J67: 1 | P67: 145 | Q67: 0 | R67: 0 | S67: =Tabla1[[#This Row],[TARIFA]]+Tabla1[[#This Row],[IMPORTE EXTRAS]] -> 145 | T67: RESERVA | U67: 0 | V67: 0 | W67: 0 | X67: 0 | Y67: ANULAT | Z67: =SUM(Tabla1[[#This Row],[RES-A]:[EXTR-B]]) -> 0 | AA67: =Tabla1[[#This Row],[Columna1]]-Tabla1[[#This Row],[IMPORTE TOTAL]] -> -145
A68: 2020 | B68: ABRIL | C68: 43939 | D68: DISSABTE | E68: NO | F68: NO | G68: 0.64583333 | H68: 0.85416667 | I68: TARDA | J68: 1 | P68: 145 | Q68: 0 | R68: 0 | S68: =Tabla1[[#This Row],[TARIFA]]+Tabla1[[#This Row],[IMPORTE EXTRAS]] -> 145 | T68: RESERVA | U68: 0 | V68: 0 | W68: 0 | X68: 0 | Y68: ANULAT | Z68: =SUM(Tabla1[[#This Row],[RES-A]:[EXTR-B]]) -> 0 | AA68: =Tabla1[[#This Row],[Columna1]]-Tabla1[[#This Row],[IMPORTE TOTAL]] -> -145
A69: 2020 | B69: ABRIL | C69: 43940 | D69: DISSABTE | E69: NO | F69: NO | G69: 0.39583333 | H69: 0.85416667 | I69: DIA SENCER | J69: 2 | P69: 270 | Q69: 0 | R69: 0 | S69: =Tabla1[[#This Row],[TARIFA]]+Tabla1[[#This Row],[IMPORTE EXTRAS]] -> 270 | T69: RESERVA | U69: 0 | V69: 0 | W69: 0 | X69: 0 | Y69: ANULAT | Z69: =SUM(Tabla1[[#This Row],[RES-A]:[EXTR-B]]) -> 0 | AA69: =Tabla1[[#This Row],[Columna1]]-Tabla1[[#This Row],[IMPORTE TOTAL]] -> -270
A70: 2020 | B70: ABRIL | C70: 43946 | D70: DISSABTE | E70: NO | F70: NO | G70: 0.39583333 | H70: 0.60416667 | I70: MATI | J70: 1 | P70: 145 | Q70: 0 | R70: 0 | S70: =Tabla1[[#This Row],[TARIFA]]+Tabla1[[#This Row],[IMPORTE EXTRAS]] -> 145 | T70: NO | U70: 0 | V70: 0 | W70: 0 | X70: 0 | Y70: ANULAT | Z70: =SUM(Tabla1[[#This Row],[RES-A]:[EXTR-B]]) -> 0 | AA70: =Tabla1[[#This Row],[Columna1]]-Tabla1[[#This Row],[IMPORTE TOTAL]] -> -145
A71: 2020 | B71: ABRIL | C71: 43946 | D71: DISSABTE | E71: NO | F71: NO | G71: 0.64583333 | H71: 0.85416667 | I71: TARDA | J71: 1 | P71: 145 | Q71: 0 | R71: 0 | S71: =Tabla1[[#This Row],[TARIFA]]+Tabla1[[#This Row],[IMPORTE EXTRAS]] -> 145 | T71: NO | U71: 0 | V71: 0 | W71: 0 | X71: 0 | Y71: ANULAT | Z71: =SUM(Tabla1[[#This Row],[RES-A]:[EXTR-B]]) -> 0 | AA71: =Tabla1[[#This Row],[Columna1]]-Tabla1[[#This Row],[IMPORTE TOTAL]] -> -145
A72: 2020 | B72: ABRIL | C72: 43947 | D72: DIUMENGE | E72: NO | F72: NO | G72: 0.39583333 | H72: 0.60416667 | I72: MATI | J72: 1 | P72: 145 | Q72: 0 | R72: 0 | S72: =Tabla1[[#This Row],[TARIFA]]+Tabla1[[#This Row],[IMPORTE EXTRAS]] -> 145 | T72: RESERVA | U72: 0 | V72: 0 | W72: 0 | X72: 0 | Y72: ANULAT | Z72: =SUM(Tabla1[[#This Row],[RES-A]:[EXTR-B]]) -> 0 | AA72: =Tabla1[[#This Row],[Columna1]]-Tabla1[[#This Row],[IMPORTE TOTAL]] -> -145
A73: 2020 | B73: MAIG | C73: 43952 | D73: DIVENDRES | E73: NO | F73: NO | I73: ESPECIAL | P73: 374.68 | Q73: 0 | R73: 0 | S73: =Tabla1[[#This Row],[TARIFA]]+Tabla1[[#This Row],[IMPORTE EXTRAS]] -> 374.68 | T73: SI | U73: 374.68 | V73: 0 | W73: 0 | X73: 0 | Z73: =SUM(Tabla1[[#This Row],[RES-A]:[EXTR-B]]) -> 374.68 | AA73: =Tabla1[[#This Row],[Columna1]]-Tabla1[[#This Row],[IMPORTE TOTAL]] -> 0
A74: 2020 | B74: MAIG | C74: 43954 | D74: DIUMENGE | E74: NO | F74: NO | G74: 0.64583333 | H74: 0.85416667 | I74: TARDA | J74: 1 | P74: 145 | Q74: 0 | R74: 0 | S74: =Tabla1[[#This Row],[TARIFA]]+Tabla1[[#This Row],[IMPORTE EXTRAS]] -> 145 | T74: RESERVA | U74: 0 | V74: 0 | W74: 0 | X74: 0 | Y74: ANULAT | Z74: =SUM(Tabla1[[#This Row],[RES-A]:[EXTR-B]]) -> 0 | AA74: =Tabla1[[#This Row],[Columna1]]-Tabla1[[#This Row],[IMPORTE TOTAL]] -> -145
A75: 2020 | B75: MAIG | C75: 43959 | D75: DIVENDRES | E75: NO | F75: NO | G75: 0.89583333 | H75: 0.10416667 | I75: NIT | J75: 1 | P75: 195 | Q75: 0 | R75: 0 | S75: =Tabla1[[#This Row],[TARIFA]]+Tabla1[[#This Row],[IMPORTE EXTRAS]] -> 195 | T75: NO | U75: 0 | V75: 0 | W75: 0 | X75: 0 | Y75: ANULAT | Z75: =SUM(Tabla1[[#This Row],[RES-A]:[EXTR-B]]) -> 0 | AA75: =Tabla1[[#This Row],[Columna1]]-Tabla1[[#This Row],[IMPORTE TOTAL]] -> -195
A76: 2020 | B76: MAIG | C76: 43966 | D76: DIVENDRES | E76: NO | F76: NO | G76: 0.64583333 | H76: 0.85416667 | I76: TARDA | J76: 1 | P76: 135 | Q76: 0 | R76: 0 | S76: =Tabla1[[#This Row],[TARIFA]]+Tabla1[[#This Row],[IMPORTE EXTRAS]] -> 135 | T76: RESERVA | U76: 0 | V76: 0 | W76: 0 | X76: 0 | Y76: ANULAT | Z76: =SUM(Tabla1[[#This Row],[RES-A]:[EXTR-B]]) -> 0 | AA76: =Tabla1[[#This Row],[Columna1]]-Tabla1[[#This Row],[IMPORTE TOTAL]] -> -135
A77: 2020 | B77: MAIG | C77: 43974 | D77: DISSABTE | E77: NO | F77: NO | G77: 0.89583333 | H77: 0.10416667 | I77: NIT | J77: 1 | P77: 195 | Q77: 0 | R77: 0 | S77: =Tabla1[[#This Row],[TARIFA]]+Tabla1[[#This Row],[IMPORTE EXTRAS]] -> 195 | T77: RESERVA | U77: 0 | V77: 0 | W77: 0 | X77: 0 | Y77: ANULAT | Z77: =SUM(Tabla1[[#This Row],[RES-A]:[EXTR-B]]) -> 0 | AA77: =Tabla1[[#This Row],[Columna1]]-Tabla1[[#This Row],[IMPORTE TOTAL]] -> -195
A78: 2020 | B78: MAIG | C78: 43981 | D78: DISSABTE | E78: NO | F78: NO | G78: 0.39583333 | H78: 0.85416667 | I78: DIA SENCER | J78: 2 | P78: 270 | Q78: 0 | R78: 0 | S78: =Tabla1[[#This Row],[TARIFA]]+Tabla1[[#This Row],[IMPORTE EXTRAS]] -> 270 | T78: RESERVA | U78: 0 | V78: 0 | W78: 0 | X78: 0 | Y78: ANULAT | Z78: =SUM(Tabla1[[#This Row],[RES-A]:[EXTR-B]]) -> 0 | AA78: =Tabla1[[#This Row],[Columna1]]-Tabla1[[#This Row],[IMPORTE TOTAL]] -> -270
A79: 2020 | B79: MAIG | C79: 43982 | D79: DIUMENGE | E79: NO | F79: NO | I79: ESPECIAL | P79: 661.2 | S79: =Tabla1[[#This Row],[TARIFA]]+Tabla1[[#This Row],[IMPORTE EXTRAS]] -> 661.2 | T79: SI | U79: 661.2 | V79: 0 | W79: 0 | X79: 0 | Z79: =SUM(Tabla1[[#This Row],[RES-A]:[EXTR-B]]) -> 661.2 | AA79: =Tabla1[[#This Row],[Columna1]]-Tabla1[[#This Row],[IMPORTE TOTAL]] -> 0
A80: 2020 | B80: JUNY | C80: 43988 | D80: DISSABTE | E80: NO | F80: NO | G80: 0.64583333 | H80: 0.85416667 | I80: TARDA | J80: 1 | P80: 145 | Q80: 0 | R80: 0 | S80: =Tabla1[[#This Row],[TARIFA]]+Tabla1[[#This Row],[IMPORTE EXTRAS]] -> 145 | T80: RESERVA | U80: 0 | V80: 0 | W80: 0 | X80: 0 | Y80: ANULAT | Z80: =SUM(Tabla1[[#This Row],[RES-A]:[EXTR-B]]) -> 0 | AA80: =Tabla1[[#This Row],[Columna1]]-Tabla1[[#This Row],[IMPORTE TOTAL]] -> -145
A81: 2020 | B81: JUNY | C81: 43998 | D81: DIMARTS | E81: NO | F81: NO | G81: 0.64583333 | H81: 0.85416667 | I81: TARDA | J81: 1 | P81: 50 | Q81: 0 | R81: 0 | S81: =Tabla1[[#This Row],[TARIFA]]+Tabla1[[#This Row],[IMPORTE EXTRAS]] -> 50 | T81: SI | U81: 0 | V81: 50 | W81: 0 | X81: 0 | Z81: =SUM(Tabla1[[#This Row],[RES-A]:[EXTR-B]]) -> 50 | AA81: =Tabla1[[#This Row],[Columna1]]-Tabla1[[#This Row],[IMPORTE TOTAL]] -> 0
A82: 2020 | B82: JUNY | C82: 44000 | D82: DIJOUS | E82: NO | F82: NO | G82: 0.64583333 | H82: 0.85416667 | I82: TARDA | J82: 1 | P82: 50 | Q82: 0 | R82: 0 | S82: =Tabla1[[#This Row],[TARIFA]]+Tabla1[[#This Row],[IMPORTE EXTRAS]] -> 50 | T82: SI | U82: 0 | V82: 50 | W82: 0 | X82: 0 | Z82: =SUM(Tabla1[[#This Row],[RES-A]:[EXTR-B]]) -> 50 | AA82: =Tabla1[[#This Row],[Columna1]]-Tabla1[[#This Row],[IMPORTE TOTAL]] -> 0
A83: 2020 | B83: JUNY | C83: 44001 | D83: DIVENDRES | E83: NO | F83: NO | G83: 0.39583333 | H83: 0.85416667 | I83: DIA SENCER | J83: 2 | P83: 190 | Q83: 0 | R83: 0 | S83: =Tabla1[[#This Row],[TARIFA]]+Tabla1[[#This Row],[IMPORTE EXTRAS]] -> 190 | T83: SI | U83: 0 | V83: 190 | W83: 0 | X83: 0 | Z83: =SUM(Tabla1[[#This Row],[RES-A]:[EXTR-B]]) -> 190 | AA83: =Tabla1[[#This Row],[Columna1]]-Tabla1[[#This Row],[IMPORTE TOTAL]] -> 0
A84: 2020 | B84: JUNY | C84: 44002 | D84: DISSABTE | E84: NO | F84: NO | G84: 0.89583333 | H84: 0.10416667 | I84: NIT | J84: 1 | P84: 195 | Q84: 1 | R84: 55 | S84: =Tabla1[[#This Row],[TARIFA]]+Tabla1[[#This Row],[IMPORTE EXTRAS]] -> 250 | T84: SI | U84: 50 | V84: 145 | W84: 0 | X84: 55 | Z84: =SUM(Tabla1[[#This Row],[RES-A]:[EXTR-B]]) -> 250 | AA84: =Tabla1[[#This Row],[Columna1]]-Tabla1[[#This Row],[IMPORTE TOTAL]] -> 0
A85: 2020 | B85: JUNY | C85: 44003 | D85: DIUMENGE | E85: NO | F85: NO | G85: 0.89583333 | H85: 0.10416667 | I85: NIT | J85: 1 | P85: 195 | Q85: 1 | R85: 50 | S85: =Tabla1[[#This Row],[TARIFA]]+Tabla1[[#This Row],[IMPORTE EXTRAS]] -> 245 | T85: SI | U85: 50 | V85: 145 | W85: 0 | X85: 50 | Z85: =SUM(Tabla1[[#This Row],[RES-A]:[EXTR-B]]) -> 245 | AA85: =Tabla1[[#This Row],[Columna1]]-Tabla1[[#This Row],[IMPORTE TOTAL]] -> 0
A86: 2020 | B86: JUNY | C86: 44005 | D86: DIMARTS | E86: NO | F86: SI | G86: 0.89583333 | H86: 0.10416667 | I86: ESPECIAL | J86: 1 | P86: 300 | Q86: 0 | R86: 0 | S86: =Tabla1[[#This Row],[TARIFA]]+Tabla1[[#This Row],[IMPORTE EXTRAS]] -> 300 | T86: SI | U86: 0 | V86: 300 | W86: 0 | X86: 0 | Z86: =SUM(Tabla1[[#This Row],[RES-A]:[EXTR-B]]) -> 300 | AA86: =Tabla1[[#This Row],[Columna1]]-Tabla1[[#This Row],[IMPORTE TOTAL]] -> 0
A87: 2020 | B87: JUNY | C87: 44007 | D87: DIMARTS | E87: NO | F87: NO | G87: 0.64583333 | H87: 0.85416667 | I87: TARDA | J87: 1 | P87: 50 | Q87: 0 | R87: 0 | S87: =Tabla1[[#This Row],[TARIFA]]+Tabla1[[#This Row],[IMPORTE EXTRAS]] -> 50 | T87: SI | U87: 0 | V87: 50 | W87: 0 | X87: 0 | Z87: =SUM(Tabla1[[#This Row],[RES-A]:[EXTR-B]]) -> 50 | AA87: =Tabla1[[#This Row],[Columna1]]-Tabla1[[#This Row],[IMPORTE TOTAL]] -> 0
A88: 2020 | B88: JUNY | C88: 44012 | D88: DIMARTS | E88: NO | F88: NO | G88: 0.64583333 | H88: 0.85416667 | I88: TARDA | J88: 1 | P88: 50 | Q88: 0 | R88: 0 | S88: =Tabla1[[#This Row],[TARIFA]]+Tabla1[[#This Row],[IMPORTE EXTRAS]] -> 50 | T88: SI | U88: 0 | V88: 50 | W88: 0 | X88: 0 | Z88: =SUM(Tabla1[[#This Row],[RES-A]:[EXTR-B]]) -> 50 | AA88: =Tabla1[[#This Row],[Columna1]]-Tabla1[[#This Row],[IMPORTE TOTAL]] -> 0
A89: 2020 | B89: JUNY | C89: 44012 | D89: DIMARTS | E89: NO | F89: NO | I89: ESPECIAL | P89: 661.2 | S89: =Tabla1[[#This Row],[TARIFA]]+Tabla1[[#This Row],[IMPORTE EXTRAS]] -> 661.2 | T89: SI | U89: 661.2 | V89: 0 | W89: 0 | X89: 0 | Z89: =SUM(Tabla1[[#This Row],[RES-A]:[EXTR-B]]) -> 661.2 | AA89: =Tabla1[[#This Row],[Columna1]]-Tabla1[[#This Row],[IMPORTE TOTAL]] -> 0
A90: 2020 | B90: JULIOL | C90: 44013 | D90: DIMECRES | E90: NO | F90: NO | I90: ESPECIAL | P90: 1400 | S90: =Tabla1[[#This Row],[TARIFA]]+Tabla1[[#This Row],[IMPORTE EXTRAS]] -> 1400 | T90: SI | U90: 1400 | V90: 0 | W90: 0 | X90: 0 | Z90: =SUM(Tabla1[[#This Row],[RES-A]:[EXTR-B]]) -> 1400 | AA90: =Tabla1[[#This Row],[Columna1]]-Tabla1[[#This Row],[IMPORTE TOTAL]] -> 0
A91: 2020 | B91: JULIOL | C91: 44014 | D91: DIJOUS | E91: NO | F91: NO | G91: 0.64583333 | H91: 0.85416667 | I91: TARDA | J91: 1 | P91: 50 | Q91: 0 | R91: 0 | S91: =Tabla1[[#This Row],[TARIFA]]+Tabla1[[#This Row],[IMPORTE EXTRAS]] -> 50 | T91: SI | U91: 0 | V91: 50 | W91: 0 | X91: 0 | Z91: =SUM(Tabla1[[#This Row],[RES-A]:[EXTR-B]]) -> 50 | AA91: =Tabla1[[#This Row],[Columna1]]-Tabla1[[#This Row],[IMPORTE TOTAL]] -> 0
A92: 2020 | B92: JULIOL | C92: 44015 | D92: DIVENDRES | E92: NO | F92: NO | G92: 0.89583333 | H92: 0.10416667 | I92: NIT | J92: 1 | P92: 195 | Q92: 0 | R92: 0 | S92: =Tabla1[[#This Row],[TARIFA]]+Tabla1[[#This Row],[IMPORTE EXTRAS]] -> 195 | T92: SI | U92: 0 | V92: 195 | W92: 0 | X92: 0 | Z92: =SUM(Tabla1[[#This Row],[RES-A]:[EXTR-B]]) -> 195 | AA92: =Tabla1[[#This Row],[Columna1]]-Tabla1[[#This Row],[IMPORTE TOTAL]] -> 0
A93: 2020 | B93: JULIOL | C93: 44016 | D93: DISSABTE | E93: NO | F93: NO | G93: 0.89583333 | H93: 0.10416667 | I93: NIT | J93: 1 | P93: 195 | Q93: 0 | R93: 0 | S93: =Tabla1[[#This Row],[TARIFA]]+Tabla1[[#This Row],[IMPORTE EXTRAS]] -> 195 | T93: SI | U93: 195 | V93: 0 | W93: 0 | X93: 0 | Y93: Venen sempre per Carnaval | Z93: =SUM(Tabla1[[#This Row],[RES-A]:[EXTR-B]]) -> 195 | AA93: =Tabla1[[#This Row],[Columna1]]-Tabla1[[#This Row],[IMPORTE TOTAL]] -> 0
A94: 2020 | B94: JULIOL | C94: 44017 | D94: DIUMENGE | E94: NO | F94: NO | G94: 0.64583333 | H94: 0.85416667 | I94: TARDA | J94: 1 | P94: 145 | Q94: 0 | R94: 5 | S94: =Tabla1[[#This Row],[TARIFA]]+Tabla1[[#This Row],[IMPORTE EXTRAS]] -> 150 | T94: SI | U94: 50 | V94: 95 | W94: 0 | X94: 5 | Z94: =SUM(Tabla1[[#This Row],[RES-A]:[EXTR-B]]) -> 150 | AA94: =Tabla1[[#This Row],[Columna1]]-Tabla1[[#This Row],[IMPORTE TOTAL]] -> 0
A95: 2020 | B95: JULIOL | C95: 44019 | D95: DIMARTS | E95: NO | F95: NO | G95: 0.64583333 | H95: 0.85416667 | I95: TARDA | J95: 1 | P95: 50 | Q95: 0 | R95: 0 | S95: =Tabla1[[#This Row],[TARIFA]]+Tabla1[[#This Row],[IMPORTE EXTRAS]] -> 50 | T95: SI | U95: 0 | V95: 50 | W95: 0 | X95: 0 | Z95: =SUM(Tabla1[[#This Row],[RES-A]:[EXTR-B]]) -> 50 | AA95: =Tabla1[[#This Row],[Columna1]]-Tabla1[[#This Row],[IMPORTE TOTAL]] -> 0
A96: 2020 | B96: JULIOL | C96: 44021 | D96: DIJOUS | E96: NO | F96: NO | G96: 0.64583333 | H96: 0.85416667 | I96: TARDA | J96: 1 | P96: 50 | Q96: 0 | R96: 0 | S96: =Tabla1[[#This Row],[TARIFA]]+Tabla1[[#This Row],[IMPORTE EXTRAS]] -> 50 | T96: SI | U96: 0 | V96: 50 | W96: 0 | X96: 0 | Z96: =SUM(Tabla1[[#This Row],[RES-A]:[EXTR-B]]) -> 50 | AA96: =Tabla1[[#This Row],[Columna1]]-Tabla1[[#This Row],[IMPORTE TOTAL]] -> 0
A97: 2020 | B97: JULIOL | C97: 44022 | D97: DIVENDRES | E97: NO | F97: NO | G97: 0.89583333 | H97: 0.10416667 | I97: NIT | J97: 1 | P97: 0 | Q97: 0 | R97: 0 | S97: =Tabla1[[#This Row],[TARIFA]]+Tabla1[[#This Row],[IMPORTE EXTRAS]] -> 0 | T97: NO | U97: 0 | V97: 0 | W97: 0 | X97: 0 | Y97: Sorteig | Z97: =SUM(Tabla1[[#This Row],[RES-A]:[EXTR-B]]) -> 0 | AA97: =Tabla1[[#This Row],[Columna1]]-Tabla1[[#This Row],[IMPORTE TOTAL]] -> 0
A98: 2020 | B98: JULIOL | C98: 44023 | D98: DISSABTE | E98: NO | F98: NO | G98: 0.89583333 | H98: 0.10416667 | I98: NIT | J98: 1 | P98: 195 | Q98: 1 | R98: 55 | S98: =Tabla1[[#This Row],[TARIFA]]+Tabla1[[#This Row],[IMPORTE EXTRAS]] -> 250 | T98: SI | U98: 50 | V98: 145 | W98: 0 | X98: 55 | Z98: =SUM(Tabla1[[#This Row],[RES-A]:[EXTR-B]]) -> 250 | AA98: =Tabla1[[#This Row],[Columna1]]-Tabla1[[#This Row],[IMPORTE TOTAL]] -> 0
A99: 2020 | B99: JULIOL | C99: 44025 | D99: DILLUNS | E99: NO | F99: NO | G99: 0.64583333 | H99: 0.85416667 | I99: TARDA | J99: 1 | P99: 50 | Q99: 0 | R99: 0 | S99: =Tabla1[[#This Row],[TARIFA]]+Tabla1[[#This Row],[IMPORTE EXTRAS]] -> 50 | T99: SI | U99: 0 | V99: 50 | W99: 0 | X99: 0 | Z99: =SUM(Tabla1[[#This Row],[RES-A]:[EXTR-B]]) -> 50 | AA99: =Tabla1[[#This Row],[Columna1]]-Tabla1[[#This Row],[IMPORTE TOTAL]] -> 0
A100: 2020 | B100: JULIOL | C100: 44027 | D100: DIMECRES | E100: NO | F100: NO | G100: 0.64583333 | H100: 0.85416667 | I100: TARDA | J100: 1 | P100: 50 | Q100: 0 | R100: 0 | S100: =Tabla1[[#This Row],[TARIFA]]+Tabla1[[#This Row],[IMPORTE EXTRAS]] -> 50 | T100: SI | U100: 0 | V100: 50 | W100: 0 | X100: 0 | Z100: =SUM(Tabla1[[#This Row],[RES-A]:[EXTR-B]]) -> 50 | AA100: =Tabla1[[#This Row],[Columna1]]-Tabla1[[#This Row],[IMPORTE TOTAL]] -> 0
A101: 2020 | B101: JULIOL | C101: 44028 | D101: DIJOUS | E101: NO | F101: NO | G101: 0.64583333 | H101: 0.85416667 | I101: TARDA | J101: 1 | P101: 50 | Q101: 0 | R101: 0 | S101: =Tabla1[[#This Row],[TARIFA]]+Tabla1[[#This Row],[IMPORTE EXTRAS]] -> 50 | T101: SI | U101: 50 | V101: 0 | W101: 0 | X101: 0 | Z101: =SUM(Tabla1[[#This Row],[RES-A]:[EXTR-B]]) -> 50 | AA101: =Tabla1[[#This Row],[Columna1]]-Tabla1[[#This Row],[IMPORTE TOTAL]] -> 0
A102: 2020 | B102: JULIOL | C102: 44029 | D102: DIVENDRES | E102: NO | F102: NO | G102: 0.89583333 | H102: 0.10416667 | I102: NIT | J102: 1 | P102: 195 | Q102: 0 | R102: 0 | S102: =Tabla1[[#This Row],[TARIFA]]+Tabla1[[#This Row],[IMPORTE EXTRAS]] -> 195 | T102: SI | U102: 50 | V102: 145 | W102: 0 | X102: 0 | Z102: =SUM(Tabla1[[#This Row],[RES-A]:[EXTR-B]]) -> 195 | AA102: =Tabla1[[#This Row],[Columna1]]-Tabla1[[#This Row],[IMPORTE TOTAL]] -> 0
A103: 2020 | B103: JULIOL | C103: 44030 | D103: DISSABTE | E103: NO | F103: NO | G103: 0.89583333 | H103: 0.10416667 | I103: NIT | J103: 1 | P103: 195 | Q103: 0 | R103: 0 | S103: =Tabla1[[#This Row],[TARIFA]]+Tabla1[[#This Row],[IMPORTE EXTRAS]] -> 195 | T103: RESERVA | U103: 100 | V103: 0 | W103: 0 | X103: 0 | Y103: APLAÇAT | Z103: =SUM(Tabla1[[#This Row],[RES-A]:[EXTR-B]]) -> 100 | AA103: =Tabla1[[#This Row],[Columna1]]-Tabla1[[#This Row],[IMPORTE TOTAL]] -> -95
A104: 2020 | B104: JULIOL | C104: 44031 | D104: DIUMENGE | E104: NO | F104: NO | G104: 0.39583333 | H104: 0.60416667 | I104: MATI | J104: 1 | P104: 145 | Q104: 1 | R104: 5 | S104: =Tabla1[[#This Row],[TARIFA]]+Tabla1[[#This Row],[IMPORTE EXTRAS]] -> 150 | T104: SI | U104: 50 | V104: 95 | W104: 0 | X104: 5 | Z104: =SUM(Tabla1[[#This Row],[RES-A]:[EXTR-B]]) -> 150 | AA104: =Tabla1[[#This Row],[Columna1]]-Tabla1[[#This Row],[IMPORTE TOTAL]] -> 0
A105: 2020 | B105: JULIOL | C105: 44033 | D105: DIMARTS | E105: NO | F105: NO | G105: 0.64583333 | H105: 0.85416667 | I105: TARDA | J105: 1 | P105: 50 | Q105: 0 | R105: 0 | S105: =Tabla1[[#This Row],[TARIFA]]+Tabla1[[#This Row],[IMPORTE EXTRAS]] -> 50 | T105: SI | U105: 50 | V105: 0 | W105: 0 | X105: 0 | Z105: =SUM(Tabla1[[#This Row],[RES-A]:[EXTR-B]]) -> 50 | AA105: =Tabla1[[#This Row],[Columna1]]-Tabla1[[#This Row],[IMPORTE TOTAL]] -> 0
A106: 2020 | B106: JULIOL | C106: 44033 | D106: DIMARTS | E106: NO | F106: NO | G106: 0.89583333 | H106: 0.10416667 | I106: NIT | J106: 1 | P106: 195 | Q106: 0 | R106: 0 | S106: =Tabla1[[#This Row],[TARIFA]]+Tabla1[[#This Row],[IMPORTE EXTRAS]] -> 195 | T106: SI | U106: 195 | V106: 0 | W106: 0 | X106: 0 | Z106: =SUM(Tabla1[[#This Row],[RES-A]:[EXTR-B]]) -> 195 | AA106: =Tabla1[[#This Row],[Columna1]]-Tabla1[[#This Row],[IMPORTE TOTAL]] -> 0
A107: 2020 | B107: JULIOL | C107: 44036 | D107: DIVENDRES | E107: NO | F107: NO | G107: 0.89583333 | H107: 0.10416667 | I107: NIT | J107: 1 | P107: 195 | Q107: 1 | R107: 5 | S107: =Tabla1[[#This Row],[TARIFA]]+Tabla1[[#This Row],[IMPORTE EXTRAS]] -> 200 | T107: SI | U107: 50 | V107: 145 | W107: 0 | X107: 5 | Z107: =SUM(Tabla1[[#This Row],[RES-A]:[EXTR-B]]) -> 200 | AA107: =Tabla1[[#This Row],[Columna1]]-Tabla1[[#This Row],[IMPORTE TOTAL]] -> 0
A108: 2020 | B108: JULIOL | C108: 44037 | D108: DISSABTE | E108: NO | F108: NO | G108: 0.89583333 | H108: 0.10416667 | I108: NIT | J108: 1 | P108: 195 | Q108: 0 | R108: 0 | S108: =Tabla1[[#This Row],[TARIFA]]+Tabla1[[#This Row],[IMPORTE EXTRAS]] -> 195 | T108: SI | U108: 50 | V108: 145 | W108: 0 | X108: 0 | Z108: =SUM(Tabla1[[#This Row],[RES-A]:[EXTR-B]]) -> 195 | AA108: =Tabla1[[#This Row],[Columna1]]-Tabla1[[#This Row],[IMPORTE TOTAL]] -> 0
A109: 2020 | B109: JULIOL | C109: 44038 | D109: DIUMENGE | E109: NO | F109: NO | G109: 0.39583333 | H109: 0.60416667 | I109: MATI | J109: 1 | P109: 145 | Q109: 0 | R109: 0 | S109: =Tabla1[[#This Row],[TARIFA]]+Tabla1[[#This Row],[IMPORTE EXTRAS]] -> 145 | T109: NO | U109: 0 | V109: 0 | W109: 0 | X109: 0 | Y109: ANULAT | Z109: =SUM(Tabla1[[#This Row],[RES-A]:[EXTR-B]]) -> 0 | AA109: =Tabla1[[#This Row],[Columna1]]-Tabla1[[#This Row],[IMPORTE TOTAL]] -> -145
A110: 2020 | B110: JULIOL | C110: 44042 | D110: DIJOUS | E110: NO | F110: NO | G110: 0.89583333 | H110: 0.10416667 | I110: NIT | J110: 1 | P110: 195 | Q110: 0 | R110: 0 | S110: =Tabla1[[#This Row],[TARIFA]]+Tabla1[[#This Row],[IMPORTE EXTRAS]] -> 195 | T110: SI | U110: 195 | V110: 0 | W110: 0 | X110: 0 | Z110: =SUM(Tabla1[[#This Row],[RES-A]:[EXTR-B]]) -> 195 | AA110: =Tabla1[[#This Row],[Columna1]]-Tabla1[[#This Row],[IMPORTE TOTAL]] -> 0
A111: 2020 | B111: JULIOL | C111: 44043 | D111: DIVENDRES | E111: NO | F111: NO | G111: 0.89583333 | H111: 0.10416667 | I111: NIT | J111: 1 | P111: 195 | Q111: 1 | R111: 50 | S111: =Tabla1[[#This Row],[TARIFA]]+Tabla1[[#This Row],[IMPORTE EXTRAS]] -> 245 | T111: SI | U111: 50 | V111: 145 | W111: 0 | X111: 50 | Z111: =SUM(Tabla1[[#This Row],[RES-A]:[EXTR-B]]) -> 245 | AA111: =Tabla1[[#This Row],[Columna1]]-Tabla1[[#This Row],[IMPORTE TOTAL]] -> 0
A112: 2020 | B112: AGOST | C112: 44044 | D112: DISSABTE | E112: NO | F112: NO | G112: 0.64583333 | H112: 0.85416667 | I112: TARDA | J112: 1 | P112: 145 | Q112: 0 | R112: 0 | S112: =Tabla1[[#This Row],[TARIFA]]+Tabla1[[#This Row],[IMPORTE EXTRAS]] -> 145 | T112: NO | U112: 0 | V112: 0 | W112: 0 | X112: 0 | Y112: ANULAT | Z112: =SUM(Tabla1[[#This Row],[RES-A]:[EXTR-B]]) -> 0 | AA112: =Tabla1[[#This Row],[Columna1]]-Tabla1[[#This Row],[IMPORTE TOTAL]] -> -145
A113: 2020 | B113: AGOST | C113: 44044 | D113: DISSABTE | E113: NO | F113: NO | G113: 0.89583333 | H113: 0.10416667 | I113: NIT | J113: 1 | P113: 195 | Q113: 0 | R113: 0 | S113: =Tabla1[[#This Row],[TARIFA]]+Tabla1[[#This Row],[IMPORTE EXTRAS]] -> 195 | T113: RESERVA | U113: 50 | V113: 0 | W113: 0 | X113: 0 | Y113: APLAÇAT | Z113: =SUM(Tabla1[[#This Row],[RES-A]:[EXTR-B]]) -> 50 | AA113: =Tabla1[[#This Row],[Columna1]]-Tabla1[[#This Row],[IMPORTE TOTAL]] -> -145
A114: 2020 | B114: AGOST | C114: 44044 | D114: DISSABTE | E114: NO | F114: NO | G114: 0.89583333 | H114: 0.10416667 | I114: NIT | J114: 1 | P114: 195 | Q114: 1 | R114: 50 | S114: =Tabla1[[#This Row],[TARIFA]]+Tabla1[[#This Row],[IMPORTE EXTRAS]] -> 245 | T114: SI | U114: 50 | V114: 145 | W114: 0 | X114: 50 | Z114: =SUM(Tabla1[[#This Row],[RES-A]:[EXTR-B]]) -> 245 | AA114: =Tabla1[[#This Row],[Columna1]]-Tabla1[[#This Row],[IMPORTE TOTAL]] -> 0
A115: 2020 | B115: AGOST | C115: 44050 | D115: DIVENDRES | E115: NO | F115: NO | G115: 0.39583333 | H115: 0.10416667 | I115: DIA SENCER | J115: 3 | P115: 300 | Q115: 0 | R115: 0 | S115: =Tabla1[[#This Row],[TARIFA]]+Tabla1[[#This Row],[IMPORTE EXTRAS]] -> 300 | T115: SI | U115: 50 | V115: 250 | W115: 0 | X115: 0 | Z115: =SUM(Tabla1[[#This Row],[RES-A]:[EXTR-B]]) -> 300 | AA115: =Tabla1[[#This Row],[Columna1]]-Tabla1[[#This Row],[IMPORTE TOTAL]] -> 0
A116: 2020 | B116: AGOST | C116: 44051 | D116: DISSABTE | E116: NO | F116: NO | G116: 0.89583333 | H116: 0.10416667 | I116: NIT | J116: 1 | P116: 195 | Q116: 0 | R116: 0 | S116: =Tabla1[[#This Row],[TARIFA]]+Tabla1[[#This Row],[IMPORTE EXTRAS]] -> 195 | T116: NO | U116: 0 | V116: 0 | W116: 0 | X116: 0 | Y116: ANULAT | Z116: =SUM(Tabla1[[#This Row],[RES-A]:[EXTR-B]]) -> 0 | AA116: =Tabla1[[#This Row],[Columna1]]-Tabla1[[#This Row],[IMPORTE TOTAL]] -> -195
A117: 2020 | B117: AGOST | C117: 44055 | D117: DIMECRES | E117: NO | F117: NO | G117: 0.89583333 | H117: 0.10416667 | I117: NIT | J117: 1 | P117: 195 | Q117: 1 | R117: 55 | S117: =Tabla1[[#This Row],[TARIFA]]+Tabla1[[#This Row],[IMPORTE EXTRAS]] -> 250 | T117: SI | U117: 50 | V117: 145 | W117: 0 | X117: 55 | Z117: =SUM(Tabla1[[#This Row],[RES-A]:[EXTR-B]]) -> 250 | AA117: =Tabla1[[#This Row],[Columna1]]-Tabla1[[#This Row],[IMPORTE TOTAL]] -> 0
...

Sheet Registre de despeses
A1: ANY | B1: MES | C1: DATA | D1: TIPUS | E1: TIPO DESPESA | F1: CONCEPTE | G1: IMPORT | H1: A | I1: B | J1: FACTURA TRIMESTRE
A2: 2020 | B2: GENER | C2: 43832 | D2: PÀGINA WEB | E2: =VLOOKUP(Tabla2[[#This Row],[TIPUS]],Tarifas!$H$12:$I$26,2,0) -> FIX | F2: Anualitat Pàgina web - 2 anys | G2: 499 | H2: 499 | I2: 0
A3: 2020 | B3: GENER | C3: 43837 | D3: ASSEGURANÇA | E3: =VLOOKUP(Tabla2[[#This Row],[TIPUS]],Tarifas!$H$12:$I$26,2,0) -> FIX | F3: Rebut anual assegurança | G3: 362.22 | H3: 362.22 | I3: 0
A4: 2020 | B4: GENER | C4: 43840 | D4: CONSUMIBLES | E4: =VLOOKUP(Tabla2[[#This Row],[TIPUS]],Tarifas!$H$12:$I$26,2,0) -> VARIABLE | F4: Productes de neteja | G4: 36.03 | H4: 36.03 | I4: 0
A5: 2020 | B5: GENER | C5: 43842 | D5: PÀGINA WEB | E5: =VLOOKUP(Tabla2[[#This Row],[TIPUS]],Tarifas!$H$12:$I$26,2,0) -> FIX | F5: Logo | G5: 250 | H5: 0 | I5: 250
A6: 2020 | B6: GENER | C6: 43848 | D6: MAQUINARIA | E6: =VLOOKUP(Tabla2[[#This Row],[TIPUS]],Tarifas!$H$12:$I$26,2,0) -> VARIABLE | F6: Arreglo porta lavabo | G6: 35 | H6: 0 | I6: 35
A7: 2020 | B7: GENER | C7: 43849 | D7: LLOGUER | E7: =VLOOKUP(Tabla2[[#This Row],[TIPUS]],Tarifas!$H$12:$I$26,2,0) -> FIX | F7: Lloguer gener 2020 | G7: 506 | H7: 306 | I7: 200
A8: 2020 | B8: GENER | C8: 43857 | D8: MAQUINARIA | E8: =VLOOKUP(Tabla2[[#This Row],[TIPUS]],Tarifas!$H$12:$I$26,2,0) -> VARIABLE | F8: Arreglo porta principal | G8: 45 | H8: 0 | I8: 45
A9: 2020 | B9: GENER | C9: 43858 | D9: LLOGUER | E9: =VLOOKUP(Tabla2[[#This Row],[TIPUS]],Tarifas!$H$12:$I$26,2,0) -> FIX | F9: INCASOL | G9: 600 | H9: 600 | I9: 0
A10: 2020 | B10: GENER | C10: 43859 | D10: INVERSIONS CAPITAL | E10: =VLOOKUP(Tabla2[[#This Row],[TIPUS]],Tarifas!$H$12:$I$26,2,0) -> INVERSIONS | F10: Nevera | G10: 377 | H10: 377 | I10: 0
A11: 2020 | B11: GENER | C11: 43860 | D11: CONSUMIBLES | E11: =VLOOKUP(Tabla2[[#This Row],[TIPUS]],Tarifas!$H$12:$I$26,2,0) -> VARIABLE | F11: Flyers | G11: 64 | H11: 0 | I11: 64
A12: 2020 | B12: GENER | C12: 43861 | D12: AUTÒNOM | E12: =VLOOKUP(Tabla2[[#This Row],[TIPUS]],Tarifas!$H$12:$I$26,2,0) -> FIX | F12: Qutoa Gener 2020 | G12: 67.54 | H12: 67.54 | I12: 0
A13: 2020 | B13: GENER | C13: 43861 | D13: TELÈFON | E13: =VLOOKUP(Tabla2[[#This Row],[TIPUS]],Tarifas!$H$12:$I$26,2,0) -> FIX | F13: Quota Gener 2020 | G13: 25 | H13: 25 | I13: 0
A14: 2020 | B14: GENER | C14: 43861 | D14: EXTERNALITZACIÓ NETEJA | E14: =VLOOKUP(Tabla2[[#This Row],[TIPUS]],Tarifas!$H$12:$I$26,2,0) -> VARIABLE | F14: Netejes Gener 2020 | G14: 150 | H14: 0 | I14: 150
A15: 2020 | B15: GENER | C15: 43861 | D15: LLUM | E15: =VLOOKUP(Tabla2[[#This Row],[TIPUS]],Tarifas!$H$12:$I$26,2,0) -> VARIABLE | F15: Quota Gener 2020 | G15: =54.32/2 -> 27.16 | H15: =54.32/2 -> 27.16 | I15: 0
A16: 2020 | B16: FEBRER | C16: 43878 | D16: LLOGUER | E16: =VLOOKUP(Tabla2[[#This Row],[TIPUS]],Tarifas!$H$12:$I$26,2,0) -> FIX | F16: Lloguer febrer 2020 | G16: 506 | H16: 306 | I16: 200
A17: 2020 | B17: FEBRER | C17: 43879 | D17: CONSUMIBLES | E17: =VLOOKUP(Tabla2[[#This Row],[TIPUS]],Tarifas!$H$12:$I$26,2,0) -> VARIABLE | F17: Lampara projector | G17: 90 | H17: 0 | I17: 90
A18: 2020 | B18: FEBRER | C18: 43880 | D18: EXTERNALITZACIÓ NETEJA | E18: =VLOOKUP(Tabla2[[#This Row],[TIPUS]],Tarifas!$H$12:$I$26,2,0) -> VARIABLE | F18: Ania febrer | G18: 120 | H18: 0 | I18: 120
A19: 2020 | B19: FEBRER | C19: 43883 | D19: EXTERNALITZACIÓ NETEJA | E19: =VLOOKUP(Tabla2[[#This Row],[TIPUS]],Tarifas!$H$12:$I$26,2,0) -> VARIABLE | F19: Netejes Febrer 2020 | G19: 175 | H19: 0 | I19: 175
A20: 2020 | B20: FEBRER | C20: 43883 | D20: INVERSIONS CAPITAL | E20: =VLOOKUP(Tabla2[[#This Row],[TIPUS]],Tarifas!$H$12:$I$26,2,0) -> INVERSIONS | F20: Taules Leroy Merlin | G20: 131.53 | H20: 131.53 | I20: 0
A21: 2020 | B21: FEBRER | C21: 43883 | D21: CONSUMIBLES | E21: =VLOOKUP(Tabla2[[#This Row],[TIPUS]],Tarifas!$H$12:$I$26,2,0) -> VARIABLE | F21: Draps Ikea | G21: 3 | H21: 3 | I21: 0
A22: 2020 | B22: FEBRER | C22: 43883 | D22: INVERSIONS CAPITAL | E22: =VLOOKUP(Tabla2[[#This Row],[TIPUS]],Tarifas!$H$12:$I$26,2,0) -> INVERSIONS | F22: Secamans Amazon | G22: 40.06 | H22: 40.06 | I22: 0
A23: 2020 | B23: FEBRER | C23: 43889 | D23: AUTÒNOM | E23: =VLOOKUP(Tabla2[[#This Row],[TIPUS]],Tarifas!$H$12:$I$26,2,0) -> FIX | F23: Quota Febrer 2020 | G23: 67.54 | H23: 67.54 | I23: 0
A24: 2020 | B24: FEBRER | C24: 43889 | D24: TELÈFON | E24: =VLOOKUP(Tabla2[[#This Row],[TIPUS]],Tarifas!$H$12:$I$26,2,0) -> FIX | F24: Quota Febrer 2020 | G24: 53.8 | H24: 53.8 | I24: 0
A25: 2020 | B25: FEBRER | C25: 43889 | D25: LLUM | E25: =VLOOKUP(Tabla2[[#This Row],[TIPUS]],Tarifas!$H$12:$I$26,2,0) -> VARIABLE | F25: Quota Febrer 2020 | G25: =54.32/2 -> 27.16 | H25: =54.32/2 -> 27.16 | I25: 0
A26: 2020 | B26: MARÇ | C26: 43896 | D26: LLOGUER | E26: =VLOOKUP(Tabla2[[#This Row],[TIPUS]],Tarifas!$H$12:$I$26,2,0) -> FIX | F26: Lloguer març 2020 | G26: 506 | H26: 306 | I26: 200
A27: 2020 | B27: MARÇ | C27: 43899 | D27: CONSUMIBLES | E27: =VLOOKUP(Tabla2[[#This Row],[TIPUS]],Tarifas!$H$12:$I$26,2,0) -> VARIABLE | F27: Pintures pel trono | G27: 18.61 | H27: 18.61 | I27: 0
A28: 2020 | B28: ABRIL | C28: 43931 | D28: TELÈFON | E28: =VLOOKUP(Tabla2[[#This Row],[TIPUS]],Tarifas!$H$12:$I$26,2,0) -> FIX | F28: Quota Abril 2020 | G28: 55.34 | H28: 55.34 | I28: 0
A29: 2020 | B29: MARÇ | C29: 43921 | D29: AUTÒNOM | E29: =VLOOKUP(Tabla2[[#This Row],[TIPUS]],Tarifas!$H$12:$I$26,2,0) -> FIX | F29: Quota Març 2020 | G29: =67.54-38.5 -> 29.04 | H29: =67.54-38.5 -> 29.04 | I29: 0 | K29: HI HA UN RETORN DE 38,50
A30: 2020 | B30: MAIG | C30: 43955 | D30: TELÈFON | E30: =VLOOKUP(Tabla2[[#This Row],[TIPUS]],Tarifas!$H$12:$I$26,2,0) -> FIX | F30: Quota Maig 2020 | G30: 57 | H30: 57 | I30: 0
A31: 2020 | B31: MAIG | C31: 43956 | D31: CONSUMIBLES | E31: =VLOOKUP(Tabla2[[#This Row],[TIPUS]],Tarifas!$H$12:$I$26,2,0) -> VARIABLE | F31: Revisió extintors | G31: 50.92 | H31: 0 | I31: 50.92
A32: 2020 | B32: MAIG | C32: 43956 | D32: CONSUMIBLES | E32: =VLOOKUP(Tabla2[[#This Row],[TIPUS]],Tarifas!$H$12:$I$26,2,0) -> VARIABLE | F32: Pintures de la sala | G32: 0 | H32: 0 | I32: 0 | K32: 199.86
A33: 2020 | B33: MAIG | C33: 43956 | D33: CONSUMIBLES | E33: =VLOOKUP(Tabla2[[#This Row],[TIPUS]],Tarifas!$H$12:$I$26,2,0) -> VARIABLE | F33: Pintures de la sala | G33: 36.23 | H33: 0 | I33: 36.23
A34: 2020 | B34: MAIG | C34: 43966 | D34: CONSUMIBLES | E34: =VLOOKUP(Tabla2[[#This Row],[TIPUS]],Tarifas!$H$12:$I$26,2,0) -> VARIABLE | F34: Rètols | G34: 100 | H34: 0 | I34: 100
A35: 2020 | B35: MAIG | C35: 43976 | D35: GESTORÍA | E35: =VLOOKUP(Tabla2[[#This Row],[TIPUS]],Tarifas!$H$12:$I$26,2,0) -> FIX | F35: Primer trimestre | G35: 90 | H35: 0 | I35: 90
A36: 2020 | B36: MAIG | C36: 43976 | D36: IMPOSTOS | E36: =VLOOKUP(Tabla2[[#This Row],[TIPUS]],Tarifas!$H$12:$I$26,2,0) -> IMPOSTOS | F36: Primer trimestre IVA i IRPF | G36: =230.93+1.62+171 -> 403.55 | H36: =230.93+1.62+171 -> 403.55 | I36: 0
A37: 2020 | B37: JUNY | C37: 43986 | D37: TELÈFON | E37: =VLOOKUP(Tabla2[[#This Row],[TIPUS]],Tarifas!$H$12:$I$26,2,0) -> FIX | F37: Quota Juny 2020 | G37: 57 | H37: 57 | I37: 0
A38: 2020 | B38: JUNY | C38: 43991 | D38: CONSUMIBLES | E38: =VLOOKUP(Tabla2[[#This Row],[TIPUS]],Tarifas!$H$12:$I$26,2,0) -> VARIABLE | F38: Rètols | G38: 125 | H38: 0 | I38: 125
A39: 2020 | B39: JUNY | C39: 44012 | D39: CONSUMIBLES | E39: =VLOOKUP(Tabla2[[#This Row],[TIPUS]],Tarifas!$H$12:$I$26,2,0) -> VARIABLE | F39: Leroy Merlin | G39: 19.08 | H39: 19.08 | I39: 0
A40: 2020 | B40: JUNY | C40: 44012 | D40: LLOGUER | E40: =VLOOKUP(Tabla2[[#This Row],[TIPUS]],Tarifas!$H$12:$I$26,2,0) -> FIX | F40: Lloguer juny 2020 | G40: 152 | H40: 0 | I40: 152
A41: 2020 | B41: JULIOL | C41: 44013 | D41: LLOGUER | E41: =VLOOKUP(Tabla2[[#This Row],[TIPUS]],Tarifas!$H$12:$I$26,2,0) -> FIX | F41: Lloguer juliol 2020 | G41: 200 | H41: 0 | I41: 200
A42: 2020 | B42: JULIOL | C42: 44018 | D42: TELÈFON | E42: =VLOOKUP(Tabla2[[#This Row],[TIPUS]],Tarifas!$H$12:$I$26,2,0) -> FIX | F42: Quota Juliol 2020 | G42: 57 | H42: 57 | I42: 0
A43: 2020 | B43: JULIOL | C43: 44034 | D43: CONSUMIBLES | E43: =VLOOKUP(Tabla2[[#This Row],[TIPUS]],Tarifas!$H$12:$I$26,2,0) -> VARIABLE | F43: Mercadona | G43: 5 | H43: 0 | I43: 5
A44: 2020 | B44: JULIOL | C44: 44036 | D44: LLUM | E44: =VLOOKUP(Tabla2[[#This Row],[TIPUS]],Tarifas!$H$12:$I$26,2,0) -> VARIABLE | F44: Llum segon trimestre | G44: 164.02 | H44: 164.02 | I44: 0
A45: 2020 | B45: JULIOL | C45: 44040 | D45: AIGUA | E45: =VLOOKUP(Tabla2[[#This Row],[TIPUS]],Tarifas!$H$12:$I$26,2,0) -> VARIABLE | F45: Aigua segon trimestre | G45: 162.01 | H45: 162.01 | I45: 0
A46: 2020 | B46: JULIOL | C46: 44040 | D46: LLOGUER | E46: =VLOOKUP(Tabla2[[#This Row],[TIPUS]],Tarifas!$H$12:$I$26,2,0) -> FIX | F46: Lloguer juliol 2020 | G46: 306 | H46: 306 | I46: 0
A47: 2020 | B47: JULIOL | C47: 44043 | D47: GESTORÍA | E47: =VLOOKUP(Tabla2[[#This Row],[TIPUS]],Tarifas!$H$12:$I$26,2,0) -> FIX | F47: Segon trimestre | G47: 90 | H47: 0 | I47: 90
A48: 2020 | B48: AGOST | C48: 44049 | D48: TELÈFON | E48: =VLOOKUP(Tabla2[[#This Row],[TIPUS]],Tarifas!$H$12:$I$26,2,0) -> FIX | F48: Quota Agost 2020 | G48: 60.21 | H48: 60.21 | I48: 0
... A59: 2020 | B59: OCTUBRE | C59: 44113 | D59: LLOGUER | E59: =VLOOKUP(Tabla2[[#This Row],[TIPUS]],Tarifas!$H$12:$I$26,2,0) -> FIX | F59: Lloguer octubre 2020 | G59: 506 | H59: 306 | I59: 200
A60: 2020 | B60: OCTUBRE | C60: 44123 | D60: IMPOSTOS | E60: =VLOOKUP(Tabla2[[#This Row],[TIPUS]],Tarifas!$H$12:$I$26,2,0) -> IMPOSTOS | F60: Tercer trimestre IVA i IRPF | G60: =251.99+171 -> 422.99 | H60: =251.99+171 -> 422.99 | I60: 0
A61: 2020 | B61: OCTUBRE | C61: 44134 | D61: AUTÒNOM | E61: =VLOOKUP(Tabla2[[#This Row],[TIPUS]],Tarifas!$H$12:$I$26,2,0) -> FIX | F61: Quota octubre 2020 | G61: 68.49 | H61: 68.49 | I61: 0
A62: 2020 | B62: NOVEMBRE | C62: 44140 | D62: TELÈFON | E62: =VLOOKUP(Tabla2[[#This Row],[TIPUS]],Tarifas!$H$12:$I$26,2,0) -> FIX | F62: Quota novembre 2020 | G62: 57 | H62: 57 | I62: 0
A63: 2020 | B63: DESEMBRE | C63: 44170 | D63: TELÈFON | E63: =VLOOKUP(Tabla2[[#This Row],[TIPUS]],Tarifas!$H$12:$I$26,2,0) -> FIX | F63: Quota desembre 2020 | G63: 57 | H63: 57 | I63: 0
A64: 2020 | B64: DESEMBRE | C64: 44193 | D64: GESTORÍA | E64: =VLOOKUP(Tabla2[[#This Row],[TIPUS]],Tarifas!$H$12:$I$26,2,0) -> FIX | F64: Quota tercer i quart trimestre | G64: 180 | H64: 0 | I64: 180
A65: 2020 | B65: DESEMBRE | C65: 44196 | D65: LLUM | E65: =VLOOKUP(Tabla2[[#This Row],[TIPUS]],Tarifas!$H$12:$I$26,2,0) -> VARIABLE | F65: Quota quart trimestre 2020 | G65: 77.94 | H65: 77.94 | I65: 0
A66: 2020 | B66: DESEMBRE | C66: 44196 | D66: IMPOSTOS | E66: =VLOOKUP(Tabla2[[#This Row],[TIPUS]],Tarifas!$H$12:$I$26,2,0) -> IMPOSTOS | F66: Quart trimestre IVA i IRPF | G66: 57 | H66: 57 | I66: 0
A67: 2021 | B67: GENER | C67: 44201 | D67: TELÈFON | E67: =VLOOKUP(Tabla2[[#This Row],[TIPUS]],Tarifas!$H$12:$I$26,2,0) -> FIX | F67: Quota gener 2021 | G67: 53.3 | H67: 53.3 | I67: 0
A68: 2021 | B68: GENER | C68: 44206 | D68: LLOGUER | E68: =VLOOKUP(Tabla2[[#This Row],[TIPUS]],Tarifas!$H$12:$I$26,2,0) -> FIX | F68: Quota Gener 2021 | G68: 204 | H68: 204 | I68: 0
A69: 2021 | B69: GENER | C69: 44215 | D69: ASSEGURANÇA | E69: =VLOOKUP(Tabla2[[#This Row],[TIPUS]],Tarifas!$H$12:$I$26,2,0) -> FIX | F69: Quota 2021 | G69: 382.66 | H69: 382.66 | I69: 0
A70: 2021 | B70: FEBRER | C70: 44237 | D70: LLOGUER | E70: =VLOOKUP(Tabla2[[#This Row],[TIPUS]],Tarifas!$H$12:$I$26,2,0) -> FIX | F70: Quota Febrer 2021 | G70: 204 | H70: 204 | I70: 0
A71: 2021 | B71: FEBRER | C71: 44237 | D71: IMPOSTOS | E71: =VLOOKUP(Tabla2[[#This Row],[TIPUS]],Tarifas!$H$12:$I$26,2,0) -> IMPOSTOS | F71: Comisió | G71: 3.07 | H71: 3.07 | I71: 0
A72: 2021 | B72: FEBRER | C72: 44237 | D72: TELÈFON | E72: =VLOOKUP(Tabla2[[#This Row],[TIPUS]],Tarifas!$H$12:$I$26,2,0) -> FIX | F72: Quota Febrer 2021 | G72: 55.58 | H72: 55.58 | I72: 0
A73: 2021 | B73: FEBRER | C73: 44242 | D73: AIGUA | E73: =VLOOKUP(Tabla2[[#This Row],[TIPUS]],Tarifas!$H$12:$I$26,2,0) -> VARIABLE | F73: Llum gener i febrer | G73: 28.45 | H73: 28.45 | I73: 0
A74: 2021 | B74: FEBRER | C74: 44253 | D74: AUTÒNOM | E74: =VLOOKUP(Tabla2[[#This Row],[TIPUS]],Tarifas!$H$12:$I$26,2,0) -> FIX | F74: Seguretat social | G74: =152.52-69.41 -> 83.11 | H74: =152.52-69.41 -> 83.11 | I74: 0 | K74: vam pagar 152,52 i ens van tornar 69,41
A75: 2021 | B75: FEBRER | C75: 44253 | D75: AUTÒNOM | E75: =VLOOKUP(Tabla2[[#This Row],[TIPUS]],Tarifas!$H$12:$I$26,2,0) -> FIX | F75: Seguretat social | G75: 0.95 | H75: 0.95 | I75: 0
A76: 2021 | B76: MARÇ | C76: 44259 | D76: TELÈFON | E76: =VLOOKUP(Tabla2[[#This Row],[TIPUS]],Tarifas!$H$12:$I$26,2,0) -> FIX | F76: Quota març 2021 | G76: 59 | H76: 59 | I76: 0
A77: 2021 | B77: MARÇ | C77: 44265 | D77: LLOGUER | E77: =VLOOKUP(Tabla2[[#This Row],[TIPUS]],Tarifas!$H$12:$I$26,2,0) -> FIX | F77: Quota Març 2021 | G77: 204 | H77: 204 | I77: 0
A78: 2021 | B78: MARÇ | C78: 44286 | D78: AUTÒNOM | E78: =VLOOKUP(Tabla2[[#This Row],[TIPUS]],Tarifas!$H$12:$I$26,2,0) -> FIX | F78: Seguretat social | G78: 0.95 | H78: 0.95 | I78: 0
A79: 2021 | B79: ABRIL | C79: 44290 | D79: TELÈFON | E79: =VLOOKUP(Tabla2[[#This Row],[TIPUS]],Tarifas!$H$12:$I$26,2,0) -> FIX | F79: Quota ABRIL 2021 | G79: 59 | H79: 59 | I79: 0
A80: 2021 | B80: ABRIL | C80: 44296 | D80: LLOGUER | E80: =VLOOKUP(Tabla2[[#This Row],[TIPUS]],Tarifas!$H$12:$I$26,2,0) -> FIX | F80: Quota ABRIL 2021 | G80: 204 | H80: 204 | I80: 0
A81: 2021 | B81: ABRIL | C81: 44314 | D81: IMPOSTOS | E81: =VLOOKUP(Tabla2[[#This Row],[TIPUS]],Tarifas!$H$12:$I$26,2,0) -> IMPOSTOS | F81: Primer trimestre IVA i IRPF | G81: 114 | H81: 114 | I81: 0
A82: 2021 | B82: ABRIL | C82: 44314 | D82: GESTORÍA | E82: =VLOOKUP(Tabla2[[#This Row],[TIPUS]],Tarifas!$H$12:$I$26,2,0) -> FIX | F82: Quota primer trimestre | G82: 90 | H82: 0 | I82: 90
A83: 2021 | B83: MAIG | C83: 44327 | D83: TELÈFON | E83: =VLOOKUP(Tabla2[[#This Row],[TIPUS]],Tarifas!$H$12:$I$26,2,0) -> FIX | F83: Quota MAIG 2021 | G83: 59 | H83: 59 | I83: 0
A84: 2021 | B84: MAIG | C84: 44329 | D84: LLOGUER | E84: =VLOOKUP(Tabla2[[#This Row],[TIPUS]],Tarifas!$H$12:$I$26,2,0) -> FIX | F84: Quota MAIG 2021 | G84: 204 | H84: 204 | I84: 0
A85: 2021 | B85: MAIG | C85: 44342 | D85: CONSUMIBLES | E85: =VLOOKUP(Tabla2[[#This Row],[TIPUS]],Tarifas!$H$12:$I$26,2,0) -> VARIABLE | F85: Revisió extintors | G85: 50.92 | H85: 50.92 | I85: 0
A86: 2021 | B86: JUNY | C86: 44348 | D86: CONSUMIBLES | E86: =VLOOKUP(Tabla2[[#This Row],[TIPUS]],Tarifas!$H$12:$I$26,2,0) -> VARIABLE | F86: Productes de neteja | G86: 14 | H86: 14 | I86: 0
... A106: 2021 | B106: SETEMBRE | C106: 44467 | D106: LLUM | E106: =VLOOKUP(Tabla2[[#This Row],[TIPUS]],Tarifas!$H$12:$I$26,2,0) -> VARIABLE | F106: Llum i agua setembre | G106: 107.7 | H106: 107.7 | I106: 0
A107: 2021 | B107: SETEMBRE | C107: 44469 | D107: AUTÒNOM | E107: =VLOOKUP(Tabla2[[#This Row],[TIPUS]],Tarifas!$H$12:$I$26,2,0) -> FIX | F107: Quota setembre 2021 | G107: =154.49+0.48 -> 154.97 | H107: =154.49+0.48 -> 154.97 | I107: 0
A108: 2021 | B108: OCTUBRE | C108: 44473 | D108: TELÈFON | E108: =VLOOKUP(Tabla2[[#This Row],[TIPUS]],Tarifas!$H$12:$I$26,2,0) -> FIX | F108: Quota octubre 2021 | G108: 59.3 | H108: 59.3 | I108: 0 | J108: x
A109: 2021 | B109: OCTUBRE | C109: 44481 | D109: LLOGUER | E109: =VLOOKUP(Tabla2[[#This Row],[TIPUS]],Tarifas!$H$12:$I$26,2,0) -> FIX | F109: Quota octubre 2021 | G109: 204 | H109: 204 | I109: 0 | J109: x
A110: 2021 | B110: OCTUBRE | C110: 44483 | D110: CONSUMIBLES | E110: =VLOOKUP(Tabla2[[#This Row],[TIPUS]],Tarifas!$H$12:$I$26,2,0) -> VARIABLE | F110: Mirall trencat | G110: 15.49 | H110: 15.49 | I110: 0 | J110: x
A111: 2021 | B111: OCTUBRE | C111: 44489 | D111: IMPOSTOS | E111: =VLOOKUP(Tabla2[[#This Row],[TIPUS]],Tarifas!$H$12:$I$26,2,0) -> IMPOSTOS | F111: TERCER trimestre IVA IRPF | G111: 130.07 | H111: 130.07 | I111: 0
A112: 2021 | B112: OCTUBRE | C112: 44499 | D112: AUTÒNOM | E112: =VLOOKUP(Tabla2[[#This Row],[TIPUS]],Tarifas!$H$12:$I$26,2,0) -> FIX | F112: Quota octubre 2021 | G112: 205.97 | H112: 205.97 | I112: 0 | J112: X
A113: 2021 | B113: OCTUBRE | C113: 44499 | D113: CONSUMIBLES | E113: =VLOOKUP(Tabla2[[#This Row],[TIPUS]],Tarifas!$H$12:$I$26,2,0) -> VARIABLE | F113: Bombetes | G113: 20 | H113: 0 | I113: 20
A114: 2021 | B114: NOVEMBRE | C114: 44505 | D114: TELÈFON | E114: =VLOOKUP(Tabla2[[#This Row],[TIPUS]],Tarifas!$H$12:$I$26,2,0) -> FIX | F114: QUOTA NOVEMBRE 2021 | G114: 59 | H114: 59 | I114: 0 | J114: x
A115: 2021 | B115: NOVEMBRE | C115: 44510 | D115: LLOGUER | E115: =VLOOKUP(Tabla2[[#This Row],[TIPUS]],Tarifas!$H$12:$I$26,2,0) -> FIX | F115: Quota Novembre 2021 | G115: 204 | H115: 204 | I115: 0 | J115: X
A116: 2021 | B116: NOVEMBRE | C116: 44510 | D116: CONSUMIBLES | E116: =VLOOKUP(Tabla2[[#This Row],[TIPUS]],Tarifas!$H$12:$I$26,2,0) -> VARIABLE | F116: Paper mans lavabo | G116: 21.3 | H116: 21.3 | I116: 0
A117: 2021 | B117: NOVEMBRE | C117: 44527 | D117: CONSUMIBLES | E117: =VLOOKUP(Tabla2[[#This Row],[TIPUS]],Tarifas!$H$12:$I$26,2,0) -> VARIABLE | F117: Reparacio maquina neteja vella | G117: 72.6 | H117: 72.6 | I117: 0 | J117: x
A118: 2021 | B118: NOVEMBRE | C118: 44530 | D118: EXTERNALITZACIÓ NETEJA | E118: =VLOOKUP(Tabla2[[#This Row],[TIPUS]],Tarifas!$H$12:$I$26,2,0) -> VARIABLE | F118: NOVEMBRE | G118: 90 | H118: 0 | I118: 90
A119: 2021 | B119: NOVEMBRE | C119: 44530 | D119: AUTÒNOM | E119: =VLOOKUP(Tabla2[[#This Row],[TIPUS]],Tarifas!$H$12:$I$26,2,0) -> FIX | F119: QUOTA NOVEMBRE 2021 | G119: 205.97 | H119: 205.97 | I119: 0 | J119: X
A120: 2021 | B120: DESEMBRE | C120: 44535 | D120: TELÈFON | E120: =VLOOKUP(Tabla2[[#This Row],[TIPUS]],Tarifas!$H$12:$I$26,2,0) -> FIX | F120: QUOTA DESEMBRE 2021 | G120: 59 | H120: 59 | I120: 0 | J120: x
A121: 2021 | B121: DESEMBRE | C121: 44537 | D121: CONSUMIBLES | E121: =VLOOKUP(Tabla2[[#This Row],[TIPUS]],Tarifas!$H$12:$I$26,2,0) -> VARIABLE | F121: Mercadona | G121: 48.64 | H121: 48.64 | I121: 0 | J121: x
A122: 2021 | B122: DESEMBRE | C122: 44537 | D122: INVERSIONS CAPITAL | E122: =VLOOKUP(Tabla2[[#This Row],[TIPUS]],Tarifas!$H$12:$I$26,2,0) -> INVERSIONS | F122: Cadires | G122: 210 | H122: 0 | I122: 210 | J122: x
A123: 2021 | B123: DESEMBRE | C123: 44537 | D123: PÀGINA WEB | E123: =VLOOKUP(Tabla2[[#This Row],[TIPUS]],Tarifas!$H$12:$I$26,2,0) -> FIX | F123: Contracte dos anys | G123: 499 | H123: 499 | I123: 0
A124: 2021 | B124: DESEMBRE | C124: 44537 | D124: DOMINI | E124: =VLOOKUP(Tabla2[[#This Row],[TIPUS]],Tarifas!$H$12:$I$26,2,0) -> FIX | F124: contracte un any | G124: 18 | H124: 18 | I124: 0
A125: 2021 | B125: DESEMBRE | C125: 44544 | D125: EXTERNALITZACIÓ NETEJA | E125: =VLOOKUP(Tabla2[[#This Row],[TIPUS]],Tarifas!$H$12:$I$26,2,0) -> VARIABLE | F125: Desembre | G125: 180 | H125: 0 | I125: 180
A126: 2021 | B126: DESEMBRE | C126: 44557 | D126: LLOGUER | E126: =VLOOKUP(Tabla2[[#This Row],[TIPUS]],Tarifas!$H$12:$I$26,2,0) -> FIX | F126: Quota desembre 2021 | G126: 204 | H126: 204 | I126: 0 | J126: X
A127: 2021 | B127: DESEMBRE | C127: 44557 | D127: LLUM | E127: =VLOOKUP(Tabla2[[#This Row],[TIPUS]],Tarifas!$H$12:$I$26,2,0) -> VARIABLE | F127: quart trimestre llum i aigua | G127: 254.43 | H127: 254.43 | I127: 0 | J127: X
A128: 2021 | B128: DESEMBRE | C128: 44561 | D128: AUTÒNOM | E128: =VLOOKUP(Tabla2[[#This Row],[TIPUS]],Tarifas!$H$12:$I$26,2,0) -> FIX | F128: DESEMBRE 2021 | G128: 208.79 | H128: 208.79 | I128: 0 | J128: X
A129: 2021 | B129: DESEMBRE | C129: 44561 | D129: GESTORÍA | E129: =VLOOKUP(Tabla2[[#This Row],[TIPUS]],Tarifas!$H$12:$I$26,2,0) -> FIX | F129: Quart trimestre | G129: 90 | H129: 0 | I129: 90
...

Sheet 2025
A2: 6 | B2: GENER | D2: FEBRER | F2: MARÇ | H2: ABRIL | J2: MAIG | L2: JUNY | N2: JULIOL | P2: AGOST | R2: SETEMBRE | T2: OCTUBRE | V2: NOVEMBRE | X2: DESEMBRE | Z2: 2025 | AB2: MITJA ANUAL
A3: INGRESOS | B3: =B4+B22 -> 4865 | C3: =IF(B3=0,0,(B3/B3)) -> 1 | D3: =D4+D22 -> 3665 | E3: =IF(D3=0,0,(D3/D3)) -> 1 | F3: =F4+F22 -> 3975 | G3: =IF(F3=0,0,(F3/F3)) -> 1 | H3: =H4+H22 -> 3265 | I3: =IF(H3=0,0,(H3/H3)) -> 1 | J3: =J4+J22 -> 3780 | K3: =IF(J3=0,0,(J3/J3)) -> 1 | L3: =L4+L22 -> 3420 | M3: =IF(L3=0,0,(L3/L3)) -> 1 | N3: =N4+N22 -> 0 | O3: =IF(N3=0,0,(N3/N3)) -> 0 | P3: =P4+P22 -> 0 | Q3: =IF(P3=0,0,(P3/P3)) -> 0 | R3: =R4+R22 -> 0 | S3: =IF(R3=0,0,(R3/R3)) -> 0 | T3: =T4+T22 -> 0 | U3: =IF(T3=0,0,(T3/T3)) -> 0 | V3: =V4+V22 -> 0 | W3: =IF(V3=0,0,(V3/V3)) -> 0 | X3: =X4+X22 -> 0 | Y3: =IF(X3=0,0,(X3/X3)) -> 0 | Z3: =Z4+Z22 -> 22970 | AA3: =IF(Z3=0,0,(Z3/Z3)) -> 1 | AB3: =Z3/$A$2 -> 3828.3333
A4: Reserves efectives | B4: =SUM(B5:B12) -> 4565 | C4: =IF(B$3=0,0,B4/B$3) -> 0.93833505 | D4: =SUM(D5:D12) -> 3585 | E4: =IF(D$3=0,0,D4/D$3) -> 0.9781719 | F4: =SUM(F5:F12) -> 3975 | G4: =IF(F$3=0,0,F4/F$3) -> 1 | H4: =SUM(H5:H12) -> 3085 | I4: =IF(H$3=0,0,H4/H$3) -> 0.94486983 | J4: =SUM(J5:J12) -> 3690 | K4: =IF(J$3=0,0,J4/J$3) -> 0.97619048 | L4: =SUM(L5:L12) -> 3360 | M4: =IF(L$3=0,0,L4/L$3) -> 0.98245614 | N4: =SUM(N5:N12) -> 0 | O4: =IF(N$3=0,0,N4/N$3) -> 0 | P4: =SUM(P5:P12) -> 0 | Q4: =IF(P$3=0,0,P4/P$3) -> 0 | R4: =SUM(R5:R12) -> 0 | S4: =IF(R$3=0,0,R4/R$3) -> 0 | T4: =SUM(T5:T12) -> 0 | U4: =IF(T$3=0,0,T4/T$3) -> 0 | V4: =SUM(V5:V12) -> 0 | W4: =IF(V$3=0,0,V4/V$3) -> 0 | X4: =SUM(X5:X12) -> 0 | Y4: =IF(X$3=0,0,X4/X$3) -> 0 | Z4: =SUM(Z5:Z12) -> 22260 | AA4: =IF(Z$3=0,0,Z4/Z$3) -> 0.96909012 | AB4: =Z4/$A$2 -> 3710
A5: Mati | B5: =SUMIFS('Registre de reserves'!$P$2:$P$1178,'Registre de reserves'!$T$2:$T$1178,"SI",'Registre de reserves'!$I$2:$I$1178,'2025'!$A5,'Registre de reserves'!$B$2:$B$1178,'2025'!B$2,Tabla1[ANY],'2025'!$Z$2)+SUMIFS('Registre de reserves'!$U$2:$U$1178,'Registre de reserves'!$T$2:$T$1178,"RESERVA",'Registre de reserves'!$I$2:$I$1178,'2025'!$A5,'Registre de reserves'!$B$2:$B$1178,'2025'!B$2,Tabla1[ANY],'2025'!$Z$2) -> 600 | C5: =IF(B$4=0,0,B5/B$4) -> 0.13143483 | D5: =SUMIFS('Registre de reserves'!$P$2:$P$1178,'Registre de reserves'!$T$2:$T$1178,"SI",'Registre de reserves'!$I$2:$I$1178,'2025'!$A5,'Registre de reserves'!$B$2:$B$1178,'2025'!D$2,Tabla1[ANY],'2025'!$Z$2)+SUMIFS('Registre de reserves'!$U$2:$U$1178,'Registre de reserves'!$T$2:$T$1178,"RESERVA",'Registre de reserves'!$I$2:$I$1178,'2025'!$A5,'Registre de reserves'!$B$2:$B$1178,'2025'!D$2,Tabla1[ANY],'2025'!$Z$2) -> 1050 | E5: =IF(D$4=0,0,D5/D$4) -> 0.29288703 | F5: =SUMIFS('Registre de reserves'!$P$2:$P$1178,'Registre de reserves'!$T$2:$T$1178,"SI",'Registre de reserves'!$I$2:$I$1178,'2025'!$A5,'Registre de reserves'!$B$2:$B$1178,'2025'!F$2,Tabla1[ANY],'2025'!$Z$2)+SUMIFS('Registre de reserves'!$U$2:$U$1178,'Registre de reserves'!$T$2:$T$1178,"RESERVA",'Registre de reserves'!$I$2:$I$1178,'2025'!$A5,'Registre de reserves'!$B$2:$B$1178,'2025'!F$2,Tabla1[ANY],'2025'!$Z$2) -> 750 | G5: =IF(F$4=0,0,F5/F$4) -> 0.18867925 | H5: =SUMIFS('Registre de reserves'!$P$2:$P$1178,'Registre de reserves'!$T$2:$T$1178,"SI",'Registre de reserves'!$I$2:$I$1178,'2025'!$A5,'Registre de reserves'!$B$2:$B$1178,'2025'!H$2,Tabla1[ANY],'2025'!$Z$2)+SUMIFS('Registre de reserves'!$U$2:$U$1178,'Registre de reserves'!$T$2:$T$1178,"RESERVA",'Registre de reserves'!$I$2:$I$1178,'2025'!$A5,'Registre de reserves'!$B$2:$B$1178,'2025'!H$2,Tabla1[ANY],'2025'!$Z$2) -> 900 | I5: =IF(H$4=0,0,H5/H$4) -> 0.2917342 | J5: =SUMIFS('Registre de reserves'!$P$2:$P$1178,'Registre de reserves'!$T$2:$T$1178,"SI",'Registre de reserves'!$I$2:$I$1178,'2025'!$A5,'Registre de reserves'!$B$2:$B$1178,'2025'!J$2,Tabla1[ANY],'2025'!$Z$2)+SUMIFS('Registre de reserves'!$U$2:$U$1178,'Registre de reserves'!$T$2:$T$1178,"RESERVA",'Registre de reserves'!$I$2:$I$1178,'2025'!$A5,'Registre de reserves'!$B$2:$B$1178,'2025'!J$2,Tabla1[ANY],'2025'!$Z$2) -> 750 | K5: =IF(J$4=0,0,J5/J$4) -> 0.20325203 | L5: =SUMIFS('Registre de reserves'!$P$2:$P$1178,'Registre de reserves'!$T$2:$T$1178,"SI",'Registre de reserves'!$I$2:$I$1178,'2025'!$A5,'Registre de reserves'!$B$2:$B$1178,'2025'!L$2,Tabla1[ANY],'2025'!$Z$2)+SUMIFS('Registre de reserves'!$U$2:$U$1178,'Registre de reserves'!$T$2:$T$1178,"RESERVA",'Registre de reserves'!$I$2:$I$1178,'2025'!$A5,'Registre de reserves'!$B$2:$B$1178,'2025'!L$2,Tabla1[ANY],'2025'!$Z$2) -> 450 | M5: =IF(L$4=0,0,L5/L$4) -> 0.13392857 | N5: =SUMIFS('Registre de reserves'!$P$2:$P$1178,'Registre de reserves'!$T$2:$T$1178,"SI",'Registre de reserves'!$I$2:$I$1178,'2025'!$A5,'Registre de reserves'!$B$2:$B$1178,'2025'!N$2,Tabla1[ANY],'2025'!$Z$2)+SUMIFS('Registre de reserves'!$U$2:$U$1178,'Registre de reserves'!$T$2:$T$1178,"RESERVA",'Registre de reserves'!$I$2:$I$1178,'2025'!$A5,'Registre de reserves'!$B$2:$B$1178,'2025'!N$2,Tabla1[ANY],'2025'!$Z$2) -> 0 | O5: =IF(N$4=0,0,N5/N$4) -> 0 | P5: =SUMIFS('Registre de reserves'!$P$2:$P$1178,'Registre de reserves'!$T$2:$T$1178,"SI",'Registre de reserves'!$I$2:$I$1178,'2025'!$A5,'Registre de reserves'!$B$2:$B$1178,'2025'!P$2,Tabla1[ANY],'2025'!$Z$2)+SUMIFS('Registre de reserves'!$U$2:$U$1178,'Registre de reserves'!$T$2:$T$1178,"RESERVA",'Registre de reserves'!$I$2:$I$1178,'2025'!$A5,'Registre de reserves'!$B$2:$B$1178,'2025'!P$2,Tabla1[ANY],'2025'!$Z$2) -> 0 | Q5: =IF(P$4=0,0,P5/P$4) -> 0 | R5: =SUMIFS('Registre de reserves'!$P$2:$P$1178,'Registre de reserves'!$T$2:$T$1178,"SI",'Registre de reserves'!$I$2:$I$1178,'2025'!$A5,'Registre de reserves'!$B$2:$B$1178,'2025'!R$2,Tabla1[ANY],'2025'!$Z$2)+SUMIFS('Registre de reserves'!$U$2:$U$1178,'Registre de reserves'!$T$2:$T$1178,"RESERVA",'Registre de reserves'!$I$2:$I$1178,'2025'!$A5,'Registre de reserves'!$B$2:$B$1178,'2025'!R$2,Tabla1[ANY],'2025'!$Z$2) -> 0 | S5: =IF(R$4=0,0,R5/R$4) -> 0 | T5: =SUMIFS('Registre de reserves'!$P$2:$P$1178,'Registre de reserves'!$T$2:$T$1178,"SI",'Registre de reserves'!$I$2:$I$1178,'2025'!$A5,'Registre de reserves'!$B$2:$B$1178,'2025'!T$2,Tabla1[ANY],'2025'!$Z$2)+SUMIFS('Registre de reserves'!$U$2:$U$1178,'Registre de reserves'!$T$2:$T$1178,"RESERVA",'Registre de reserves'!$I$2:$I$1178,'2025'!$A5,'Registre de reserves'!$B$2:$B$1178,'2025'!T$2,Tabla1[ANY],'2025'!$Z$2) -> 0 | U5: =IF(T$4=0,0,T5/T$4) -> 0 | V5: =SUMIFS('Registre de reserves'!$P$2:$P$1178,'Registre de reserves'!$T$2:$T$1178,"SI",'Registre de reserves'!$I$2:$I$1178,'2025'!$A5,'Registre de reserves'!$B$2:$B$1178,'2025'!V$2,Tabla1[ANY],'2025'!$Z$2)+SUMIFS('Registre de reserves'!$U$2:$U$1178,'Registre de reserves'!$T$2:$T$1178,"RESERVA",'Registre de reserves'!$I$2:$I$1178,'2025'!$A5,'Registre de reserves'!$B$2:$B$1178,'2025'!V$2,Tabla1[ANY],'2025'!$Z$2) -> 0 | W5: =IF(V$4=0,0,V5/V$4) -> 0 | X5: =SUMIFS('Registre de reserves'!$P$2:$P$1178,'Registre de reserves'!$T$2:$T$1178,"SI",'Registre de reserves'!$I$2:$I$1178,'2025'!$A5,'Registre de reserves'!$B$2:$B$1178,'2025'!X$2,Tabla1[ANY],'2025'!$Z$2)+SUMIFS('Registre de reserves'!$U$2:$U$1178,'Registre de reserves'!$T$2:$T$1178,"RESERVA",'Registre de reserves'!$I$2:$I$1178,'2025'!$A5,'Registre de reserves'!$B$2:$B$1178,'2025'!X$2,Tabla1[ANY],'2025'!$Z$2) -> 0 | Y5: =IF(X$4=0,0,X5/X$4) -> 0 | Z5: =B5+D5+F5+H5+J5+L5+N5+P5+R5+T5+V5+X5 -> 4500 | AA5: =IF(Z$4=0,0,Z5/Z$4) -> 0.20215633 | AB5: =Z5/$A$2 -> 750
A6: Tarda | B6: =SUMIFS('Registre de reserves'!$P$2:$P$1178,'Registre de reserves'!$T$2:$T$1178,"SI",'Registre de reserves'!$I$2:$I$1178,'2025'!$A6,'Registre de reserves'!$B$2:$B$1178,'2025'!B$2,Tabla1[ANY],'2025'!$Z$2)+SUMIFS('Registre de reserves'!$U$2:$U$1178,'Registre de reserves'!$T$2:$T$1178,"RESERVA",'Registre de reserves'!$I$2:$I$1178,'2025'!$A6,'Registre de reserves'!$B$2:$B$1178,'2025'!B$2,Tabla1[ANY],'2025'!$Z$2) -> 1855 | C6: =IF(B$4=0,0,B6/B$4) -> 0.40635268 | D6: =SUMIFS('Registre de reserves'!$P$2:$P$1178,'Registre de reserves'!$T$2:$T$1178,"SI",'Registre de reserves'!$I$2:$I$1178,'2025'!$A6,'Registre de reserves'!$B$2:$B$1178,'2025'!D$2,Tabla1[ANY],'2025'!$Z$2)+SUMIFS('Registre de reserves'!$U$2:$U$1178,'Registre de reserves'!$T$2:$T$1178,"RESERVA",'Registre de reserves'!$I$2:$I$1178,'2025'!$A6,'Registre de reserves'!$B$2:$B$1178,'2025'!D$2,Tabla1[ANY],'2025'!$Z$2) -> 1415 | E6: =IF(D$4=0,0,D6/D$4) -> 0.39470014 | F6: =SUMIFS('Registre de reserves'!$P$2:$P$1178,'Registre de reserves'!$T$2:$T$1178,"SI",'Registre de reserves'!$I$2:$I$1178,'2025'!$A6,'Registre de reserves'!$B$2:$B$1178,'2025'!F$2,Tabla1[ANY],'2025'!$Z$2)+SUMIFS('Registre de reserves'!$U$2:$U$1178,'Registre de reserves'!$T$2:$T$1178,"RESERVA",'Registre de reserves'!$I$2:$I$1178,'2025'!$A6,'Registre de reserves'!$B$2:$B$1178,'2025'!F$2,Tabla1[ANY],'2025'!$Z$2) -> 1625 | G6: =IF(F$4=0,0,F6/F$4) -> 0.40880503 | H6: =SUMIFS('Registre de reserves'!$P$2:$P$1178,'Registre de reserves'!$T$2:$T$1178,"SI",'Registre de reserves'!$I$2:$I$1178,'2025'!$A6,'Registre de reserves'!$B$2:$B$1178,'2025'!H$2,Tabla1[ANY],'2025'!$Z$2)+SUMIFS('Registre de reserves'!$U$2:$U$1178,'Registre de reserves'!$T$2:$T$1178,"RESERVA",'Registre de reserves'!$I$2:$I$1178,'2025'!$A6,'Registre de reserves'!$B$2:$B$1178,'2025'!H$2,Tabla1[ANY],'2025'!$Z$2) -> 1185 | I6: =IF(H$4=0,0,H6/H$4) -> 0.38411669 | J6: =SUMIFS('Registre de reserves'!$P$2:$P$1178,'Registre de reserves'!$T$2:$T$1178,"SI",'Registre de reserves'!$I$2:$I$1178,'2025'!$A6,'Registre de reserves'!$B$2:$B$1178,'2025'!J$2,Tabla1[ANY],'2025'!$Z$2)+SUMIFS('Registre de reserves'!$U$2:$U$1178,'Registre de reserves'!$T$2:$T$1178,"RESERVA",'Registre de reserves'!$I$2:$I$1178,'2025'!$A6,'Registre de reserves'!$B$2:$B$1178,'2025'!J$2,Tabla1[ANY],'2025'!$Z$2) -> 1420 | K6: =IF(J$4=0,0,J6/J$4) -> 0.38482385 | L6: =SUMIFS('Registre de reserves'!$P$2:$P$1178,'Registre de reserves'!$T$2:$T$1178,"SI",'Registre de reserves'!$I$2:$I$1178,'2025'!$A6,'Registre de reserves'!$B$2:$B$1178,'2025'!L$2,Tabla1[ANY],'2025'!$Z$2)+SUMIFS('Registre de reserves'!$U$2:$U$1178,'Registre de reserves'!$T$2:$T$1178,"RESERVA",'Registre de reserves'!$I$2:$I$1178,'2025'!$A6,'Registre de reserves'!$B$2:$B$1178,'2025'!L$2,Tabla1[ANY],'2025'!$Z$2) -> 1230 | M6: =IF(L$4=0,0,L6/L$4) -> 0.36607143 | N6: =SUMIFS('Registre de reserves'!$P$2:$P$1178,'Registre de reserves'!$T$2:$T$1178,"SI",'Registre de reserves'!$I$2:$I$1178,'2025'!$A6,'Registre de reserves'!$B$2:$B$1178,'2025'!N$2,Tabla1[ANY],'2025'!$Z$2)+SUMIFS('Registre de reserves'!$U$2:$U$1178,'Registre de reserves'!$T$2:$T$1178,"RESERVA",'Registre de reserves'!$I$2:$I$1178,'2025'!$A6,'Registre de reserves'!$B$2:$B$1178,'2025'!N$2,Tabla1[ANY],'2025'!$Z$2) -> 0 | O6: =IF(N$4=0,0,N6/N$4) -> 0 | P6: =SUMIFS('Registre de reserves'!$P$2:$P$1178,'Registre de reserves'!$T$2:$T$1178,"SI",'Registre de reserves'!$I$2:$I$1178,'2025'!$A6,'Registre de reserves'!$B$2:$B$1178,'2025'!P$2,Tabla1[ANY],'2025'!$Z$2)+SUMIFS('Registre de reserves'!$U$2:$U$1178,'Registre de reserves'!$T$2:$T$1178,"RESERVA",'Registre de reserves'!$I$2:$I$1178,'2025'!$A6,'Registre de reserves'!$B$2:$B$1178,'2025'!P$2,Tabla1[ANY],'2025'!$Z$2) -> 0 | Q6: =IF(P$4=0,0,P6/P$4) -> 0 | R6: =SUMIFS('Registre de reserves'!$P$2:$P$1178,'Registre de reserves'!$T$2:$T$1178,"SI",'Registre de reserves'!$I$2:$I$1178,'2025'!$A6,'Registre de reserves'!$B$2:$B$1178,'2025'!R$2,Tabla1[ANY],'2025'!$Z$2)+SUMIFS('Registre de reserves'!$U$2:$U$1178,'Registre de reserves'!$T$2:$T$1178,"RESERVA",'Registre de reserves'!$I$2:$I$1178,'2025'!$A6,'Registre de reserves'!$B$2:$B$1178,'2025'!R$2,Tabla1[ANY],'2025'!$Z$2) -> 0 | S6: =IF(R$4=0,0,R6/R$4) -> 0 | T6: =SUMIFS('Registre de reserves'!$P$2:$P$1178,'Registre de reserves'!$T$2:$T$1178,"SI",'Registre de reserves'!$I$2:$I$1178,'2025'!$A6,'Registre de reserves'!$B$2:$B$1178,'2025'!T$2,Tabla1[ANY],'2025'!$Z$2)+SUMIFS('Registre de reserves'!$U$2:$U$1178,'Registre de reserves'!$T$2:$T$1178,"RESERVA",'Registre de reserves'!$I$2:$I$1178,'2025'!$A6,'Registre de reserves'!$B$2:$B$1178,'2025'!T$2,Tabla1[ANY],'2025'!$Z$2) -> 0 | U6: =IF(T$4=0,0,T6/T$4) -> 0 | V6: =SUMIFS('Registre de reserves'!$P$2:$P$1178,'Registre de reserves'!$T$2:$T$1178,"SI",'Registre de reserves'!$I$2:$I$1178,'2025'!$A6,'Registre de reserves'!$B$2:$B$1178,'2025'!V$2,Tabla1[ANY],'2025'!$Z$2)+SUMIFS('Registre de reserves'!$U$2:$U$1178,'Registre de reserves'!$T$2:$T$1178,"RESERVA",'Registre de reserves'!$I$2:$I$1178,'2025'!$A6,'Registre de reserves'!$B$2:$B$1178,'2025'!V$2,Tabla1[ANY],'2025'!$Z$2) -> 0 | W6: =IF(V$4=0,0,V6/V$4) -> 0 | X6: =SUMIFS('Registre de reserves'!$P$2:$P$1178,'Registre de reserves'!$T$2:$T$1178,"SI",'Registre de reserves'!$I$2:$I$1178,'2025'!$A6,'Registre de reserves'!$B$2:$B$1178,'2025'!X$2,Tabla1[ANY],'2025'!$Z$2)+SUMIFS('Registre de reserves'!$U$2:$U$1178,'Registre de reserves'!$T$2:$T$1178,"RESERVA",'Registre de reserves'!$I$2:$I$1178,'2025'!$A6,'Registre de reserves'!$B$2:$B$1178,'2025'!X$2,Tabla1[ANY],'2025'!$Z$2) -> 0 | Y6: =IF(X$4=0,0,X6/X$4) -> 0 | Z6: =B6+D6+F6+H6+J6+L6+N6+P6+R6+T6+V6+X6 -> 8730 | AA6: =IF(Z$4=0,0,Z6/Z$4) -> 0.39218329 | AB6: =Z6/$A$2 -> 1455
A7: Dia sencer | B7: =SUMIFS('Registre de reserves'!$P$2:$P$1178,'Registre de reserves'!$T$2:$T$1178,"SI",'Registre de reserves'!$I$2:$I$1178,'2025'!$A7,'Registre de reserves'!$B$2:$B$1178,'2025'!B$2,Tabla1[ANY],'2025'!$Z$2)+SUMIFS('Registre de reserves'!$U$2:$U$1178,'Registre de reserves'!$T$2:$T$1178,"RESERVA",'Registre de reserves'!$I$2:$I$1178,'2025'!$A7,'Registre de reserves'!$B$2:$B$1178,'2025'!B$2,Tabla1[ANY],'2025'!$Z$2) -> 910 | C7: =IF(B$4=0,0,B7/B$4) -> 0.19934283 | D7: =SUMIFS('Registre de reserves'!$P$2:$P$1178,'Registre de reserves'!$T$2:$T$1178,"SI",'Registre de reserves'!$I$2:$I$1178,'2025'!$A7,'Registre de reserves'!$B$2:$B$1178,'2025'!D$2,Tabla1[ANY],'2025'!$Z$2)+SUMIFS('Registre de reserves'!$U$2:$U$1178,'Registre de reserves'!$T$2:$T$1178,"RESERVA",'Registre de reserves'!$I$2:$I$1178,'2025'!$A7,'Registre de reserves'!$B$2:$B$1178,'2025'!D$2,Tabla1[ANY],'2025'!$Z$2) -> 320 | E7: =IF(D$4=0,0,D7/D$4) -> 0.089260809 | F7: =SUMIFS('Registre de reserves'!$P$2:$P$1178,'Registre de reserves'!$T$2:$T$1178,"SI",'Registre de reserves'!$I$2:$I$1178,'2025'!$A7,'Registre de reserves'!$B$2:$B$1178,'2025'!F$2,Tabla1[ANY],'2025'!$Z$2)+SUMIFS('Registre de reserves'!$U$2:$U$1178,'Registre de reserves'!$T$2:$T$1178,"RESERVA",'Registre de reserves'!$I$2:$I$1178,'2025'!$A7,'Registre de reserves'!$B$2:$B$1178,'2025'!F$2,Tabla1[ANY],'2025'!$Z$2) -> 0 | G7: =IF(F$4=0,0,F7/F$4) -> 0 | H7: =SUMIFS('Registre de reserves'!$P$2:$P$1178,'Registre de reserves'!$T$2:$T$1178,"SI",'Registre de reserves'!$I$2:$I$1178,'2025'!$A7,'Registre de reserves'!$B$2:$B$1178,'2025'!H$2,Tabla1[ANY],'2025'!$Z$2)+SUMIFS('Registre de reserves'!$U$2:$U$1178,'Registre de reserves'!$T$2:$T$1178,"RESERVA",'Registre de reserves'!$I$2:$I$1178,'2025'!$A7,'Registre de reserves'!$B$2:$B$1178,'2025'!H$2,Tabla1[ANY],'2025'!$Z$2) -> 0 | I7: =IF(H$4=0,0,H7/H$4) -> 0 | J7: =SUMIFS('Registre de reserves'!$P$2:$P$1178,'Registre de reserves'!$T$2:$T$1178,"SI",'Registre de reserves'!$I$2:$I$1178,'2025'!$A7,'Registre de reserves'!$B$2:$B$1178,'2025'!J$2,Tabla1[ANY],'2025'!$Z$2)+SUMIFS('Registre de reserves'!$U$2:$U$1178,'Registre de reserves'!$T$2:$T$1178,"RESERVA",'Registre de reserves'!$I$2:$I$1178,'2025'!$A7,'Registre de reserves'!$B$2:$B$1178,'2025'!J$2,Tabla1[ANY],'2025'!$Z$2) -> 0 | K7: =IF(J$4=0,0,J7/J$4) -> 0 | L7: =SUMIFS('Registre de reserves'!$P$2:$P$1178,'Registre de reserves'!$T$2:$T$1178,"SI",'Registre de reserves'!$I$2:$I$1178,'2025'!$A7,'Registre de reserves'!$B$2:$B$1178,'2025'!L$2,Tabla1[ANY],'2025'!$Z$2)+SUMIFS('Registre de reserves'!$U$2:$U$1178,'Registre de reserves'!$T$2:$T$1178,"RESERVA",'Registre de reserves'!$I$2:$I$1178,'2025'!$A7,'Registre de reserves'!$B$2:$B$1178,'2025'!L$2,Tabla1[ANY],'2025'!$Z$2) -> 0 | M7: =IF(L$4=0,0,L7/L$4) -> 0 | N7: =SUMIFS('Registre de reserves'!$P$2:$P$1178,'Registre de reserves'!$T$2:$T$1178,"SI",'Registre de reserves'!$I$2:$I$1178,'2025'!$A7,'Registre de reserves'!$B$2:$B$1178,'2025'!N$2,Tabla1[ANY],'2025'!$Z$2)+SUMIFS('Registre de reserves'!$U$2:$U$1178,'Registre de reserves'!$T$2:$T$1178,"RESERVA",'Registre de reserves'!$I$2:$I$1178,'2025'!$A7,'Registre de reserves'!$B$2:$B$1178,'2025'!N$2,Tabla1[ANY],'2025'!$Z$2) -> 0 | O7: =IF(N$4=0,0,N7/N$4) -> 0 | P7: =SUMIFS('Registre de reserves'!$P$2:$P$1178,'Registre de reserves'!$T$2:$T$1178,"SI",'Registre de reserves'!$I$2:$I$1178,'2025'!$A7,'Registre de reserves'!$B$2:$B$1178,'2025'!P$2,Tabla1[ANY],'2025'!$Z$2)+SUMIFS('Registre de reserves'!$U$2:$U$1178,'Registre de reserves'!$T$2:$T$1178,"RESERVA",'Registre de reserves'!$I$2:$I$1178,'2025'!$A7,'Registre de reserves'!$B$2:$B$1178,'2025'!P$2,Tabla1[ANY],'2025'!$Z$2) -> 0 | Q7: =IF(P$4=0,0,P7/P$4) -> 0 | R7: =SUMIFS('Registre de reserves'!$P$2:$P$1178,'Registre de reserves'!$T$2:$T$1178,"SI",'Registre de reserves'!$I$2:$I$1178,'2025'!$A7,'Registre de reserves'!$B$2:$B$1178,'2025'!R$2,Tabla1[ANY],'2025'!$Z$2)+SUMIFS('Registre de reserves'!$U$2:$U$1178,'Registre de reserves'!$T$2:$T$1178,"RESERVA",'Registre de reserves'!$I$2:$I$1178,'2025'!$A7,'Registre de reserves'!$B$2:$B$1178,'2025'!R$2,Tabla1[ANY],'2025'!$Z$2) -> 0 | S7: =IF(R$4=0,0,R7/R$4) -> 0 | T7: =SUMIFS('Registre de reserves'!$P$2:$P$1178,'Registre de reserves'!$T$2:$T$1178,"SI",'Registre de reserves'!$I$2:$I$1178,'2025'!$A7,'Registre de reserves'!$B$2:$B$1178,'2025'!T$2,Tabla1[ANY],'2025'!$Z$2)+SUMIFS('Registre de reserves'!$U$2:$U$1178,'Registre de reserves'!$T$2:$T$1178,"RESERVA",'Registre de reserves'!$I$2:$I$1178,'2025'!$A7,'Registre de reserves'!$B$2:$B$1178,'2025'!T$2,Tabla1[ANY],'2025'!$Z$2) -> 0 | U7: =IF(T$4=0,0,T7/T$4) -> 0 | V7: =SUMIFS('Registre de reserves'!$P$2:$P$1178,'Registre de reserves'!$T$2:$T$1178,"SI",'Registre de reserves'!$I$2:$I$1178,'2025'!$A7,'Registre de reserves'!$B$2:$B$1178,'2025'!V$2,Tabla1[ANY],'2025'!$Z$2)+SUMIFS('Registre de reserves'!$U$2:$U$1178,'Registre de reserves'!$T$2:$T$1178,"RESERVA",'Registre de reserves'!$I$2:$I$1178,'2025'!$A7,'Registre de reserves'!$B$2:$B$1178,'2025'!V$2,Tabla1[ANY],'2025'!$Z$2) -> 0 | W7: =IF(V$4=0,0,V7/V$4) -> 0 | X7: =SUMIFS('Registre de reserves'!$P$2:$P$1178,'Registre de reserves'!$T$2:$T$1178,"SI",'Registre de reserves'!$I$2:$I$1178,'2025'!$A7,'Registre de reserves'!$B$2:$B$1178,'2025'!X$2,Tabla1[ANY],'2025'!$Z$2)+SUMIFS('Registre de reserves'!$U$2:$U$1178,'Registre de reserves'!$T$2:$T$1178,"RESERVA",'Registre de reserves'!$I$2:$I$1178,'2025'!$A7,'Registre de reserves'!$B$2:$B$1178,'2025'!X$2,Tabla1[ANY],'2025'!$Z$2) -> 0 | Y7: =IF(X$4=0,0,X7/X$4) -> 0 | Z7: =B7+D7+F7+H7+J7+L7+N7+P7+R7+T7+V7+X7 -> 1230 | AA7: =IF(Z$4=0,0,Z7/Z$4) -> 0.055256065 | AB7: =Z7/$A$2 -> 205
A8: Dinar | B8: =SUMIFS('Registre de reserves'!$P$2:$P$1178,'Registre de reserves'!$T$2:$T$1178,"SI",'Registre de reserves'!$I$2:$I$1178,'2025'!$A8,'Registre de reserves'!$B$2:$B$1178,'2025'!B$2,Tabla1[ANY],'2025'!$Z$2)+SUMIFS('Registre de reserves'!$U$2:$U$1178,'Registre de reserves'!$T$2:$T$1178,"RESERVA",'Registre de reserves'!$I$2:$I$1178,'2025'!$A8,'Registre de reserves'!$B$2:$B$1178,'2025'!B$2,Tabla1[ANY],'2025'!$Z$2) -> 0 | C8: =IF(B$4=0,0,B8/B$4) -> 0 | D8: =SUMIFS('Registre de reserves'!$P$2:$P$1178,'Registre de reserves'!$T$2:$T$1178,"SI",'Registre de reserves'!$I$2:$I$1178,'2025'!$A8,'Registre de reserves'!$B$2:$B$1178,'2025'!D$2,Tabla1[ANY],'2025'!$Z$2)+SUMIFS('Registre de reserves'!$U$2:$U$1178,'Registre de reserves'!$T$2:$T$1178,"RESERVA",'Registre de reserves'!$I$2:$I$1178,'2025'!$A8,'Registre de reserves'!$B$2:$B$1178,'2025'!D$2,Tabla1[ANY],'2025'!$Z$2) -> 0 | E8: =IF(D$4=0,0,D8/D$4) -> 0 | F8: =SUMIFS('Registre de reserves'!$P$2:$P$1178,'Registre de reserves'!$T$2:$T$1178,"SI",'Registre de reserves'!$I$2:$I$1178,'2025'!$A8,'Registre de reserves'!$B$2:$B$1178,'2025'!F$2,Tabla1[ANY],'2025'!$Z$2)+SUMIFS('Registre de reserves'!$U$2:$U$1178,'Registre de reserves'!$T$2:$T$1178,"RESERVA",'Registre de reserves'!$I$2:$I$1178,'2025'!$A8,'Registre de reserves'!$B$2:$B$1178,'2025'!F$2,Tabla1[ANY],'2025'!$Z$2) -> 0 | G8: =IF(F$4=0,0,F8/F$4) -> 0 | H8: =SUMIFS('Registre de reserves'!$P$2:$P$1178,'Registre de reserves'!$T$2:$T$1178,"SI",'Registre de reserves'!$I$2:$I$1178,'2025'!$A8,'Registre de reserves'!$B$2:$B$1178,'2025'!H$2,Tabla1[ANY],'2025'!$Z$2)+SUMIFS('Registre de reserves'!$U$2:$U$1178,'Registre de reserves'!$T$2:$T$1178,"RESERVA",'Registre de reserves'!$I$2:$I$1178,'2025'!$A8,'Registre de reserves'!$B$2:$B$1178,'2025'!H$2,Tabla1[ANY],'2025'!$Z$2) -> 0 | I8: =IF(H$4=0,0,H8/H$4) -> 0 | J8: =SUMIFS('Registre de reserves'!$P$2:$P$1178,'Registre de reserves'!$T$2:$T$1178,"SI",'Registre de reserves'!$I$2:$I$1178,'2025'!$A8,'Registre de reserves'!$B$2:$B$1178,'2025'!J$2,Tabla1[ANY],'2025'!$Z$2)+SUMIFS('Registre de reserves'!$U$2:$U$1178,'Registre de reserves'!$T$2:$T$1178,"RESERVA",'Registre de reserves'!$I$2:$I$1178,'2025'!$A8,'Registre de reserves'!$B$2:$B$1178,'2025'!J$2,Tabla1[ANY],'2025'!$Z$2) -> 0 | K8: =IF(J$4=0,0,J8/J$4) -> 0 | L8: =SUMIFS('Registre de reserves'!$P$2:$P$1178,'Registre de reserves'!$T$2:$T$1178,"SI",'Registre de reserves'!$I$2:$I$1178,'2025'!$A8,'Registre de reserves'!$B$2:$B$1178,'2025'!L$2,Tabla1[ANY],'2025'!$Z$2)+SUMIFS('Registre de reserves'!$U$2:$U$1178,'Registre de reserves'!$T$2:$T$1178,"RESERVA",'Registre de reserves'!$I$2:$I$1178,'2025'!$A8,'Registre de reserves'!$B$2:$B$1178,'2025'!L$2,Tabla1[ANY],'2025'!$Z$2) -> 0 | M8: =IF(L$4=0,0,L8/L$4) -> 0 | N8: =SUMIFS('Registre de reserves'!$P$2:$P$1178,'Registre de reserves'!$T$2:$T$1178,"SI",'Registre de reserves'!$I$2:$I$1178,'2025'!$A8,'Registre de reserves'!$B$2:$B$1178,'2025'!N$2,Tabla1[ANY],'2025'!$Z$2)+SUMIFS('Registre de reserves'!$U$2:$U$1178,'Registre de reserves'!$T$2:$T$1178,"RESERVA",'Registre de reserves'!$I$2:$I$1178,'2025'!$A8,'Registre de reserves'!$B$2:$B$1178,'2025'!N$2,Tabla1[ANY],'2025'!$Z$2) -> 0 | O8: =IF(N$4=0,0,N8/N$4) -> 0 | P8: =SUMIFS('Registre de reserves'!$P$2:$P$1178,'Registre de reserves'!$T$2:$T$1178,"SI",'Registre de reserves'!$I$2:$I$1178,'2025'!$A8,'Registre de reserves'!$B$2:$B$1178,'2025'!P$2,Tabla1[ANY],'2025'!$Z$2)+SUMIFS('Registre de reserves'!$U$2:$U$1178,'Registre de reserves'!$T$2:$T$1178,"RESERVA",'Registre de reserves'!$I$2:$I$1178,'2025'!$A8,'Registre de reserves'!$B$2:$B$1178,'2025'!P$2,Tabla1[ANY],'2025'!$Z$2) -> 0 | Q8: =IF(P$4=0,0,P8/P$4) -> 0 | R8: =SUMIFS('Registre de reserves'!$P$2:$P$1178,'Registre de reserves'!$T$2:$T$1178,"SI",'Registre de reserves'!$I$2:$I$1178,'2025'!$A8,'Registre de reserves'!$B$2:$B$1178,'2025'!R$2,Tabla1[ANY],'2025'!$Z$2)+SUMIFS('Registre de reserves'!$U$2:$U$1178,'Registre de reserves'!$T$2:$T$1178,"RESERVA",'Registre de reserves'!$I$2:$I$1178,'2025'!$A8,'Registre de reserves'!$B$2:$B$1178,'2025'!R$2,Tabla1[ANY],'2025'!$Z$2) -> 0 | S8: =IF(R$4=0,0,R8/R$4) -> 0 | T8: =SUMIFS('Registre de reserves'!$P$2:$P$1178,'Registre de reserves'!$T$2:$T$1178,"SI",'Registre de reserves'!$I$2:$I$1178,'2025'!$A8,'Registre de reserves'!$B$2:$B$1178,'2025'!T$2,Tabla1[ANY],'2025'!$Z$2)+SUMIFS('Registre de reserves'!$U$2:$U$1178,'Registre de reserves'!$T$2:$T$1178,"RESERVA",'Registre de reserves'!$I$2:$I$1178,'2025'!$A8,'Registre de reserves'!$B$2:$B$1178,'2025'!T$2,Tabla1[ANY],'2025'!$Z$2) -> 0 | U8: =IF(T$4=0,0,T8/T$4) -> 0 | V8: =SUMIFS('Registre de reserves'!$P$2:$P$1178,'Registre de reserves'!$T$2:$T$1178,"SI",'Registre de reserves'!$I$2:$I$1178,'2025'!$A8,'Registre de reserves'!$B$2:$B$1178,'2025'!V$2,Tabla1[ANY],'2025'!$Z$2)+SUMIFS('Registre de reserves'!$U$2:$U$1178,'Registre de reserves'!$T$2:$T$1178,"RESERVA",'Registre de reserves'!$I$2:$I$1178,'2025'!$A8,'Registre de reserves'!$B$2:$B$1178,'2025'!V$2,Tabla1[ANY],'2025'!$Z$2) -> 0 | W8: =IF(V$4=0,0,V8/V$4) -> 0 | X8: =SUMIFS('Registre de reserves'!$P$2:$P$1178,'Registre de reserves'!$T$2:$T$1178,"SI",'Registre de reserves'!$I$2:$I$1178,'2025'!$A8,'Registre de reserves'!$B$2:$B$1178,'2025'!X$2,Tabla1[ANY],'2025'!$Z$2)+SUMIFS('Registre de reserves'!$U$2:$U$1178,'Registre de reserves'!$T$2:$T$1178,"RESERVA",'Registre de reserves'!$I$2:$I$1178,'2025'!$A8,'Registre de reserves'!$B$2:$B$1178,'2025'!X$2,Tabla1[ANY],'2025'!$Z$2) -> 0 | Y8: =IF(X$4=0,0,X8/X$4) -> 0 | Z8: =B8+D8+F8+H8+J8+L8+N8+P8+R8+T8+V8+X8 -> 0 | AA8: =IF(Z$4=0,0,Z8/Z$4) -> 0 | AB8: =Z8/$A$2 -> 0
A9: Sopar | B9: =SUMIFS('Registre de reserves'!$P$2:$P$1178,'Registre de reserves'!$T$2:$T$1178,"SI",'Registre de reserves'!$I$2:$I$1178,'2025'!$A9,'Registre de reserves'!$B$2:$B$1178,'2025'!B$2,Tabla1[ANY],'2025'!$Z$2)+SUMIFS('Registre de reserves'!$U$2:$U$1178,'Registre de reserves'!$T$2:$T$1178,"RESERVA",'Registre de reserves'!$I$2:$I$1178,'2025'!$A9,'Registre de reserves'!$B$2:$B$1178,'2025'!B$2,Tabla1[ANY],'2025'!$Z$2) -> 0 | C9: =IF(B$4=0,0,B9/B$4) -> 0 | D9: =SUMIFS('Registre de reserves'!$P$2:$P$1178,'Registre de reserves'!$T$2:$T$1178,"SI",'Registre de reserves'!$I$2:$I$1178,'2025'!$A9,'Registre de reserves'!$B$2:$B$1178,'2025'!D$2,Tabla1[ANY],'2025'!$Z$2)+SUMIFS('Registre de reserves'!$U$2:$U$1178,'Registre de reserves'!$T$2:$T$1178,"RESERVA",'Registre de reserves'!$I$2:$I$1178,'2025'!$A9,'Registre de reserves'!$B$2:$B$1178,'2025'!D$2,Tabla1[ANY],'2025'!$Z$2) -> 0 | E9: =IF(D$4=0,0,D9/D$4) -> 0 | F9: =SUMIFS('Registre de reserves'!$P$2:$P$1178,'Registre de reserves'!$T$2:$T$1178,"SI",'Registre de reserves'!$I$2:$I$1178,'2025'!$A9,'Registre de reserves'!$B$2:$B$1178,'2025'!F$2,Tabla1[ANY],'2025'!$Z$2)+SUMIFS('Registre de reserves'!$U$2:$U$1178,'Registre de reserves'!$T$2:$T$1178,"RESERVA",'Registre de reserves'!$I$2:$I$1178,'2025'!$A9,'Registre de reserves'!$B$2:$B$1178,'2025'!F$2,Tabla1[ANY],'2025'!$Z$2) -> 0 | G9: =IF(F$4=0,0,F9/F$4) -> 0 | H9: =SUMIFS('Registre de reserves'!$P$2:$P$1178,'Registre de reserves'!$T$2:$T$1178,"SI",'Registre de reserves'!$I$2:$I$1178,'2025'!$A9,'Registre de reserves'!$B$2:$B$1178,'2025'!H$2,Tabla1[ANY],'2025'!$Z$2)+SUMIFS('Registre de reserves'!$U$2:$U$1178,'Registre de reserves'!$T$2:$T$1178,"RESERVA",'Registre de reserves'!$I$2:$I$1178,'2025'!$A9,'Registre de reserves'!$B$2:$B$1178,'2025'!H$2,Tabla1[ANY],'2025'!$Z$2) -> 0 | I9: =IF(H$4=0,0,H9/H$4) -> 0 | J9: =SUMIFS('Registre de reserves'!$P$2:$P$1178,'Registre de reserves'!$T$2:$T$1178,"SI",'Registre de reserves'!$I$2:$I$1178,'2025'!$A9,'Registre de reserves'!$B$2:$B$1178,'2025'!J$2,Tabla1[ANY],'2025'!$Z$2)+SUMIFS('Registre de reserves'!$U$2:$U$1178,'Registre de reserves'!$T$2:$T$1178,"RESERVA",'Registre de reserves'!$I$2:$I$1178,'2025'!$A9,'Registre de reserves'!$B$2:$B$1178,'2025'!J$2,Tabla1[ANY],'2025'!$Z$2) -> 0 | K9: =IF(J$4=0,0,J9/J$4) -> 0 | L9: =SUMIFS('Registre de reserves'!$P$2:$P$1178,'Registre de reserves'!$T$2:$T$1178,"SI",'Registre de reserves'!$I$2:$I$1178,'2025'!$A9,'Registre de reserves'!$B$2:$B$1178,'2025'!L$2,Tabla1[ANY],'2025'!$Z$2)+SUMIFS('Registre de reserves'!$U$2:$U$1178,'Registre de reserves'!$T$2:$T$1178,"RESERVA",'Registre de reserves'!$I$2:$I$1178,'2025'!$A9,'Registre de reserves'!$B$2:$B$1178,'2025'!L$2,Tabla1[ANY],'2025'!$Z$2) -> 0 | M9: =IF(L$4=0,0,L9/L$4) -> 0 | N9: =SUMIFS('Registre de reserves'!$P$2:$P$1178,'Registre de reserves'!$T$2:$T$1178,"SI",'Registre de reserves'!$I$2:$I$1178,'2025'!$A9,'Registre de reserves'!$B$2:$B$1178,'2025'!N$2,Tabla1[ANY],'2025'!$Z$2)+SUMIFS('Registre de reserves'!$U$2:$U$1178,'Registre de reserves'!$T$2:$T$1178,"RESERVA",'Registre de reserves'!$I$2:$I$1178,'2025'!$A9,'Registre de reserves'!$B$2:$B$1178,'2025'!N$2,Tabla1[ANY],'2025'!$Z$2) -> 0 | O9: =IF(N$4=0,0,N9/N$4) -> 0 | P9: =SUMIFS('Registre de reserves'!$P$2:$P$1178,'Registre de reserves'!$T$2:$T$1178,"SI",'Registre de reserves'!$I$2:$I$1178,'2025'!$A9,'Registre de reserves'!$B$2:$B$1178,'2025'!P$2,Tabla1[ANY],'2025'!$Z$2)+SUMIFS('Registre de reserves'!$U$2:$U$1178,'Registre de reserves'!$T$2:$T$1178,"RESERVA",'Registre de reserves'!$I$2:$I$1178,'2025'!$A9,'Registre de reserves'!$B$2:$B$1178,'2025'!P$2,Tabla1[ANY],'2025'!$Z$2) -> 0 | Q9: =IF(P$4=0,0,P9/P$4) -> 0 | R9: =SUMIFS('Registre de reserves'!$P$2:$P$1178,'Registre de reserves'!$T$2:$T$1178,"SI",'Registre de reserves'!$I$2:$I$1178,'2025'!$A9,'Registre de reserves'!$B$2:$B$1178,'2025'!R$2,Tabla1[ANY],'2025'!$Z$2)+SUMIFS('Registre de reserves'!$U$2:$U$1178,'Registre de reserves'!$T$2:$T$1178,"RESERVA",'Registre de reserves'!$I$2:$I$1178,'2025'!$A9,'Registre de reserves'!$B$2:$B$1178,'2025'!R$2,Tabla1[ANY],'2025'!$Z$2) -> 0 | S9: =IF(R$4=0,0,R9/R$4) -> 0 | T9: =SUMIFS('Registre de reserves'!$P$2:$P$1178,'Registre de reserves'!$T$2:$T$1178,"SI",'Registre de reserves'!$I$2:$I$1178,'2025'!$A9,'Registre de reserves'!$B$2:$B$1178,'2025'!T$2,Tabla1[ANY],'2025'!$Z$2)+SUMIFS('Registre de reserves'!$U$2:$U$1178,'Registre de reserves'!$T$2:$T$1178,"RESERVA",'Registre de reserves'!$I$2:$I$1178,'2025'!$A9,'Registre de reserves'!$B$2:$B$1178,'2025'!T$2,Tabla1[ANY],'2025'!$Z$2) -> 0 | U9: =IF(T$4=0,0,T9/T$4) -> 0 | V9: =SUMIFS('Registre de reserves'!$P$2:$P$1178,'Registre de reserves'!$T$2:$T$1178,"SI",'Registre de reserves'!$I$2:$I$1178,'2025'!$A9,'Registre de reserves'!$B$2:$B$1178,'2025'!V$2,Tabla1[ANY],'2025'!$Z$2)+SUMIFS('Registre de reserves'!$U$2:$U$1178,'Registre de reserves'!$T$2:$T$1178,"RESERVA",'Registre de reserves'!$I$2:$I$1178,'2025'!$A9,'Registre de reserves'!$B$2:$B$1178,'2025'!V$2,Tabla1[ANY],'2025'!$Z$2) -> 0 | W9: =IF(V$4=0,0,V9/V$4) -> 0 | X9: =SUMIFS('Registre de reserves'!$P$2:$P$1178,'Registre de reserves'!$T$2:$T$1178,"SI",'Registre de reserves'!$I$2:$I$1178,'2025'!$A9,'Registre de reserves'!$B$2:$B$1178,'2025'!X$2,Tabla1[ANY],'2025'!$Z$2)+SUMIFS('Registre de reserves'!$U$2:$U$1178,'Registre de reserves'!$T$2:$T$1178,"RESERVA",'Registre de reserves'!$I$2:$I$1178,'2025'!$A9,'Registre de reserves'!$B$2:$B$1178,'2025'!X$2,Tabla1[ANY],'2025'!$Z$2) -> 0 | Y9: =IF(X$4=0,0,X9/X$4) -> 0 | Z9: =B9+D9+F9+H9+J9+L9+N9+P9+R9+T9+V9+X9 -> 0 | AA9: =IF(Z$4=0,0,Z9/Z$4) -> 0 | AB9: =Z9/$A$2 -> 0
A10: Nit | B10: =SUMIFS('Registre de reserves'!$P$2:$P$1178,'Registre de reserves'!$T$2:$T$1178,"SI",'Registre de reserves'!$I$2:$I$1178,'2025'!$A10,'Registre de reserves'!$B$2:$B$1178,'2025'!B$2,Tabla1[ANY],'2025'!$Z$2)+SUMIFS('Registre de reserves'!$U$2:$U$1178,'Registre de reserves'!$T$2:$T$1178,"RESERVA",'Registre de reserves'!$I$2:$I$1178,'2025'!$A10,'Registre de reserves'!$B$2:$B$1178,'2025'!B$2,Tabla1[ANY],'2025'!$Z$2) -> 1200 | C10: =IF(B$4=0,0,B10/B$4) -> 0.26286966 | D10: =SUMIFS('Registre de reserves'!$P$2:$P$1178,'Registre de reserves'!$T$2:$T$1178,"SI",'Registre de reserves'!$I$2:$I$1178,'2025'!$A10,'Registre de reserves'!$B$2:$B$1178,'2025'!D$2,Tabla1[ANY],'2025'!$Z$2)+SUMIFS('Registre de reserves'!$U$2:$U$1178,'Registre de reserves'!$T$2:$T$1178,"RESERVA",'Registre de reserves'!$I$2:$I$1178,'2025'!$A10,'Registre de reserves'!$B$2:$B$1178,'2025'!D$2,Tabla1[ANY],'2025'!$Z$2) -> 800 | E10: =IF(D$4=0,0,D10/D$4) -> 0.22315202 | F10: =SUMIFS('Registre de reserves'!$P$2:$P$1178,'Registre de reserves'!$T$2:$T$1178,"SI",'Registre de reserves'!$I$2:$I$1178,'2025'!$A10,'Registre de reserves'!$B$2:$B$1178,'2025'!F$2,Tabla1[ANY],'2025'!$Z$2)+SUMIFS('Registre de reserves'!$U$2:$U$1178,'Registre de reserves'!$T$2:$T$1178,"RESERVA",'Registre de reserves'!$I$2:$I$1178,'2025'!$A10,'Registre de reserves'!$B$2:$B$1178,'2025'!F$2,Tabla1[ANY],'2025'!$Z$2) -> 1000 | G10: =IF(F$4=0,0,F10/F$4) -> 0.25157233 | H10: =SUMIFS('Registre de reserves'!$P$2:$P$1178,'Registre de reserves'!$T$2:$T$1178,"SI",'Registre de reserves'!$I$2:$I$1178,'2025'!$A10,'Registre de reserves'!$B$2:$B$1178,'2025'!H$2,Tabla1[ANY],'2025'!$Z$2)+SUMIFS('Registre de reserves'!$U$2:$U$1178,'Registre de reserves'!$T$2:$T$1178,"RESERVA",'Registre de reserves'!$I$2:$I$1178,'2025'!$A10,'Registre de reserves'!$B$2:$B$1178,'2025'!H$2,Tabla1[ANY],'2025'!$Z$2) -> 1000 | I10: =IF(H$4=0,0,H10/H$4) -> 0.32414911 | J10: =SUMIFS('Registre de reserves'!$P$2:$P$1178,'Registre de reserves'!$T$2:$T$1178,"SI",'Registre de reserves'!$I$2:$I$1178,'2025'!$A10,'Registre de reserves'!$B$2:$B$1178,'2025'!J$2,Tabla1[ANY],'2025'!$Z$2)+SUMIFS('Registre de reserves'!$U$2:$U$1178,'Registre de reserves'!$T$2:$T$1178,"RESERVA",'Registre de reserves'!$I$2:$I$1178,'2025'!$A10,'Registre de reserves'!$B$2:$B$1178,'2025'!J$2,Tabla1[ANY],'2025'!$Z$2) -> 1200 | K10: =IF(J$4=0,0,J10/J$4) -> 0.32520325 | L10: =SUMIFS('Registre de reserves'!$P$2:$P$1178,'Registre de reserves'!$T$2:$T$1178,"SI",'Registre de reserves'!$I$2:$I$1178,'2025'!$A10,'Registre de reserves'!$B$2:$B$1178,'2025'!L$2,Tabla1[ANY],'2025'!$Z$2)+SUMIFS('Registre de reserves'!$U$2:$U$1178,'Registre de reserves'!$T$2:$T$1178,"RESERVA",'Registre de reserves'!$I$2:$I$1178,'2025'!$A10,'Registre de reserves'!$B$2:$B$1178,'2025'!L$2,Tabla1[ANY],'2025'!$Z$2) -> 760 | M10: =IF(L$4=0,0,L10/L$4) -> 0.22619048 | N10: =SUMIFS('Registre de reserves'!$P$2:$P$1178,'Registre de reserves'!$T$2:$T$1178,"SI",'Registre de reserves'!$I$2:$I$1178,'2025'!$A10,'Registre de reserves'!$B$2:$B$1178,'2025'!N$2,Tabla1[ANY],'2025'!$Z$2)+SUMIFS('Registre de reserves'!$U$2:$U$1178,'Registre de reserves'!$T$2:$T$1178,"RESERVA",'Registre de reserves'!$I$2:$I$1178,'2025'!$A10,'Registre de reserves'!$B$2:$B$1178,'2025'!N$2,Tabla1[ANY],'2025'!$Z$2) -> 0 | O10: =IF(N$4=0,0,N10/N$4) -> 0 | P10: =SUMIFS('Registre de reserves'!$P$2:$P$1178,'Registre de reserves'!$T$2:$T$1178,"SI",'Registre de reserves'!$I$2:$I$1178,'2025'!$A10,'Registre de reserves'!$B$2:$B$1178,'2025'!P$2,Tabla1[ANY],'2025'!$Z$2)+SUMIFS('Registre de reserves'!$U$2:$U$1178,'Registre de reserves'!$T$2:$T$1178,"RESERVA",'Registre de reserves'!$I$2:$I$1178,'2025'!$A10,'Registre de reserves'!$B$2:$B$1178,'2025'!P$2,Tabla1[ANY],'2025'!$Z$2) -> 0 | Q10: =IF(P$4=0,0,P10/P$4) -> 0 | R10: =SUMIFS('Registre de reserves'!$P$2:$P$1178,'Registre de reserves'!$T$2:$T$1178,"SI",'Registre de reserves'!$I$2:$I$1178,'2025'!$A10,'Registre de reserves'!$B$2:$B$1178,'2025'!R$2,Tabla1[ANY],'2025'!$Z$2)+SUMIFS('Registre de reserves'!$U$2:$U$1178,'Registre de reserves'!$T$2:$T$1178,"RESERVA",'Registre de reserves'!$I$2:$I$1178,'2025'!$A10,'Registre de reserves'!$B$2:$B$1178,'2025'!R$2,Tabla1[ANY],'2025'!$Z$2) -> 0 | S10: =IF(R$4=0,0,R10/R$4) -> 0 | T10: =SUMIFS('Registre de reserves'!$P$2:$P$1178,'Registre de reserves'!$T$2:$T$1178,"SI",'Registre de reserves'!$I$2:$I$1178,'2025'!$A10,'Registre de reserves'!$B$2:$B$1178,'2025'!T$2,Tabla1[ANY],'2025'!$Z$2)+SUMIFS('Registre de reserves'!$U$2:$U$1178,'Registre de reserves'!$T$2:$T$1178,"RESERVA",'Registre de reserves'!$I$2:$I$1178,'2025'!$A10,'Registre de reserves'!$B$2:$B$1178,'2025'!T$2,Tabla1[ANY],'2025'!$Z$2) -> 0 | U10: =IF(T$4=0,0,T10/T$4) -> 0 | V10: =SUMIFS('Registre de reserves'!$P$2:$P$1178,'Registre de reserves'!$T$2:$T$1178,"SI",'Registre de reserves'!$I$2:$I$1178,'2025'!$A10,'Registre de reserves'!$B$2:$B$1178,'2025'!V$2,Tabla1[ANY],'2025'!$Z$2)+SUMIFS('Registre de reserves'!$U$2:$U$1178,'Registre de reserves'!$T$2:$T$1178,"RESERVA",'Registre de reserves'!$I$2:$I$1178,'2025'!$A10,'Registre de reserves'!$B$2:$B$1178,'2025'!V$2,Tabla1[ANY],'2025'!$Z$2) -> 0 | W10: =IF(V$4=0,0,V10/V$4) -> 0 | X10: =SUMIFS('Registre de reserves'!$P$2:$P$1178,'Registre de reserves'!$T$2:$T$1178,"SI",'Registre de reserves'!$I$2:$I$1178,'2025'!$A10,'Registre de reserves'!$B$2:$B$1178,'2025'!X$2,Tabla1[ANY],'2025'!$Z$2)+SUMIFS('Registre de reserves'!$U$2:$U$1178,'Registre de reserves'!$T$2:$T$1178,"RESERVA",'Registre de reserves'!$I$2:$I$1178,'2025'!$A10,'Registre de reserves'!$B$2:$B$1178,'2025'!X$2,Tabla1[ANY],'2025'!$Z$2) -> 0 | Y10: =IF(X$4=0,0,X10/X$4) -> 0 | Z10: =B10+D10+F10+H10+J10+L10+N10+P10+R10+T10+V10+X10 -> 5960 | AA10: =IF(Z$4=0,0,Z10/Z$4) -> 0.26774483 | AB10: =Z10/$A$2 -> 993.33333
A11: Tarda+Nit | B11: =SUMIFS('Registre de reserves'!$P$2:$P$1178,'Registre de reserves'!$T$2:$T$1178,"SI",'Registre de reserves'!$I$2:$I$1178,'2025'!$A11,'Registre de reserves'!$B$2:$B$1178,'2025'!B$2,Tabla1[ANY],'2025'!$Z$2)+SUMIFS('Registre de reserves'!$U$2:$U$1178,'Registre de reserves'!$T$2:$T$1178,"RESERVA",'Registre de reserves'!$I$2:$I$1178,'2025'!$A11,'Registre de reserves'!$B$2:$B$1178,'2025'!B$2,Tabla1[ANY],'2025'!$Z$2) -> 0 | C11: =IF(B$4=0,0,B11/B$4) -> 0 | D11: =SUMIFS('Registre de reserves'!$P$2:$P$1178,'Registre de reserves'!$T$2:$T$1178,"SI",'Registre de reserves'!$I$2:$I$1178,'2025'!$A11,'Registre de reserves'!$B$2:$B$1178,'2025'!D$2,Tabla1[ANY],'2025'!$Z$2)+SUMIFS('Registre de reserves'!$U$2:$U$1178,'Registre de reserves'!$T$2:$T$1178,"RESERVA",'Registre de reserves'!$I$2:$I$1178,'2025'!$A11,'Registre de reserves'!$B$2:$B$1178,'2025'!D$2,Tabla1[ANY],'2025'!$Z$2) -> 0 | E11: =IF(D$4=0,0,D11/D$4) -> 0 | F11: =SUMIFS('Registre de reserves'!$P$2:$P$1178,'Registre de reserves'!$T$2:$T$1178,"SI",'Registre de reserves'!$I$2:$I$1178,'2025'!$A11,'Registre de reserves'!$B$2:$B$1178,'2025'!F$2,Tabla1[ANY],'2025'!$Z$2)+SUMIFS('Registre de reserves'!$U$2:$U$1178,'Registre de reserves'!$T$2:$T$1178,"RESERVA",'Registre de reserves'!$I$2:$I$1178,'2025'!$A11,'Registre de reserves'!$B$2:$B$1178,'2025'!F$2,Tabla1[ANY],'2025'!$Z$2) -> 600 | G11: =IF(F$4=0,0,F11/F$4) -> 0.1509434 | H11: =SUMIFS('Registre de reserves'!$P$2:$P$1178,'Registre de reserves'!$T$2:$T$1178,"SI",'Registre de reserves'!$I$2:$I$1178,'2025'!$A11,'Registre de reserves'!$B$2:$B$1178,'2025'!H$2,Tabla1[ANY],'2025'!$Z$2)+SUMIFS('Registre de reserves'!$U$2:$U$1178,'Registre de reserves'!$T$2:$T$1178,"RESERVA",'Registre de reserves'!$I$2:$I$1178,'2025'!$A11,'Registre de reserves'!$B$2:$B$1178,'2025'!H$2,Tabla1[ANY],'2025'!$Z$2) -> 0 | I11: =IF(H$4=0,0,H11/H$4) -> 0 | J11: =SUMIFS('Registre de reserves'!$P$2:$P$1178,'Registre de reserves'!$T$2:$T$1178,"SI",'Registre de reserves'!$I$2:$I$1178,'2025'!$A11,'Registre de reserves'!$B$2:$B$1178,'2025'!J$2,Tabla1[ANY],'2025'!$Z$2)+SUMIFS('Registre de reserves'!$U$2:$U$1178,'Registre de reserves'!$T$2:$T$1178,"RESERVA",'Registre de reserves'!$I$2:$I$1178,'2025'!$A11,'Registre de reserves'!$B$2:$B$1178,'2025'!J$2,Tabla1[ANY],'2025'!$Z$2) -> 320 | K11: =IF(J$4=0,0,J11/J$4) -> 0.086720867 | L11: =SUMIFS('Registre de reserves'!$P$2:$P$1178,'Registre de reserves'!$T$2:$T$1178,"SI",'Registre de reserves'!$I$2:$I$1178,'2025'!$A11,'Registre de reserves'!$B$2:$B$1178,'2025'!L$2,Tabla1[ANY],'2025'!$Z$2)+SUMIFS('Registre de reserves'!$U$2:$U$1178,'Registre de reserves'!$T$2:$T$1178,"RESERVA",'Registre de reserves'!$I$2:$I$1178,'2025'!$A11,'Registre de reserves'!$B$2:$B$1178,'2025'!L$2,Tabla1[ANY],'2025'!$Z$2) -> 920 | M11: =IF(L$4=0,0,L11/L$4) -> 0.27380952 | N11: =SUMIFS('Registre de reserves'!$P$2:$P$1178,'Registre de reserves'!$T$2:$T$1178,"SI",'Registre de reserves'!$I$2:$I$1178,'2025'!$A11,'Registre de reserves'!$B$2:$B$1178,'2025'!N$2,Tabla1[ANY],'2025'!$Z$2)+SUMIFS('Registre de reserves'!$U$2:$U$1178,'Registre de reserves'!$T$2:$T$1178,"RESERVA",'Registre de reserves'!$I$2:$I$1178,'2025'!$A11,'Registre de reserves'!$B$2:$B$1178,'2025'!N$2,Tabla1[ANY],'2025'!$Z$2) -> 0 | O11: =IF(N$4=0,0,N11/N$4) -> 0 | P11: =SUMIFS('Registre de reserves'!$P$2:$P$1178,'Registre de reserves'!$T$2:$T$1178,"SI",'Registre de reserves'!$I$2:$I$1178,'2025'!$A11,'Registre de reserves'!$B$2:$B$1178,'2025'!P$2,Tabla1[ANY],'2025'!$Z$2)+SUMIFS('Registre de reserves'!$U$2:$U$1178,'Registre de reserves'!$T$2:$T$1178,"RESERVA",'Registre de reserves'!$I$2:$I$1178,'2025'!$A11,'Registre de reserves'!$B$2:$B$1178,'2025'!P$2,Tabla1[ANY],'2025'!$Z$2) -> 0 | Q11: =IF(P$4=0,0,P11/P$4) -> 0 | R11: =SUMIFS('Registre de reserves'!$P$2:$P$1178,'Registre de reserves'!$T$2:$T$1178,"SI",'Registre de reserves'!$I$2:$I$1178,'2025'!$A11,'Registre de reserves'!$B$2:$B$1178,'2025'!R$2,Tabla1[ANY],'2025'!$Z$2)+SUMIFS('Registre de reserves'!$U$2:$U$1178,'Registre de reserves'!$T$2:$T$1178,"RESERVA",'Registre de reserves'!$I$2:$I$1178,'2025'!$A11,'Registre de reserves'!$B$2:$B$1178,'2025'!R$2,Tabla1[ANY],'2025'!$Z$2) -> 0 | S11: =IF(R$4=0,0,R11/R$4) -> 0 | T11: =SUMIFS('Registre de reserves'!$P$2:$P$1178,'Registre de reserves'!$T$2:$T$1178,"SI",'Registre de reserves'!$I$2:$I$1178,'2025'!$A11,'Registre de reserves'!$B$2:$B$1178,'2025'!T$2,Tabla1[ANY],'2025'!$Z$2)+SUMIFS('Registre de reserves'!$U$2:$U$1178,'Registre de reserves'!$T$2:$T$1178,"RESERVA",'Registre de reserves'!$I$2:$I$1178,'2025'!$A11,'Registre de reserves'!$B$2:$B$1178,'2025'!T$2,Tabla1[ANY],'2025'!$Z$2) -> 0 | U11: =IF(T$4=0,0,T11/T$4) -> 0 | V11: =SUMIFS('Registre de reserves'!$P$2:$P$1178,'Registre de reserves'!$T$2:$T$1178,"SI",'Registre de reserves'!$I$2:$I$1178,'2025'!$A11,'Registre de reserves'!$B$2:$B$1178,'2025'!V$2,Tabla1[ANY],'2025'!$Z$2)+SUMIFS('Registre de reserves'!$U$2:$U$1178,'Registre de reserves'!$T$2:$T$1178,"RESERVA",'Registre de reserves'!$I$2:$I$1178,'2025'!$A11,'Registre de reserves'!$B$2:$B$1178,'2025'!V$2,Tabla1[ANY],'2025'!$Z$2) -> 0 | W11: =IF(V$4=0,0,V11/V$4) -> 0 | X11: =SUMIFS('Registre de reserves'!$P$2:$P$1178,'Registre de reserves'!$T$2:$T$1178,"SI",'Registre de reserves'!$I$2:$I$1178,'2025'!$A11,'Registre de reserves'!$B$2:$B$1178,'2025'!X$2,Tabla1[ANY],'2025'!$Z$2)+SUMIFS('Registre de reserves'!$U$2:$U$1178,'Registre de reserves'!$T$2:$T$1178,"RESERVA",'Registre de reserves'!$I$2:$I$1178,'2025'!$A11,'Registre de reserves'!$B$2:$B$1178,'2025'!X$2,Tabla1[ANY],'2025'!$Z$2) -> 0 | Y11: =IF(X$4=0,0,X11/X$4) -> 0 | Z11: =B11+D11+F11+H11+J11+L11+N11+P11+R11+T11+V11+X11 -> 1840 | AA11: =IF(Z$4=0,0,Z11/Z$4) -> 0.082659479 | AB11: =Z11/$A$2 -> 306.66667
A12: Especial | B12: =SUMIFS('Registre de reserves'!$P$2:$P$1178,'Registre de reserves'!$T$2:$T$1178,"SI",'Registre de reserves'!$I$2:$I$1178,'2025'!$A12,'Registre de reserves'!$B$2:$B$1178,'2025'!B$2,Tabla1[ANY],'2025'!$Z$2)+SUMIFS('Registre de reserves'!$U$2:$U$1178,'Registre de reserves'!$T$2:$T$1178,"RESERVA",'Registre de reserves'!$I$2:$I$1178,'2025'!$A12,'Registre de reserves'!$B$2:$B$1178,'2025'!B$2,Tabla1[ANY],'2025'!$Z$2) -> 0 | C12: =IF(B$4=0,0,B12/B$4) -> 0 | D12: =SUMIFS('Registre de reserves'!$P$2:$P$1178,'Registre de reserves'!$T$2:$T$1178,"SI",'Registre de reserves'!$I$2:$I$1178,'2025'!$A12,'Registre de reserves'!$B$2:$B$1178,'2025'!D$2,Tabla1[ANY],'2025'!$Z$2)+SUMIFS('Registre de reserves'!$U$2:$U$1178,'Registre de reserves'!$T$2:$T$1178,"RESERVA",'Registre de reserves'!$I$2:$I$1178,'2025'!$A12,'Registre de reserves'!$B$2:$B$1178,'2025'!D$2,Tabla1[ANY],'2025'!$Z$2) -> 0 | E12: =IF(D$4=0,0,D12/D$4) -> 0 | F12: =SUMIFS('Registre de reserves'!$P$2:$P$1178,'Registre de reserves'!$T$2:$T$1178,"SI",'Registre de reserves'!$I$2:$I$1178,'2025'!$A12,'Registre de reserves'!$B$2:$B$1178,'2025'!F$2,Tabla1[ANY],'2025'!$Z$2)+SUMIFS('Registre de reserves'!$U$2:$U$1178,'Registre de reserves'!$T$2:$T$1178,"RESERVA",'Registre de reserves'!$I$2:$I$1178,'2025'!$A12,'Registre de reserves'!$B$2:$B$1178,'2025'!F$2,Tabla1[ANY],'2025'!$Z$2) -> 0 | G12: =IF(F$4=0,0,F12/F$4) -> 0 | H12: =SUMIFS('Registre de reserves'!$P$2:$P$1178,'Registre de reserves'!$T$2:$T$1178,"SI",'Registre de reserves'!$I$2:$I$1178,'2025'!$A12,'Registre de reserves'!$B$2:$B$1178,'2025'!H$2,Tabla1[ANY],'2025'!$Z$2)+SUMIFS('Registre de reserves'!$U$2:$U$1178,'Registre de reserves'!$T$2:$T$1178,"RESERVA",'Registre de reserves'!$I$2:$I$1178,'2025'!$A12,'Registre de reserves'!$B$2:$B$1178,'2025'!H$2,Tabla1[ANY],'2025'!$Z$2) -> 0 | I12: =IF(H$4=0,0,H12/H$4) -> 0 | J12: =SUMIFS('Registre de reserves'!$P$2:$P$1178,'Registre de reserves'!$T$2:$T$1178,"SI",'Registre de reserves'!$I$2:$I$1178,'2025'!$A12,'Registre de reserves'!$B$2:$B$1178,'2025'!J$2,Tabla1[ANY],'2025'!$Z$2)+SUMIFS('Registre de reserves'!$U$2:$U$1178,'Registre de reserves'!$T$2:$T$1178,"RESERVA",'Registre de reserves'!$I$2:$I$1178,'2025'!$A12,'Registre de reserves'!$B$2:$B$1178,'2025'!J$2,Tabla1[ANY],'2025'!$Z$2) -> 0 | K12: =IF(J$4=0,0,J12/J$4) -> 0 | L12: =SUMIFS('Registre de reserves'!$P$2:$P$1178,'Registre de reserves'!$T$2:$T$1178,"SI",'Registre de reserves'!$I$2:$I$1178,'2025'!$A12,'Registre de reserves'!$B$2:$B$1178,'2025'!L$2,Tabla1[ANY],'2025'!$Z$2)+SUMIFS('Registre de reserves'!$U$2:$U$1178,'Registre de reserves'!$T$2:$T$1178,"RESERVA",'Registre de reserves'!$I$2:$I$1178,'2025'!$A12,'Registre de reserves'!$B$2:$B$1178,'2025'!L$2,Tabla1[ANY],'2025'!$Z$2) -> 0 | M12: =IF(L$4=0,0,L12/L$4) -> 0 | N12: =SUMIFS('Registre de reserves'!$P$2:$P$1178,'Registre de reserves'!$T$2:$T$1178,"SI",'Registre de reserves'!$I$2:$I$1178,'2025'!$A12,'Registre de reserves'!$B$2:$B$1178,'2025'!N$2,Tabla1[ANY],'2025'!$Z$2)+SUMIFS('Registre de reserves'!$U$2:$U$1178,'Registre de reserves'!$T$2:$T$1178,"RESERVA",'Registre de reserves'!$I$2:$I$1178,'2025'!$A12,'Registre de reserves'!$B$2:$B$1178,'2025'!N$2,Tabla1[ANY],'2025'!$Z$2) -> 0 | O12: =IF(N$4=0,0,N12/N$4) -> 0 | P12: =SUMIFS('Registre de reserves'!$P$2:$P$1178,'Registre de reserves'!$T$2:$T$1178,"SI",'Registre de reserves'!$I$2:$I$1178,'2025'!$A12,'Registre de reserves'!$B$2:$B$1178,'2025'!P$2,Tabla1[ANY],'2025'!$Z$2)+SUMIFS('Registre de reserves'!$U$2:$U$1178,'Registre de reserves'!$T$2:$T$1178,"RESERVA",'Registre de reserves'!$I$2:$I$1178,'2025'!$A12,'Registre de reserves'!$B$2:$B$1178,'2025'!P$2,Tabla1[ANY],'2025'!$Z$2) -> 0 | Q12: =IF(P$4=0,0,P12/P$4) -> 0 | R12: =SUMIFS('Registre de reserves'!$P$2:$P$1178,'Registre de reserves'!$T$2:$T$1178,"SI",'Registre de reserves'!$I$2:$I$1178,'2025'!$A12,'Registre de reserves'!$B$2:$B$1178,'2025'!R$2,Tabla1[ANY],'2025'!$Z$2)+SUMIFS('Registre de reserves'!$U$2:$U$1178,'Registre de reserves'!$T$2:$T$1178,"RESERVA",'Registre de reserves'!$I$2:$I$1178,'2025'!$A12,'Registre de reserves'!$B$2:$B$1178,'2025'!R$2,Tabla1[ANY],'2025'!$Z$2) -> 0 | S12: =IF(R$4=0,0,R12/R$4) -> 0 | T12: =SUMIFS('Registre de reserves'!$P$2:$P$1178,'Registre de reserves'!$T$2:$T$1178,"SI",'Registre de reserves'!$I$2:$I$1178,'2025'!$A12,'Registre de reserves'!$B$2:$B$1178,'2025'!T$2,Tabla1[ANY],'2025'!$Z$2)+SUMIFS('Registre de reserves'!$U$2:$U$1178,'Registre de reserves'!$T$2:$T$1178,"RESERVA",'Registre de reserves'!$I$2:$I$1178,'2025'!$A12,'Registre de reserves'!$B$2:$B$1178,'2025'!T$2,Tabla1[ANY],'2025'!$Z$2) -> 0 | U12: =IF(T$4=0,0,T12/T$4) -> 0 | V12: =SUMIFS('Registre de reserves'!$P$2:$P$1178,'Registre de reserves'!$T$2:$T$1178,"SI",'Registre de reserves'!$I$2:$I$1178,'2025'!$A12,'Registre de reserves'!$B$2:$B$1178,'2025'!V$2,Tabla1[ANY],'2025'!$Z$2)+SUMIFS('Registre de reserves'!$U$2:$U$1178,'Registre de reserves'!$T$2:$T$1178,"RESERVA",'Registre de reserves'!$I$2:$I$1178,'2025'!$A12,'Registre de reserves'!$B$2:$B$1178,'2025'!V$2,Tabla1[ANY],'2025'!$Z$2) -> 0 | W12: =IF(V$4=0,0,V12/V$4) -> 0 | X12: =SUMIFS('Registre de reserves'!$P$2:$P$1178,'Registre de reserves'!$T$2:$T$1178,"SI",'Registre de reserves'!$I$2:$I$1178,'2025'!$A12,'Registre de reserves'!$B$2:$B$1178,'2025'!X$2,Tabla1[ANY],'2025'!$Z$2)+SUMIFS('Registre de reserves'!$U$2:$U$1178,'Registre de reserves'!$T$2:$T$1178,"RESERVA",'Registre de reserves'!$I$2:$I$1178,'2025'!$A12,'Registre de reserves'!$B$2:$B$1178,'2025'!X$2,Tabla1[ANY],'2025'!$Z$2) -> 0 | Y12: =IF(X$4=0,0,X12/X$4) -> 0 | Z12: =B12+D12+F12+H12+J12+L12+N12+P12+R12+T12+V12+X12 -> 0 | AA12: =IF(Z$4=0,0,Z12/Z$4) -> 0 | AB12: =Z12/$A$2 -> 0
A13: Reserves pendents | B13: =SUM(B14:B21) -> 0 | C13: =IF((B$13+B$31)=0,0,B13/(B$13+B$31)) -> 0 | D13: =SUM(D14:D21) -> 0 | E13: =IF((D$13+D$31)=0,0,D13/(D$13+D$31)) -> 0 | F13: =SUM(F14:F21) -> 0 | G13: =IF((F$13+F$31)=0,0,F13/(F$13+F$31)) -> 0 | H13: =SUM(H14:H21) -> 0 | I13: =IF((H$13+H$31)=0,0,H13/(H$13+H$31)) -> 0 | J13: =SUM(J14:J21) -> 0 | K13: =IF((J$13+J$31)=0,0,J13/(J$13+J$31)) -> 0 | L13: =SUM(L14:L21) -> 1375 | M13: =IF((L$13+L$31)=0,0,L13/(L$13+L$31)) -> 1 | N13: =SUM(N14:N21) -> 2835 | O13: =IF((N$13+N$31)=0,0,N13/(N$13+N$31)) -> 1 | P13: =SUM(P14:P21) -> 0 | Q13: =IF((P$13+P$31)=0,0,P13/(P$13+P$31)) -> 0 | R13: =SUM(R14:R21) -> 0 | S13: =IF((R$13+R$31)=0,0,R13/(R$13+R$31)) -> 0 | T13: =SUM(T14:T21) -> 0 | U13: =IF((T$13+T$31)=0,0,T13/(T$13+T$31)) -> 0 | V13: =SUM(V14:V21) -> 0 | W13: =IF((V$13+V$31)=0,0,V13/(V$13+V$31)) -> 0 | X13: =SUM(X14:X21) -> 600 | Y13: =IF((X$13+X$31)=0,0,X13/(X$13+X$31)) -> 1 | Z13: =SUM(Z14:Z21) -> 4810 | AA13: =IF((Z$13+Z$31)=0,0,Z13/(Z$13+Z$31)) -> 1 | AB13: =Z13/$A$2 -> 801.66667
A14: Mati | B14: =SUMIFS('Registre de reserves'!$P$2:$P$1178,'Registre de reserves'!$T$2:$T$1178,"NO",'Registre de reserves'!$I$2:$I$1178,'2025'!$A14,'Registre de reserves'!$B$2:$B$1178,'2025'!B$2,Tabla1[ANY],'2025'!$Z$2)+SUMIFS('Registre de reserves'!$P$2:$P$1178,'Registre de reserves'!$T$2:$T$1178,"RESERVA",'Registre de reserves'!$I$2:$I$1178,'2025'!$A14,'Registre de reserves'!$B$2:$B$1178,'2025'!B$2,Tabla1[ANY],'2025'!$Z$2)-SUMIFS('Registre de reserves'!$U$2:$U$1178,'Registre de reserves'!$T$2:$T$1178,"RESERVA",'Registre de reserves'!$I$2:$I$1178,'2025'!$A14,'Registre de reserves'!$B$2:$B$1178,'2025'!B$2,Tabla1[ANY],'2025'!$Z$2) -> 0 | C14: =IF($B$13=0,0,B14/B$13) -> 0 | D14: =SUMIFS('Registre de reserves'!$P$2:$P$1178,'Registre de reserves'!$T$2:$T$1178,"NO",'Registre de reserves'!$I$2:$I$1178,'2025'!$A14,'Registre de reserves'!$B$2:$B$1178,'2025'!D$2,Tabla1[ANY],'2025'!$Z$2)+SUMIFS('Registre de reserves'!$P$2:$P$1178,'Registre de reserves'!$T$2:$T$1178,"RESERVA",'Registre de reserves'!$I$2:$I$1178,'2025'!$A14,'Registre de reserves'!$B$2:$B$1178,'2025'!D$2,Tabla1[ANY],'2025'!$Z$2)-SUMIFS('Registre de reserves'!$U$2:$U$1178,'Registre de reserves'!$T$2:$T$1178,"RESERVA",'Registre de reserves'!$I$2:$I$1178,'2025'!$A14,'Registre de reserves'!$B$2:$B$1178,'2025'!D$2,Tabla1[ANY],'2025'!$Z$2) -> 0 | E14: =IF($D$13=0,0,D14/D$13) -> 0 | F14: =SUMIFS('Registre de reserves'!$P$2:$P$1178,'Registre de reserves'!$T$2:$T$1178,"NO",'Registre de reserves'!$I$2:$I$1178,'2025'!$A14,'Registre de reserves'!$B$2:$B$1178,'2025'!F$2,Tabla1[ANY],'2025'!$Z$2)+SUMIFS('Registre de reserves'!$P$2:$P$1178,'Registre de reserves'!$T$2:$T$1178,"RESERVA",'Registre de reserves'!$I$2:$I$1178,'2025'!$A14,'Registre de reserves'!$B$2:$B$1178,'2025'!F$2,Tabla1[ANY],'2025'!$Z$2)-SUMIFS('Registre de reserves'!$U$2:$U$1178,'Registre de reserves'!$T$2:$T$1178,"RESERVA",'Registre de reserves'!$I$2:$I$1178,'2025'!$A14,'Registre de reserves'!$B$2:$B$1178,'2025'!F$2,Tabla1[ANY],'2025'!$Z$2) -> 0 | G14: =IF($F$13=0,0,F14/F$13) -> 0 | H14: =SUMIFS('Registre de reserves'!$P$2:$P$1178,'Registre de reserves'!$T$2:$T$1178,"NO",'Registre de reserves'!$I$2:$I$1178,'2025'!$A14,'Registre de reserves'!$B$2:$B$1178,'2025'!H$2,Tabla1[ANY],'2025'!$Z$2)+SUMIFS('Registre de reserves'!$P$2:$P$1178,'Registre de reserves'!$T$2:$T$1178,"RESERVA",'Registre de reserves'!$I$2:$I$1178,'2025'!$A14,'Registre de reserves'!$B$2:$B$1178,'2025'!H$2,Tabla1[ANY],'2025'!$Z$2)-SUMIFS('Registre de reserves'!$U$2:$U$1178,'Registre de reserves'!$T$2:$T$1178,"RESERVA",'Registre de reserves'!$I$2:$I$1178,'2025'!$A14,'Registre de reserves'!$B$2:$B$1178,'2025'!H$2,Tabla1[ANY],'2025'!$Z$2) -> 0 | I14: =IF($H$13=0,0,H14/H$13) -> 0 | J14: =SUMIFS('Registre de reserves'!$P$2:$P$1178,'Registre de reserves'!$T$2:$T$1178,"NO",'Registre de reserves'!$I$2:$I$1178,'2025'!$A14,'Registre de reserves'!$B$2:$B$1178,'2025'!J$2,Tabla1[ANY],'2025'!$Z$2)+SUMIFS('Registre de reserves'!$P$2:$P$1178,'Registre de reserves'!$T$2:$T$1178,"RESERVA",'Registre de reserves'!$I$2:$I$1178,'2025'!$A14,'Registre de reserves'!$B$2:$B$1178,'2025'!J$2,Tabla1[ANY],'2025'!$Z$2)-SUMIFS('Registre de reserves'!$U$2:$U$1178,'Registre de reserves'!$T$2:$T$1178,"RESERVA",'Registre de reserves'!$I$2:$I$1178,'2025'!$A14,'Registre de reserves'!$B$2:$B$1178,'2025'!J$2,Tabla1[ANY],'2025'!$Z$2) -> 0 | K14: =IF($J$13=0,0,J14/J$13) -> 0 | L14: =SUMIFS('Registre de reserves'!$P$2:$P$1178,'Registre de reserves'!$T$2:$T$1178,"NO",'Registre de reserves'!$I$2:$I$1178,'2025'!$A14,'Registre de reserves'!$B$2:$B$1178,'2025'!L$2,Tabla1[ANY],'2025'!$Z$2)+SUMIFS('Registre de reserves'!$P$2:$P$1178,'Registre de reserves'!$T$2:$T$1178,"RESERVA",'Registre de reserves'!$I$2:$I$1178,'2025'!$A14,'Registre de reserves'!$B$2:$B$1178,'2025'!L$2,Tabla1[ANY],'2025'!$Z$2)-SUMIFS('Registre de reserves'!$U$2:$U$1178,'Registre de reserves'!$T$2:$T$1178,"RESERVA",'Registre de reserves'!$I$2:$I$1178,'2025'!$A14,'Registre de reserves'!$B$2:$B$1178,'2025'!L$2,Tabla1[ANY],'2025'!$Z$2) -> 150 | M14: =IF($L$13=0,0,L14/L$13) -> 0.10909091 | N14: =SUMIFS('Registre de reserves'!$P$2:$P$1178,'Registre de reserves'!$T$2:$T$1178,"NO",'Registre de reserves'!$I$2:$I$1178,'2025'!$A14,'Registre de reserves'!$B$2:$B$1178,'2025'!N$2,Tabla1[ANY],'2025'!$Z$2)+SUMIFS('Registre de reserves'!$P$2:$P$1178,'Registre de reserves'!$T$2:$T$1178,"RESERVA",'Registre de reserves'!$I$2:$I$1178,'2025'!$A14,'Registre de reserves'!$B$2:$B$1178,'2025'!N$2,Tabla1[ANY],'2025'!$Z$2)-SUMIFS('Registre de reserves'!$U$2:$U$1178,'Registre de reserves'!$T$2:$T$1178,"RESERVA",'Registre de reserves'!$I$2:$I$1178,'2025'!$A14,'Registre de reserves'!$B$2:$B$1178,'2025'!N$2,Tabla1[ANY],'2025'!$Z$2) -> 150 | O14: =IF($N$13=0,0,N14/N$13) -> 0.052910053 | P14: =SUMIFS('Registre de reserves'!$P$2:$P$1178,'Registre de reserves'!$T$2:$T$1178,"NO",'Registre de reserves'!$I$2:$I$1178,'2025'!$A14,'Registre de reserves'!$B$2:$B$1178,'2025'!P$2,Tabla1[ANY],'2025'!$Z$2)+SUMIFS('Registre de reserves'!$P$2:$P$1178,'Registre de reserves'!$T$2:$T$1178,"RESERVA",'Registre de reserves'!$I$2:$I$1178,'2025'!$A14,'Registre de reserves'!$B$2:$B$1178,'2025'!P$2,Tabla1[ANY],'2025'!$Z$2)-SUMIFS('Registre de reserves'!$U$2:$U$1178,'Registre de reserves'!$T$2:$T$1178,"RESERVA",'Registre de reserves'!$I$2:$I$1178,'2025'!$A14,'Registre de reserves'!$B$2:$B$1178,'2025'!P$2,Tabla1[ANY],'2025'!$Z$2) -> 0 | Q14: =IF($P$13=0,0,P14/P$13) -> 0 | R14: =SUMIFS('Registre de reserves'!$P$2:$P$1178,'Registre de reserves'!$T$2:$T$1178,"NO",'Registre de reserves'!$I$2:$I$1178,'2025'!$A14,'Registre de reserves'!$B$2:$B$1178,'2025'!R$2,Tabla1[ANY],'2025'!$Z$2)+SUMIFS('Registre de reserves'!$P$2:$P$1178,'Registre de reserves'!$T$2:$T$1178,"RESERVA",'Registre de reserves'!$I$2:$I$1178,'2025'!$A14,'Registre de reserves'!$B$2:$B$1178,'2025'!R$2,Tabla1[ANY],'2025'!$Z$2)-SUMIFS('Registre de reserves'!$U$2:$U$1178,'Registre de reserves'!$T$2:$T$1178,"RESERVA",'Registre de reserves'!$I$2:$I$1178,'2025'!$A14,'Registre de reserves'!$B$2:$B$1178,'2025'!R$2,Tabla1[ANY],'2025'!$Z$2) -> 0 | S14: =IF($R$13=0,0,R14/R$13) -> 0 | T14: =SUMIFS('Registre de reserves'!$P$2:$P$1178,'Registre de reserves'!$T$2:$T$1178,"NO",'Registre de reserves'!$I$2:$I$1178,'2025'!$A14,'Registre de reserves'!$B$2:$B$1178,'2025'!T$2,Tabla1[ANY],'2025'!$Z$2)+SUMIFS('Registre de reserves'!$P$2:$P$1178,'Registre de reserves'!$T$2:$T$1178,"RESERVA",'Registre de reserves'!$I$2:$I$1178,'2025'!$A14,'Registre de reserves'!$B$2:$B$1178,'2025'!T$2,Tabla1[ANY],'2025'!$Z$2)-SUMIFS('Registre de reserves'!$U$2:$U$1178,'Registre de reserves'!$T$2:$T$1178,"RESERVA",'Registre de reserves'!$I$2:$I$1178,'2025'!$A14,'Registre de reserves'!$B$2:$B$1178,'2025'!T$2,Tabla1[ANY],'2025'!$Z$2) -> 0 | U14: =IF($T$13=0,0,T14/T$13) -> 0 | V14: =SUMIFS('Registre de reserves'!$P$2:$P$1178,'Registre de reserves'!$T$2:$T$1178,"NO",'Registre de reserves'!$I$2:$I$1178,'2025'!$A14,'Registre de reserves'!$B$2:$B$1178,'2025'!V$2,Tabla1[ANY],'2025'!$Z$2)+SUMIFS('Registre de reserves'!$P$2:$P$1178,'Registre de reserves'!$T$2:$T$1178,"RESERVA",'Registre de reserves'!$I$2:$I$1178,'2025'!$A14,'Registre de reserves'!$B$2:$B$1178,'2025'!V$2,Tabla1[ANY],'2025'!$Z$2)-SUMIFS('Registre de reserves'!$U$2:$U$1178,'Registre de reserves'!$T$2:$T$1178,"RESERVA",'Registre de reserves'!$I$2:$I$1178,'2025'!$A14,'Registre de reserves'!$B$2:$B$1178,'2025'!V$2,Tabla1[ANY],'2025'!$Z$2) -> 0 | W14: =IF($V$13=0,0,V14/V$13) -> 0 | X14: =SUMIFS('Registre de reserves'!$P$2:$P$1178,'Registre de reserves'!$T$2:$T$1178,"NO",'Registre de reserves'!$I$2:$I$1178,'2025'!$A14,'Registre de reserves'!$B$2:$B$1178,'2025'!X$2,Tabla1[ANY],'2025'!$Z$2)+SUMIFS('Registre de reserves'!$P$2:$P$1178,'Registre de reserves'!$T$2:$T$1178,"RESERVA",'Registre de reserves'!$I$2:$I$1178,'2025'!$A14,'Registre de reserves'!$B$2:$B$1178,'2025'!X$2,Tabla1[ANY],'2025'!$Z$2)-SUMIFS('Registre de reserves'!$U$2:$U$1178,'Registre de reserves'!$T$2:$T$1178,"RESERVA",'Registre de reserves'!$I$2:$I$1178,'2025'!$A14,'Registre de reserves'!$B$2:$B$1178,'2025'!X$2,Tabla1[ANY],'2025'!$Z$2) -> 0 | Y14: =IF($X$13=0,0,X14/X$13) -> 0 | Z14: =B14+D14+F14+H14+J14+L14+N14+P14+R14+T14+V14+X14 -> 300 | AA14: =IF($Z$13=0,0,Z14/Z$13) -> 0.062370062 | AB14: =Z14/$A$2 -> 50
A15: Tarda | B15: =SUMIFS('Registre de reserves'!$P$2:$P$1178,'Registre de reserves'!$T$2:$T$1178,"NO",'Registre de reserves'!$I$2:$I$1178,'2025'!$A15,'Registre de reserves'!$B$2:$B$1178,'2025'!B$2,Tabla1[ANY],'2025'!$Z$2)+SUMIFS('Registre de reserves'!$P$2:$P$1178,'Registre de reserves'!$T$2:$T$1178,"RESERVA",'Registre de reserves'!$I$2:$I$1178,'2025'!$A15,'Registre de reserves'!$B$2:$B$1178,'2025'!B$2,Tabla1[ANY],'2025'!$Z$2)-SUMIFS('Registre de reserves'!$U$2:$U$1178,'Registre de reserves'!$T$2:$T$1178,"RESERVA",'Registre de reserves'!$I$2:$I$1178,'2025'!$A15,'Registre de reserves'!$B$2:$B$1178,'2025'!B$2,Tabla1[ANY],'2025'!$Z$2) -> 0 | C15: =IF($B$13=0,0,B15/B$13) -> 0 | D15: =SUMIFS('Registre de reserves'!$P$2:$P$1178,'Registre de reserves'!$T$2:$T$1178,"NO",'Registre de reserves'!$I$2:$I$1178,'2025'!$A15,'Registre de reserves'!$B$2:$B$1178,'2025'!D$2,Tabla1[ANY],'2025'!$Z$2)+SUMIFS('Registre de reserves'!$P$2:$P$1178,'Registre de reserves'!$T$2:$T$1178,"RESERVA",'Registre de reserves'!$I$2:$I$1178,'2025'!$A15,'Registre de reserves'!$B$2:$B$1178,'2025'!D$2,Tabla1[ANY],'2025'!$Z$2)-SUMIFS('Registre de reserves'!$U$2:$U$1178,'Registre de reserves'!$T$2:$T$1178,"RESERVA",'Registre de reserves'!$I$2:$I$1178,'2025'!$A15,'Registre de reserves'!$B$2:$B$1178,'2025'!D$2,Tabla1[ANY],'2025'!$Z$2) -> 0 | E15: =IF($D$13=0,0,D15/D$13) -> 0 | F15: =SUMIFS('Registre de reserves'!$P$2:$P$1178,'Registre de reserves'!$T$2:$T$1178,"NO",'Registre de reserves'!$I$2:$I$1178,'2025'!$A15,'Registre de reserves'!$B$2:$B$1178,'2025'!F$2,Tabla1[ANY],'2025'!$Z$2)+SUMIFS('Registre de reserves'!$P$2:$P$1178,'Registre de reserves'!$T$2:$T$1178,"RESERVA",'Registre de reserves'!$I$2:$I$1178,'2025'!$A15,'Registre de reserves'!$B$2:$B$1178,'2025'!F$2,Tabla1[ANY],'2025'!$Z$2)-SUMIFS('Registre de reserves'!$U$2:$U$1178,'Registre de reserves'!$T$2:$T$1178,"RESERVA",'Registre de reserves'!$I$2:$I$1178,'2025'!$A15,'Registre de reserves'!$B$2:$B$1178,'2025'!F$2,Tabla1[ANY],'2025'!$Z$2) -> 0 | G15: =IF($F$13=0,0,F15/F$13) -> 0 | H15: =SUMIFS('Registre de reserves'!$P$2:$P$1178,'Registre de reserves'!$T$2:$T$1178,"NO",'Registre de reserves'!$I$2:$I$1178,'2025'!$A15,'Registre de reserves'!$B$2:$B$1178,'2025'!H$2,Tabla1[ANY],'2025'!$Z$2)+SUMIFS('Registre de reserves'!$P$2:$P$1178,'Registre de reserves'!$T$2:$T$1178,"RESERVA",'Registre de reserves'!$I$2:$I$1178,'2025'!$A15,'Registre de reserves'!$B$2:$B$1178,'2025'!H$2,Tabla1[ANY],'2025'!$Z$2)-SUMIFS('Registre de reserves'!$U$2:$U$1178,'Registre de reserves'!$T$2:$T$1178,"RESERVA",'Registre de reserves'!$I$2:$I$1178,'2025'!$A15,'Registre de reserves'!$B$2:$B$1178,'2025'!H$2,Tabla1[ANY],'2025'!$Z$2) -> 0 | I15: =IF($H$13=0,0,H15/H$13) -> 0 | J15: =SUMIFS('Registre de reserves'!$P$2:$P$1178,'Registre de reserves'!$T$2:$T$1178,"NO",'Registre de reserves'!$I$2:$I$1178,'2025'!$A15,'Registre de reserves'!$B$2:$B$1178,'2025'!J$2,Tabla1[ANY],'2025'!$Z$2)+SUMIFS('Registre de reserves'!$P$2:$P$1178,'Registre de reserves'!$T$2:$T$1178,"RESERVA",'Registre de reserves'!$I$2:$I$1178,'2025'!$A15,'Registre de reserves'!$B$2:$B$1178,'2025'!J$2,Tabla1[ANY],'2025'!$Z$2)-SUMIFS('Registre de reserves'!$U$2:$U$1178,'Registre de reserves'!$T$2:$T$1178,"RESERVA",'Registre de reserves'!$I$2:$I$1178,'2025'!$A15,'Registre de reserves'!$B$2:$B$1178,'2025'!J$2,Tabla1[ANY],'2025'!$Z$2) -> 0 | K15: =IF($J$13=0,0,J15/J$13) -> 0 | L15: =SUMIFS('Registre de reserves'!$P$2:$P$1178,'Registre de reserves'!$T$2:$T$1178,"NO",'Registre de reserves'!$I$2:$I$1178,'2025'!$A15,'Registre de reserves'!$B$2:$B$1178,'2025'!L$2,Tabla1[ANY],'2025'!$Z$2)+SUMIFS('Registre de reserves'!$P$2:$P$1178,'Registre de reserves'!$T$2:$T$1178,"RESERVA",'Registre de reserves'!$I$2:$I$1178,'2025'!$A15,'Registre de reserves'!$B$2:$B$1178,'2025'!L$2,Tabla1[ANY],'2025'!$Z$2)-SUMIFS('Registre de reserves'!$U$2:$U$1178,'Registre de reserves'!$T$2:$T$1178,"RESERVA",'Registre de reserves'!$I$2:$I$1178,'2025'!$A15,'Registre de reserves'!$B$2:$B$1178,'2025'!L$2,Tabla1[ANY],'2025'!$Z$2) -> 675 | M15: =IF($L$13=0,0,L15/L$13) -> 0.49090909 | N15: =SUMIFS('Registre de reserves'!$P$2:$P$1178,'Registre de reserves'!$T$2:$T$1178,"NO",'Registre de reserves'!$I$2:$I$1178,'2025'!$A15,'Registre de reserves'!$B$2:$B$1178,'2025'!N$2,Tabla1[ANY],'2025'!$Z$2)+SUMIFS('Registre de reserves'!$P$2:$P$1178,'Registre de reserves'!$T$2:$T$1178,"RESERVA",'Registre de reserves'!$I$2:$I$1178,'2025'!$A15,'Registre de reserves'!$B$2:$B$1178,'2025'!N$2,Tabla1[ANY],'2025'!$Z$2)-SUMIFS('Registre de reserves'!$U$2:$U$1178,'Registre de reserves'!$T$2:$T$1178,"RESERVA",'Registre de reserves'!$I$2:$I$1178,'2025'!$A15,'Registre de reserves'!$B$2:$B$1178,'2025'!N$2,Tabla1[ANY],'2025'!$Z$2) -> 975 | O15: =IF($N$13=0,0,N15/N$13) -> 0.34391534 | P15: =SUMIFS('Registre de reserves'!$P$2:$P$1178,'Registre de reserves'!$T$2:$T$1178,"NO",'Registre de reserves'!$I$2:$I$1178,'2025'!$A15,'Registre de reserves'!$B$2:$B$1178,'2025'!P$2,Tabla1[ANY],'2025'!$Z$2)+SUMIFS('Registre de reserves'!$P$2:$P$1178,'Registre de reserves'!$T$2:$T$1178,"RESERVA",'Registre de reserves'!$I$2:$I$1178,'2025'!$A15,'Registre de reserves'!$B$2:$B$1178,'2025'!P$2,Tabla1[ANY],'2025'!$Z$2)-SUMIFS('Registre de reserves'!$U$2:$U$1178,'Registre de reserves'!$T$2:$T$1178,"RESERVA",'Registre de reserves'!$I$2:$I$1178,'2025'!$A15,'Registre de reserves'!$B$2:$B$1178,'2025'!P$2,Tabla1[ANY],'2025'!$Z$2) -> 0 | Q15: =IF($P$13=0,0,P15/P$13) -> 0 | R15: =SUMIFS('Registre de reserves'!$P$2:$P$1178,'Registre de reserves'!$T$2:$T$1178,"NO",'Registre de reserves'!$I$2:$I$1178,'2025'!$A15,'Registre de reserves'!$B$2:$B$1178,'2025'!R$2,Tabla1[ANY],'2025'!$Z$2)+SUMIFS('Registre de reserves'!$P$2:$P$1178,'Registre de reserves'!$T$2:$T$1178,"RESERVA",'Registre de reserves'!$I$2:$I$1178,'2025'!$A15,'Registre de reserves'!$B$2:$B$1178,'2025'!R$2,Tabla1[ANY],'2025'!$Z$2)-SUMIFS('Registre de reserves'!$U$2:$U$1178,'Registre de reserves'!$T$2:$T$1178,"RESERVA",'Registre de reserves'!$I$2:$I$1178,'2025'!$A15,'Registre de reserves'!$B$2:$B$1178,'2025'!R$2,Tabla1[ANY],'2025'!$Z$2) -> 0 | S15: =IF($R$13=0,0,R15/R$13) -> 0 | T15: =SUMIFS('Registre de reserves'!$P$2:$P$1178,'Registre de reserves'!$T$2:$T$1178,"NO",'Registre de reserves'!$I$2:$I$1178,'2025'!$A15,'Registre de reserves'!$B$2:$B$1178,'2025'!T$2,Tabla1[ANY],'2025'!$Z$2)+SUMIFS('Registre de reserves'!$P$2:$P$1178,'Registre de reserves'!$T$2:$T$1178,"RESERVA",'Registre de reserves'!$I$2:$I$1178,'2025'!$A15,'Registre de reserves'!$B$2:$B$1178,'2025'!T$2,Tabla1[ANY],'2025'!$Z$2)-SUMIFS('Registre de reserves'!$U$2:$U$1178,'Registre de reserves'!$T$2:$T$1178,"RESERVA",'Registre de reserves'!$I$2:$I$1178,'2025'!$A15,'Registre de reserves'!$B$2:$B$1178,'2025'!T$2,Tabla1[ANY],'2025'!$Z$2) -> 0 | U15: =IF($T$13=0,0,T15/T$13) -> 0 | V15: =SUMIFS('Registre de reserves'!$P$2:$P$1178,'Registre de reserves'!$T$2:$T$1178,"NO",'Registre de reserves'!$I$2:$I$1178,'2025'!$A15,'Registre de reserves'!$B$2:$B$1178,'2025'!V$2,Tabla1[ANY],'2025'!$Z$2)+SUMIFS('Registre de reserves'!$P$2:$P$1178,'Registre de reserves'!$T$2:$T$1178,"RESERVA",'Registre de reserves'!$I$2:$I$1178,'2025'!$A15,'Registre de reserves'!$B$2:$B$1178,'2025'!V$2,Tabla1[ANY],'2025'!$Z$2)-SUMIFS('Registre de reserves'!$U$2:$U$1178,'Registre de reserves'!$T$2:$T$1178,"RESERVA",'Registre de reserves'!$I$2:$I$1178,'2025'!$A15,'Registre de reserves'!$B$2:$B$1178,'2025'!V$2,Tabla1[ANY],'2025'!$Z$2) -> 0 | W15: =IF($V$13=0,0,V15/V$13) -> 0 | X15: =SUMIFS('Registre de reserves'!$P$2:$P$1178,'Registre de reserves'!$T$2:$T$1178,"NO",'Registre de reserves'!$I$2:$I$1178,'2025'!$A15,'Registre de reserves'!$B$2:$B$1178,'2025'!X$2,Tabla1[ANY],'2025'!$Z$2)+SUMIFS('Registre de reserves'!$P$2:$P$1178,'Registre de reserves'!$T$2:$T$1178,"RESERVA",'Registre de reserves'!$I$2:$I$1178,'2025'!$A15,'Registre de reserves'!$B$2:$B$1178,'2025'!X$2,Tabla1[ANY],'2025'!$Z$2)-SUMIFS('Registre de reserves'!$U$2:$U$1178,'Registre de reserves'!$T$2:$T$1178,"RESERVA",'Registre de reserves'!$I$2:$I$1178,'2025'!$A15,'Registre de reserves'!$B$2:$B$1178,'2025'!X$2,Tabla1[ANY],'2025'!$Z$2) -> 0 | Y15: =IF($X$13=0,0,X15/X$13) -> 0 | Z15: =B15+D15+F15+H15+J15+L15+N15+P15+R15+T15+V15+X15 -> 1650 | AA15: =IF($Z$13=0,0,Z15/Z$13) -> 0.34303534 | AB15: =Z15/$A$2 -> 275
A16: Dia sencer | B16: =SUMIFS('Registre de reserves'!$P$2:$P$1178,'Registre de reserves'!$T$2:$T$1178,"NO",'Registre de reserves'!$I$2:$I$1178,'2025'!$A16,'Registre de reserves'!$B$2:$B$1178,'2025'!B$2,Tabla1[ANY],'2025'!$Z$2)+SUMIFS('Registre de reserves'!$P$2:$P$1178,'Registre de reserves'!$T$2:$T$1178,"RESERVA",'Registre de reserves'!$I$2:$I$1178,'2025'!$A16,'Registre de reserves'!$B$2:$B$1178,'2025'!B$2,Tabla1[ANY],'2025'!$Z$2)-SUMIFS('Registre de reserves'!$U$2:$U$1178,'Registre de reserves'!$T$2:$T$1178,"RESERVA",'Registre de reserves'!$I$2:$I$1178,'2025'!$A16,'Registre de reserves'!$B$2:$B$1178,'2025'!B$2,Tabla1[ANY],'2025'!$Z$2) -> 0 | C16: =IF($B$13=0,0,B16/B$13) -> 0 | D16: =SUMIFS('Registre de reserves'!$P$2:$P$1178,'Registre de reserves'!$T$2:$T$1178,"NO",'Registre de reserves'!$I$2:$I$1178,'2025'!$A16,'Registre de reserves'!$B$2:$B$1178,'2025'!D$2,Tabla1[ANY],'2025'!$Z$2)+SUMIFS('Registre de reserves'!$P$2:$P$1178,'Registre de reserves'!$T$2:$T$1178,"RESERVA",'Registre de reserves'!$I$2:$I$1178,'2025'!$A16,'Registre de reserves'!$B$2:$B$1178,'2025'!D$2,Tabla1[ANY],'2025'!$Z$2)-SUMIFS('Registre de reserves'!$U$2:$U$1178,'Registre de reserves'!$T$2:$T$1178,"RESERVA",'Registre de reserves'!$I$2:$I$1178,'2025'!$A16,'Registre de reserves'!$B$2:$B$1178,'2025'!D$2,Tabla1[ANY],'2025'!$Z$2) -> 0 | E16: =IF($D$13=0,0,D16/D$13) -> 0 | F16: =SUMIFS('Registre de reserves'!$P$2:$P$1178,'Registre de reserves'!$T$2:$T$1178,"NO",'Registre de reserves'!$I$2:$I$1178,'2025'!$A16,'Registre de reserves'!$B$2:$B$1178,'2025'!F$2,Tabla1[ANY],'2025'!$Z$2)+SUMIFS('Registre de reserves'!$P$2:$P$1178,'Registre de reserves'!$T$2:$T$1178,"RESERVA",'Registre de reserves'!$I$2:$I$1178,'2025'!$A16,'Registre de reserves'!$B$2:$B$1178,'2025'!F$2,Tabla1[ANY],'2025'!$Z$2)-SUMIFS('Registre de reserves'!$U$2:$U$1178,'Registre de reserves'!$T$2:$T$1178,"RESERVA",'Registre de reserves'!$I$2:$I$1178,'2025'!$A16,'Registre de reserves'!$B$2:$B$1178,'2025'!F$2,Tabla1[ANY],'2025'!$Z$2) -> 0 | G16: =IF($F$13=0,0,F16/F$13) -> 0 | H16: =SUMIFS('Registre de reserves'!$P$2:$P$1178,'Registre de reserves'!$T$2:$T$1178,"NO",'Registre de reserves'!$I$2:$I$1178,'2025'!$A16,'Registre de reserves'!$B$2:$B$1178,'2025'!H$2,Tabla1[ANY],'2025'!$Z$2)+SUMIFS('Registre de reserves'!$P$2:$P$1178,'Registre de reserves'!$T$2:$T$1178,"RESERVA",'Registre de reserves'!$I$2:$I$1178,'2025'!$A16,'Registre de reserves'!$B$2:$B$1178,'2025'!H$2,Tabla1[ANY],'2025'!$Z$2)-SUMIFS('Registre de reserves'!$U$2:$U$1178,'Registre de reserves'!$T$2:$T$1178,"RESERVA",'Registre de reserves'!$I$2:$I$1178,'2025'!$A16,'Registre de reserves'!$B$2:$B$1178,'2025'!H$2,Tabla1[ANY],'2025'!$Z$2) -> 0 | I16: =IF($H$13=0,0,H16/H$13) -> 0 | J16: =SUMIFS('Registre de reserves'!$P$2:$P$1178,'Registre de reserves'!$T$2:$T$1178,"NO",'Registre de reserves'!$I$2:$I$1178,'2025'!$A16,'Registre de reserves'!$B$2:$B$1178,'2025'!J$2,Tabla1[ANY],'2025'!$Z$2)+SUMIFS('Registre de reserves'!$P$2:$P$1178,'Registre de reserves'!$T$2:$T$1178,"RESERVA",'Registre de reserves'!$I$2:$I$1178,'2025'!$A16,'Registre de reserves'!$B$2:$B$1178,'2025'!J$2,Tabla1[ANY],'2025'!$Z$2)-SUMIFS('Registre de reserves'!$U$2:$U$1178,'Registre de reserves'!$T$2:$T$1178,"RESERVA",'Registre de reserves'!$I$2:$I$1178,'2025'!$A16,'Registre de reserves'!$B$2:$B$1178,'2025'!J$2,Tabla1[ANY],'2025'!$Z$2) -> 0 | K16: =IF($J$13=0,0,J16/J$13) -> 0 | L16: =SUMIFS('Registre de reserves'!$P$2:$P$1178,'Registre de reserves'!$T$2:$T$1178,"NO",'Registre de reserves'!$I$2:$I$1178,'2025'!$A16,'Registre de reserves'!$B$2:$B$1178,'2025'!L$2,Tabla1[ANY],'2025'!$Z$2)+SUMIFS('Registre de reserves'!$P$2:$P$1178,'Registre de reserves'!$T$2:$T$1178,"RESERVA",'Registre de reserves'!$I$2:$I$1178,'2025'!$A16,'Registre de reserves'!$B$2:$B$1178,'2025'!L$2,Tabla1[ANY],'2025'!$Z$2)-SUMIFS('Registre de reserves'!$U$2:$U$1178,'Registre de reserves'!$T$2:$T$1178,"RESERVA",'Registre de reserves'!$I$2:$I$1178,'2025'!$A16,'Registre de reserves'!$B$2:$B$1178,'2025'!L$2,Tabla1[ANY],'2025'!$Z$2) -> 0 | M16: =IF($L$13=0,0,L16/L$13) -> 0 | N16: =SUMIFS('Registre de reserves'!$P$2:$P$1178,'Registre de reserves'!$T$2:$T$1178,"NO",'Registre de reserves'!$I$2:$I$1178,'2025'!$A16,'Registre de reserves'!$B$2:$B$1178,'2025'!N$2,Tabla1[ANY],'2025'!$Z$2)+SUMIFS('Registre de reserves'!$P$2:$P$1178,'Registre de reserves'!$T$2:$T$1178,"RESERVA",'Registre de reserves'!$I$2:$I$1178,'2025'!$A16,'Registre de reserves'!$B$2:$B$1178,'2025'!N$2,Tabla1[ANY],'2025'!$Z$2)-SUMIFS('Registre de reserves'!$U$2:$U$1178,'Registre de reserves'!$T$2:$T$1178,"RESERVA",'Registre de reserves'!$I$2:$I$1178,'2025'!$A16,'Registre de reserves'!$B$2:$B$1178,'2025'!N$2,Tabla1[ANY],'2025'!$Z$2) -> 290 | O16: =IF($N$13=0,0,N16/N$13) -> 0.10229277 | P16: =SUMIFS('Registre de reserves'!$P$2:$P$1178,'Registre de reserves'!$T$2:$T$1178,"NO",'Registre de reserves'!$I$2:$I$1178,'2025'!$A16,'Registre de reserves'!$B$2:$B$1178,'2025'!P$2,Tabla1[ANY],'2025'!$Z$2)+SUMIFS('Registre de reserves'!$P$2:$P$1178,'Registre de reserves'!$T$2:$T$1178,"RESERVA",'Registre de reserves'!$I$2:$I$1178,'2025'!$A16,'Registre de reserves'!$B$2:$B$1178,'2025'!P$2,Tabla1[ANY],'2025'!$Z$2)-SUMIFS('Registre de reserves'!$U$2:$U$1178,'Registre de reserves'!$T$2:$T$1178,"RESERVA",'Registre de reserves'!$I$2:$I$1178,'2025'!$A16,'Registre de reserves'!$B$2:$B$1178,'2025'!P$2,Tabla1[ANY],'2025'!$Z$2) -> 0 | Q16: =IF($P$13=0,0,P16/P$13) -> 0 | R16: =SUMIFS('Registre de reserves'!$P$2:$P$1178,'Registre de reserves'!$T$2:$T$1178,"NO",'Registre de reserves'!$I$2:$I$1178,'2025'!$A16,'Registre de reserves'!$B$2:$B$1178,'2025'!R$2,Tabla1[ANY],'2025'!$Z$2)+SUMIFS('Registre de reserves'!$P$2:$P$1178,'Registre de reserves'!$T$2:$T$1178,"RESERVA",'Registre de reserves'!$I$2:$I$1178,'2025'!$A16,'Registre de reserves'!$B$2:$B$1178,'2025'!R$2,Tabla1[ANY],'2025'!$Z$2)-SUMIFS('Registre de reserves'!$U$2:$U$1178,'Registre de reserves'!$T$2:$T$1178,"RESERVA",'Registre de reserves'!$I$2:$I$1178,'2025'!$A16,'Registre de reserves'!$B$2:$B$1178,'2025'!R$2,Tabla1[ANY],'2025'!$Z$2) -> 0 | S16: =IF($R$13=0,0,R16/R$13) -> 0 | T16: =SUMIFS('Registre de reserves'!$P$2:$P$1178,'Registre de reserves'!$T$2:$T$1178,"NO",'Registre de reserves'!$I$2:$I$1178,'2025'!$A16,'Registre de reserves'!$B$2:$B$1178,'2025'!T$2,Tabla1[ANY],'2025'!$Z$2)+SUMIFS('Registre de reserves'!$P$2:$P$1178,'Registre de reserves'!$T$2:$T$1178,"RESERVA",'Registre de reserves'!$I$2:$I$1178,'2025'!$A16,'Registre de reserves'!$B$2:$B$1178,'2025'!T$2,Tabla1[ANY],'2025'!$Z$2)-SUMIFS('Registre de reserves'!$U$2:$U$1178,'Registre de reserves'!$T$2:$T$1178,"RESERVA",'Registre de reserves'!$I$2:$I$1178,'2025'!$A16,'Registre de reserves'!$B$2:$B$1178,'2025'!T$2,Tabla1[ANY],'2025'!$Z$2) -> 0 | U16: =IF($T$13=0,0,T16/T$13) -> 0 | V16: =SUMIFS('Registre de reserves'!$P$2:$P$1178,'Registre de reserves'!$T$2:$T$1178,"NO",'Registre de reserves'!$I$2:$I$1178,'2025'!$A16,'Registre de reserves'!$B$2:$B$1178,'2025'!V$2,Tabla1[ANY],'2025'!$Z$2)+SUMIFS('Registre de reserves'!$P$2:$P$1178,'Registre de reserves'!$T$2:$T$1178,"RESERVA",'Registre de reserves'!$I$2:$I$1178,'2025'!$A16,'Registre de reserves'!$B$2:$B$1178,'2025'!V$2,Tabla1[ANY],'2025'!$Z$2)-SUMIFS('Registre de reserves'!$U$2:$U$1178,'Registre de reserves'!$T$2:$T$1178,"RESERVA",'Registre de reserves'!$I$2:$I$1178,'2025'!$A16,'Registre de reserves'!$B$2:$B$1178,'2025'!V$2,Tabla1[ANY],'2025'!$Z$2) -> 0 | W16: =IF($V$13=0,0,V16/V$13) -> 0 | X16: =SUMIFS('Registre de reserves'!$P$2:$P$1178,'Registre de reserves'!$T$2:$T$1178,"NO",'Registre de reserves'!$I$2:$I$1178,'2025'!$A16,'Registre de reserves'!$B$2:$B$1178,'2025'!X$2,Tabla1[ANY],'2025'!$Z$2)+SUMIFS('Registre de reserves'!$P$2:$P$1178,'Registre de reserves'!$T$2:$T$1178,"RESERVA",'Registre de reserves'!$I$2:$I$1178,'2025'!$A16,'Registre de reserves'!$B$2:$B$1178,'2025'!X$2,Tabla1[ANY],'2025'!$Z$2)-SUMIFS('Registre de reserves'!$U$2:$U$1178,'Registre de reserves'!$T$2:$T$1178,"RESERVA",'Registre de reserves'!$I$2:$I$1178,'2025'!$A16,'Registre de reserves'!$B$2:$B$1178,'2025'!X$2,Tabla1[ANY],'2025'!$Z$2) -> 0 | Y16: =IF($X$13=0,0,X16/X$13) -> 0 | Z16: =B16+D16+F16+H16+J16+L16+N16+P16+R16+T16+V16+X16 -> 290 | AA16: =IF($Z$13=0,0,Z16/Z$13) -> 0.06029106 | AB16: =Z16/$A$2 -> 48.333333
A17: Dinar | B17: =SUMIFS('Registre de reserves'!$P$2:$P$1178,'Registre de reserves'!$T$2:$T$1178,"NO",'Registre de reserves'!$I$2:$I$1178,'2025'!$A17,'Registre de reserves'!$B$2:$B$1178,'2025'!B$2,Tabla1[ANY],'2025'!$Z$2)+SUMIFS('Registre de reserves'!$P$2:$P$1178,'Registre de reserves'!$T$2:$T$1178,"RESERVA",'Registre de reserves'!$I$2:$I$1178,'2025'!$A17,'Registre de reserves'!$B$2:$B$1178,'2025'!B$2,Tabla1[ANY],'2025'!$Z$2)-SUMIFS('Registre de reserves'!$U$2:$U$1178,'Registre de reserves'!$T$2:$T$1178,"RESERVA",'Registre de reserves'!$I$2:$I$1178,'2025'!$A17,'Registre de reserves'!$B$2:$B$1178,'2025'!B$2,Tabla1[ANY],'2025'!$Z$2) -> 0 | C17: =IF($B$13=0,0,B17/B$13) -> 0 | D17: =SUMIFS('Registre de reserves'!$P$2:$P$1178,'Registre de reserves'!$T$2:$T$1178,"NO",'Registre de reserves'!$I$2:$I$1178,'2025'!$A17,'Registre de reserves'!$B$2:$B$1178,'2025'!D$2,Tabla1[ANY],'2025'!$Z$2)+SUMIFS('Registre de reserves'!$P$2:$P$1178,'Registre de reserves'!$T$2:$T$1178,"RESERVA",'Registre de reserves'!$I$2:$I$1178,'2025'!$A17,'Registre de reserves'!$B$2:$B$1178,'2025'!D$2,Tabla1[ANY],'2025'!$Z$2)-SUMIFS('Registre de reserves'!$U$2:$U$1178,'Registre de reserves'!$T$2:$T$1178,"RESERVA",'Registre de reserves'!$I$2:$I$1178,'2025'!$A17,'Registre de reserves'!$B$2:$B$1178,'2025'!D$2,Tabla1[ANY],'2025'!$Z$2) -> 0 | E17: =IF($D$13=0,0,D17/D$13) -> 0 | F17: =SUMIFS('Registre de reserves'!$P$2:$P$1178,'Registre de reserves'!$T$2:$T$1178,"NO",'Registre de reserves'!$I$2:$I$1178,'2025'!$A17,'Registre de reserves'!$B$2:$B$1178,'2025'!F$2,Tabla1[ANY],'2025'!$Z$2)+SUMIFS('Registre de reserves'!$P$2:$P$1178,'Registre de reserves'!$T$2:$T$1178,"RESERVA",'Registre de reserves'!$I$2:$I$1178,'2025'!$A17,'Registre de reserves'!$B$2:$B$1178,'2025'!F$2,Tabla1[ANY],'2025'!$Z$2)-SUMIFS('Registre de reserves'!$U$2:$U$1178,'Registre de reserves'!$T$2:$T$1178,"RESERVA",'Registre de reserves'!$I$2:$I$1178,'2025'!$A17,'Registre de reserves'!$B$2:$B$1178,'2025'!F$2,Tabla1[ANY],'2025'!$Z$2) -> 0 | G17: =IF($F$13=0,0,F17/F$13) -> 0 | H17: =SUMIFS('Registre de reserves'!$P$2:$P$1178,'Registre de reserves'!$T$2:$T$1178,"NO",'Registre de reserves'!$I$2:$I$1178,'2025'!$A17,'Registre de reserves'!$B$2:$B$1178,'2025'!H$2,Tabla1[ANY],'2025'!$Z$2)+SUMIFS('Registre de reserves'!$P$2:$P$1178,'Registre de reserves'!$T$2:$T$1178,"RESERVA",'Registre de reserves'!$I$2:$I$1178,'2025'!$A17,'Registre de reserves'!$B$2:$B$1178,'2025'!H$2,Tabla1[ANY],'2025'!$Z$2)-SUMIFS('Registre de reserves'!$U$2:$U$1178,'Registre de reserves'!$T$2:$T$1178,"RESERVA",'Registre de reserves'!$I$2:$I$1178,'2025'!$A17,'Registre de reserves'!$B$2:$B$1178,'2025'!H$2,Tabla1[ANY],'2025'!$Z$2) -> 0 | I17: =IF($H$13=0,0,H17/H$13) -> 0 | J17: =SUMIFS('Registre de reserves'!$P$2:$P$1178,'Registre de reserves'!$T$2:$T$1178,"NO",'Registre de reserves'!$I$2:$I$1178,'2025'!$A17,'Registre de reserves'!$B$2:$B$1178,'2025'!J$2,Tabla1[ANY],'2025'!$Z$2)+SUMIFS('Registre de reserves'!$P$2:$P$1178,'Registre de reserves'!$T$2:$T$1178,"RESERVA",'Registre de reserves'!$I$2:$I$1178,'2025'!$A17,'Registre de reserves'!$B$2:$B$1178,'2025'!J$2,Tabla1[ANY],'2025'!$Z$2)-SUMIFS('Registre de reserves'!$U$2:$U$1178,'Registre de reserves'!$T$2:$T$1178,"RESERVA",'Registre de reserves'!$I$2:$I$1178,'2025'!$A17,'Registre de reserves'!$B$2:$B$1178,'2025'!J$2,Tabla1[ANY],'2025'!$Z$2) -> 0 | K17: =IF($J$13=0,0,J17/J$13) -> 0 | L17: =SUMIFS('Registre de reserves'!$P$2:$P$1178,'Registre de reserves'!$T$2:$T$1178,"NO",'Registre de reserves'!$I$2:$I$1178,'2025'!$A17,'Registre de reserves'!$B$2:$B$1178,'2025'!L$2,Tabla1[ANY],'2025'!$Z$2)+SUMIFS('Registre de reserves'!$P$2:$P$1178,'Registre de reserves'!$T$2:$T$1178,"RESERVA",'Registre de reserves'!$I$2:$I$1178,'2025'!$A17,'Registre de reserves'!$B$2:$B$1178,'2025'!L$2,Tabla1[ANY],'2025'!$Z$2)-SUMIFS('Registre de reserves'!$U$2:$U$1178,'Registre de reserves'!$T$2:$T$1178,"RESERVA",'Registre de reserves'!$I$2:$I$1178,'2025'!$A17,'Registre de reserves'!$B$2:$B$1178,'2025'!L$2,Tabla1[ANY],'2025'!$Z$2) -> 0 | M17: =IF($L$13=0,0,L17/L$13) -> 0 | N17: =SUMIFS('Registre de reserves'!$P$2:$P$1178,'Registre de reserves'!$T$2:$T$1178,"NO",'Registre de reserves'!$I$2:$I$1178,'2025'!$A17,'Registre de reserves'!$B$2:$B$1178,'2025'!N$2,Tabla1[ANY],'2025'!$Z$2)+SUMIFS('Registre de reserves'!$P$2:$P$1178,'Registre de reserves'!$T$2:$T$1178,"RESERVA",'Registre de reserves'!$I$2:$I$1178,'2025'!$A17,'Registre de reserves'!$B$2:$B$1178,'2025'!N$2,Tabla1[ANY],'2025'!$Z$2)-SUMIFS('Registre de reserves'!$U$2:$U$1178,'Registre de reserves'!$T$2:$T$1178,"RESERVA",'Registre de reserves'!$I$2:$I$1178,'2025'!$A17,'Registre de reserves'!$B$2:$B$1178,'2025'!N$2,Tabla1[ANY],'2025'!$Z$2) -> 0 | O17: =IF($N$13=0,0,N17/N$13) -> 0 | P17: =SUMIFS('Registre de reserves'!$P$2:$P$1178,'Registre de reserves'!$T$2:$T$1178,"NO",'Registre de reserves'!$I$2:$I$1178,'2025'!$A17,'Registre de reserves'!$B$2:$B$1178,'2025'!P$2,Tabla1[ANY],'2025'!$Z$2)+SUMIFS('Registre de reserves'!$P$2:$P$1178,'Registre de reserves'!$T$2:$T$1178,"RESERVA",'Registre de reserves'!$I$2:$I$1178,'2025'!$A17,'Registre de reserves'!$B$2:$B$1178,'2025'!P$2,Tabla1[ANY],'2025'!$Z$2)-SUMIFS('Registre de reserves'!$U$2:$U$1178,'Registre de reserves'!$T$2:$T$1178,"RESERVA",'Registre de reserves'!$I$2:$I$1178,'2025'!$A17,'Registre de reserves'!$B$2:$B$1178,'2025'!P$2,Tabla1[ANY],'2025'!$Z$2) -> 0 | Q17: =IF($P$13=0,0,P17/P$13) -> 0 | R17: =SUMIFS('Registre de reserves'!$P$2:$P$1178,'Registre de reserves'!$T$2:$T$1178,"NO",'Registre de reserves'!$I$2:$I$1178,'2025'!$A17,'Registre de reserves'!$B$2:$B$1178,'2025'!R$2,Tabla1[ANY],'2025'!$Z$2)+SUMIFS('Registre de reserves'!$P$2:$P$1178,'Registre de reserves'!$T$2:$T$1178,"RESERVA",'Registre de reserves'!$I$2:$I$1178,'2025'!$A17,'Registre de reserves'!$B$2:$B$1178,'2025'!R$2,Tabla1[ANY],'2025'!$Z$2)-SUMIFS('Registre de reserves'!$U$2:$U$1178,'Registre de reserves'!$T$2:$T$1178,"RESERVA",'Registre de reserves'!$I$2:$I$1178,'2025'!$A17,'Registre de reserves'!$B$2:$B$1178,'2025'!R$2,Tabla1[ANY],'2025'!$Z$2) -> 0 | S17: =IF($R$13=0,0,R17/R$13) -> 0 | T17: =SUMIFS('Registre de reserves'!$P$2:$P$1178,'Registre de reserves'!$T$2:$T$1178,"NO",'Registre de reserves'!$I$2:$I$1178,'2025'!$A17,'Registre de reserves'!$B$2:$B$1178,'2025'!T$2,Tabla1[ANY],'2025'!$Z$2)+SUMIFS('Registre de reserves'!$P$2:$P$1178,'Registre de reserves'!$T$2:$T$1178,"RESERVA",'Registre de reserves'!$I$2:$I$1178,'2025'!$A17,'Registre de reserves'!$B$2:$B$1178,'2025'!T$2,Tabla1[ANY],'2025'!$Z$2)-SUMIFS('Registre de reserves'!$U$2:$U$1178,'Registre de reserves'!$T$2:$T$1178,"RESERVA",'Registre de reserves'!$I$2:$I$1178,'2025'!$A17,'Registre de reserves'!$B$2:$B$1178,'2025'!T$2,Tabla1[ANY],'2025'!$Z$2) -> 0 | U17: =IF($T$13=0,0,T17/T$13) -> 0 | V17: =SUMIFS('Registre de reserves'!$P$2:$P$1178,'Registre de reserves'!$T$2:$T$1178,"NO",'Registre de reserves'!$I$2:$I$1178,'2025'!$A17,'Registre de reserves'!$B$2:$B$1178,'2025'!V$2,Tabla1[ANY],'2025'!$Z$2)+SUMIFS('Registre de reserves'!$P$2:$P$1178,'Registre de reserves'!$T$2:$T$1178,"RESERVA",'Registre de reserves'!$I$2:$I$1178,'2025'!$A17,'Registre de reserves'!$B$2:$B$1178,'2025'!V$2,Tabla1[ANY],'2025'!$Z$2)-SUMIFS('Registre de reserves'!$U$2:$U$1178,'Registre de reserves'!$T$2:$T$1178,"RESERVA",'Registre de reserves'!$I$2:$I$1178,'2025'!$A17,'Registre de reserves'!$B$2:$B$1178,'2025'!V$2,Tabla1[ANY],'2025'!$Z$2) -> 0 | W17: =IF($V$13=0,0,V17/V$13) -> 0 | X17: =SUMIFS('Registre de reserves'!$P$2:$P$1178,'Registre de reserves'!$T$2:$T$1178,"NO",'Registre de reserves'!$I$2:$I$1178,'2025'!$A17,'Registre de reserves'!$B$2:$B$1178,'2025'!X$2,Tabla1[ANY],'2025'!$Z$2)+SUMIFS('Registre de reserves'!$P$2:$P$1178,'Registre de reserves'!$T$2:$T$1178,"RESERVA",'Registre de reserves'!$I$2:$I$1178,'2025'!$A17,'Registre de reserves'!$B$2:$B$1178,'2025'!X$2,Tabla1[ANY],'2025'!$Z$2)-SUMIFS('Registre de reserves'!$U$2:$U$1178,'Registre de reserves'!$T$2:$T$1178,"RESERVA",'Registre de reserves'!$I$2:$I$1178,'2025'!$A17,'Registre de reserves'!$B$2:$B$1178,'2025'!X$2,Tabla1[ANY],'2025'!$Z$2) -> 0 | Y17: =IF($X$13=0,0,X17/X$13) -> 0 | Z17: =B17+D17+F17+H17+J17+L17+N17+P17+R17+T17+V17+X17 -> 0 | AA17: =IF($Z$13=0,0,Z17/Z$13) -> 0 | AB17: =Z17/$A$2 -> 0
A18: Sopar | B18: =SUMIFS('Registre de reserves'!$P$2:$P$1178,'Registre de reserves'!$T$2:$T$1178,"NO",'Registre de reserves'!$I$2:$I$1178,'2025'!$A18,'Registre de reserves'!$B$2:$B$1178,'2025'!B$2,Tabla1[ANY],'2025'!$Z$2)+SUMIFS('Registre de reserves'!$P$2:$P$1178,'Registre de reserves'!$T$2:$T$1178,"RESERVA",'Registre de reserves'!$I$2:$I$1178,'2025'!$A18,'Registre de reserves'!$B$2:$B$1178,'2025'!B$2,Tabla1[ANY],'2025'!$Z$2)-SUMIFS('Registre de reserves'!$U$2:$U$1178,'Registre de reserves'!$T$2:$T$1178,"RESERVA",'Registre de reserves'!$I$2:$I$1178,'2025'!$A18,'Registre de reserves'!$B$2:$B$1178,'2025'!B$2,Tabla1[ANY],'2025'!$Z$2) -> 0 | C18: =IF($B$13=0,0,B18/B$13) -> 0 | D18: =SUMIFS('Registre de reserves'!$P$2:$P$1178,'Registre de reserves'!$T$2:$T$1178,"NO",'Registre de reserves'!$I$2:$I$1178,'2025'!$A18,'Registre de reserves'!$B$2:$B$1178,'2025'!D$2,Tabla1[ANY],'2025'!$Z$2)+SUMIFS('Registre de reserves'!$P$2:$P$1178,'Registre de reserves'!$T$2:$T$1178,"RESERVA",'Registre de reserves'!$I$2:$I$1178,'2025'!$A18,'Registre de reserves'!$B$2:$B$1178,'2025'!D$2,Tabla1[ANY],'2025'!$Z$2)-SUMIFS('Registre de reserves'!$U$2:$U$1178,'Registre de reserves'!$T$2:$T$1178,"RESERVA",'Registre de reserves'!$I$2:$I$1178,'2025'!$A18,'Registre de reserves'!$B$2:$B$1178,'2025'!D$2,Tabla1[ANY],'2025'!$Z$2) -> 0 | E18: =IF($D$13=0,0,D18/D$13) -> 0 | F18: =SUMIFS('Registre de reserves'!$P$2:$P$1178,'Registre de reserves'!$T$2:$T$1178,"NO",'Registre de reserves'!$I$2:$I$1178,'2025'!$A18,'Registre de reserves'!$B$2:$B$1178,'2025'!F$2,Tabla1[ANY],'2025'!$Z$2)+SUMIFS('Registre de reserves'!$P$2:$P$1178,'Registre de reserves'!$T$2:$T$1178,"RESERVA",'Registre de reserves'!$I$2:$I$1178,'2025'!$A18,'Registre de reserves'!$B$2:$B$1178,'2025'!F$2,Tabla1[ANY],'2025'!$Z$2)-SUMIFS('Registre de reserves'!$U$2:$U$1178,'Registre de reserves'!$T$2:$T$1178,"RESERVA",'Registre de reserves'!$I$2:$I$1178,'2025'!$A18,'Registre de reserves'!$B$2:$B$1178,'2025'!F$2,Tabla1[ANY],'2025'!$Z$2) -> 0 | G18: =IF($F$13=0,0,F18/F$13) -> 0 | H18: =SUMIFS('Registre de reserves'!$P$2:$P$1178,'Registre de reserves'!$T$2:$T$1178,"NO",'Registre de reserves'!$I$2:$I$1178,'2025'!$A18,'Registre de reserves'!$B$2:$B$1178,'2025'!H$2,Tabla1[ANY],'2025'!$Z$2)+SUMIFS('Registre de reserves'!$P$2:$P$1178,'Registre de reserves'!$T$2:$T$1178,"RESERVA",'Registre de reserves'!$I$2:$I$1178,'2025'!$A18,'Registre de reserves'!$B$2:$B$1178,'2025'!H$2,Tabla1[ANY],'2025'!$Z$2)-SUMIFS('Registre de reserves'!$U$2:$U$1178,'Registre de reserves'!$T$2:$T$1178,"RESERVA",'Registre de reserves'!$I$2:$I$1178,'2025'!$A18,'Registre de reserves'!$B$2:$B$1178,'2025'!H$2,Tabla1[ANY],'2025'!$Z$2) -> 0 | I18: =IF($H$13=0,0,H18/H$13) -> 0 | J18: =SUMIFS('Registre de reserves'!$P$2:$P$1178,'Registre de reserves'!$T$2:$T$1178,"NO",'Registre de reserves'!$I$2:$I$1178,'2025'!$A18,'Registre de reserves'!$B$2:$B$1178,'2025'!J$2,Tabla1[ANY],'2025'!$Z$2)+SUMIFS('Registre de reserves'!$P$2:$P$1178,'Registre de reserves'!$T$2:$T$1178,"RESERVA",'Registre de reserves'!$I$2:$I$1178,'2025'!$A18,'Registre de reserves'!$B$2:$B$1178,'2025'!J$2,Tabla1[ANY],'2025'!$Z$2)-SUMIFS('Registre de reserves'!$U$2:$U$1178,'Registre de reserves'!$T$2:$T$1178,"RESERVA",'Registre de reserves'!$I$2:$I$1178,'2025'!$A18,'Registre de reserves'!$B$2:$B$1178,'2025'!J$2,Tabla1[ANY],'2025'!$Z$2) -> 0 | K18: =IF($J$13=0,0,J18/J$13) -> 0 | L18: =SUMIFS('Registre de reserves'!$P$2:$P$1178,'Registre de reserves'!$T$2:$T$1178,"NO",'Registre de reserves'!$I$2:$I$1178,'2025'!$A18,'Registre de reserves'!$B$2:$B$1178,'2025'!L$2,Tabla1[ANY],'2025'!$Z$2)+SUMIFS('Registre de reserves'!$P$2:$P$1178,'Registre de reserves'!$T$2:$T$1178,"RESERVA",'Registre de reserves'!$I$2:$I$1178,'2025'!$A18,'Registre de reserves'!$B$2:$B$1178,'2025'!L$2,Tabla1[ANY],'2025'!$Z$2)-SUMIFS('Registre de reserves'!$U$2:$U$1178,'Registre de reserves'!$T$2:$T$1178,"RESERVA",'Registre de reserves'!$I$2:$I$1178,'2025'!$A18,'Registre de reserves'!$B$2:$B$1178,'2025'!L$2,Tabla1[ANY],'2025'!$Z$2) -> 0 | M18: =IF($L$13=0,0,L18/L$13) -> 0 | N18: =SUMIFS('Registre de reserves'!$P$2:$P$1178,'Registre de reserves'!$T$2:$T$1178,"NO",'Registre de reserves'!$I$2:$I$1178,'2025'!$A18,'Registre de reserves'!$B$2:$B$1178,'2025'!N$2,Tabla1[ANY],'2025'!$Z$2)+SUMIFS('Registre de reserves'!$P$2:$P$1178,'Registre de reserves'!$T$2:$T$1178,"RESERVA",'Registre de reserves'!$I$2:$I$1178,'2025'!$A18,'Registre de reserves'!$B$2:$B$1178,'2025'!N$2,Tabla1[ANY],'2025'!$Z$2)-SUMIFS('Registre de reserves'!$U$2:$U$1178,'Registre de reserves'!$T$2:$T$1178,"RESERVA",'Registre de reserves'!$I$2:$I$1178,'2025'!$A18,'Registre de reserves'!$B$2:$B$1178,'2025'!N$2,Tabla1[ANY],'2025'!$Z$2) -> 0 | O18: =IF($N$13=0,0,N18/N$13) -> 0 | P18: =SUMIFS('Registre de reserves'!$P$2:$P$1178,'Registre de reserves'!$T$2:$T$1178,"NO",'Registre de reserves'!$I$2:$I$1178,'2025'!$A18,'Registre de reserves'!$B$2:$B$1178,'2025'!P$2,Tabla1[ANY],'2025'!$Z$2)+SUMIFS('Registre de reserves'!$P$2:$P$1178,'Registre de reserves'!$T$2:$T$1178,"RESERVA",'Registre de reserves'!$I$2:$I$1178,'2025'!$A18,'Registre de reserves'!$B$2:$B$1178,'2025'!P$2,Tabla1[ANY],'2025'!$Z$2)-SUMIFS('Registre de reserves'!$U$2:$U$1178,'Registre de reserves'!$T$2:$T$1178,"RESERVA",'Registre de reserves'!$I$2:$I$1178,'2025'!$A18,'Registre de reserves'!$B$2:$B$1178,'2025'!P$2,Tabla1[ANY],'2025'!$Z$2) -> 0 | Q18: =IF($P$13=0,0,P18/P$13) -> 0 | R18: =SUMIFS('Registre de reserves'!$P$2:$P$1178,'Registre de reserves'!$T$2:$T$1178,"NO",'Registre de reserves'!$I$2:$I$1178,'2025'!$A18,'Registre de reserves'!$B$2:$B$1178,'2025'!R$2,Tabla1[ANY],'2025'!$Z$2)+SUMIFS('Registre de reserves'!$P$2:$P$1178,'Registre de reserves'!$T$2:$T$1178,"RESERVA",'Registre de reserves'!$I$2:$I$1178,'2025'!$A18,'Registre de reserves'!$B$2:$B$1178,'2025'!R$2,Tabla1[ANY],'2025'!$Z$2)-SUMIFS('Registre de reserves'!$U$2:$U$1178,'Registre de reserves'!$T$2:$T$1178,"RESERVA",'Registre de reserves'!$I$2:$I$1178,'2025'!$A18,'Registre de reserves'!$B$2:$B$1178,'2025'!R$2,Tabla1[ANY],'2025'!$Z$2) -> 0 | S18: =IF($R$13=0,0,R18/R$13) -> 0 | T18: =SUMIFS('Registre de reserves'!$P$2:$P$1178,'Registre de reserves'!$T$2:$T$1178,"NO",'Registre de reserves'!$I$2:$I$1178,'2025'!$A18,'Registre de reserves'!$B$2:$B$1178,'2025'!T$2,Tabla1[ANY],'2025'!$Z$2)+SUMIFS('Registre de reserves'!$P$2:$P$1178,'Registre de reserves'!$T$2:$T$1178,"RESERVA",'Registre de reserves'!$I$2:$I$1178,'2025'!$A18,'Registre de reserves'!$B$2:$B$1178,'2025'!T$2,Tabla1[ANY],'2025'!$Z$2)-SUMIFS('Registre de reserves'!$U$2:$U$1178,'Registre de reserves'!$T$2:$T$1178,"RESERVA",'Registre de reserves'!$I$2:$I$1178,'2025'!$A18,'Registre de reserves'!$B$2:$B$1178,'2025'!T$2,Tabla1[ANY],'2025'!$Z$2) -> 0 | U18: =IF($T$13=0,0,T18/T$13) -> 0 | V18: =SUMIFS('Registre de reserves'!$P$2:$P$1178,'Registre de reserves'!$T$2:$T$1178,"NO",'Registre de reserves'!$I$2:$I$1178,'2025'!$A18,'Registre de reserves'!$B$2:$B$1178,'2025'!V$2,Tabla1[ANY],'2025'!$Z$2)+SUMIFS('Registre de reserves'!$P$2:$P$1178,'Registre de reserves'!$T$2:$T$1178,"RESERVA",'Registre de reserves'!$I$2:$I$1178,'2025'!$A18,'Registre de reserves'!$B$2:$B$1178,'2025'!V$2,Tabla1[ANY],'2025'!$Z$2)-SUMIFS('Registre de reserves'!$U$2:$U$1178,'Registre de reserves'!$T$2:$T$1178,"RESERVA",'Registre de reserves'!$I$2:$I$1178,'2025'!$A18,'Registre de reserves'!$B$2:$B$1178,'2025'!V$2,Tabla1[ANY],'2025'!$Z$2) -> 0 | W18: =IF($V$13=0,0,V18/V$13) -> 0 | X18: =SUMIFS('Registre de reserves'!$P$2:$P$1178,'Registre de reserves'!$T$2:$T$1178,"NO",'Registre de reserves'!$I$2:$I$1178,'2025'!$A18,'Registre de reserves'!$B$2:$B$1178,'2025'!X$2,Tabla1[ANY],'2025'!$Z$2)+SUMIFS('Registre de reserves'!$P$2:$P$1178,'Registre de reserves'!$T$2:$T$1178,"RESERVA",'Registre de reserves'!$I$2:$I$1178,'2025'!$A18,'Registre de reserves'!$B$2:$B$1178,'2025'!X$2,Tabla1[ANY],'2025'!$Z$2)-SUMIFS('Registre de reserves'!$U$2:$U$1178,'Registre de reserves'!$T$2:$T$1178,"RESERVA",'Registre de reserves'!$I$2:$I$1178,'2025'!$A18,'Registre de reserves'!$B$2:$B$1178,'2025'!X$2,Tabla1[ANY],'2025'!$Z$2) -> 0 | Y18: =IF($X$13=0,0,X18/X$13) -> 0 | Z18: =B18+D18+F18+H18+J18+L18+N18+P18+R18+T18+V18+X18 -> 0 | AA18: =IF($Z$13=0,0,Z18/Z$13) -> 0 | AB18: =Z18/$A$2 -> 0
A19: Nit | B19: =SUMIFS('Registre de reserves'!$P$2:$P$1178,'Registre de reserves'!$T$2:$T$1178,"NO",'Registre de reserves'!$I$2:$I$1178,'2025'!$A19,'Registre de reserves'!$B$2:$B$1178,'2025'!B$2,Tabla1[ANY],'2025'!$Z$2)+SUMIFS('Registre de reserves'!$P$2:$P$1178,'Registre de reserves'!$T$2:$T$1178,"RESERVA",'Registre de reserves'!$I$2:$I$1178,'2025'!$A19,'Registre de reserves'!$B$2:$B$1178,'2025'!B$2,Tabla1[ANY],'2025'!$Z$2)-SUMIFS('Registre de reserves'!$U$2:$U$1178,'Registre de reserves'!$T$2:$T$1178,"RESERVA",'Registre de reserves'!$I$2:$I$1178,'2025'!$A19,'Registre de reserves'!$B$2:$B$1178,'2025'!B$2,Tabla1[ANY],'2025'!$Z$2) -> 0 | C19: =IF($B$13=0,0,B19/B$13) -> 0 | D19: =SUMIFS('Registre de reserves'!$P$2:$P$1178,'Registre de reserves'!$T$2:$T$1178,"NO",'Registre de reserves'!$I$2:$I$1178,'2025'!$A19,'Registre de reserves'!$B$2:$B$1178,'2025'!D$2,Tabla1[ANY],'2025'!$Z$2)+SUMIFS('Registre de reserves'!$P$2:$P$1178,'Registre de reserves'!$T$2:$T$1178,"RESERVA",'Registre de reserves'!$I$2:$I$1178,'2025'!$A19,'Registre de reserves'!$B$2:$B$1178,'2025'!D$2,Tabla1[ANY],'2025'!$Z$2)-SUMIFS('Registre de reserves'!$U$2:$U$1178,'Registre de reserves'!$T$2:$T$1178,"RESERVA",'Registre de reserves'!$I$2:$I$1178,'2025'!$A19,'Registre de reserves'!$B$2:$B$1178,'2025'!D$2,Tabla1[ANY],'2025'!$Z$2) -> 0 | E19: =IF($D$13=0,0,D19/D$13) -> 0 | F19: =SUMIFS('Registre de reserves'!$P$2:$P$1178,'Registre de reserves'!$T$2:$T$1178,"NO",'Registre de reserves'!$I$2:$I$1178,'2025'!$A19,'Registre de reserves'!$B$2:$B$1178,'2025'!F$2,Tabla1[ANY],'2025'!$Z$2)+SUMIFS('Registre de reserves'!$P$2:$P$1178,'Registre de reserves'!$T$2:$T$1178,"RESERVA",'Registre de reserves'!$I$2:$I$1178,'2025'!$A19,'Registre de reserves'!$B$2:$B$1178,'2025'!F$2,Tabla1[ANY],'2025'!$Z$2)-SUMIFS('Registre de reserves'!$U$2:$U$1178,'Registre de reserves'!$T$2:$T$1178,"RESERVA",'Registre de reserves'!$I$2:$I$1178,'2025'!$A19,'Registre de reserves'!$B$2:$B$1178,'2025'!F$2,Tabla1[ANY],'2025'!$Z$2) -> 0 | G19: =IF($F$13=0,0,F19/F$13) -> 0 | H19: =SUMIFS('Registre de reserves'!$P$2:$P$1178,'Registre de reserves'!$T$2:$T$1178,"NO",'Registre de reserves'!$I$2:$I$1178,'2025'!$A19,'Registre de reserves'!$B$2:$B$1178,'2025'!H$2,Tabla1[ANY],'2025'!$Z$2)+SUMIFS('Registre de reserves'!$P$2:$P$1178,'Registre de reserves'!$T$2:$T$1178,"RESERVA",'Registre de reserves'!$I$2:$I$1178,'2025'!$A19,'Registre de reserves'!$B$2:$B$1178,'2025'!H$2,Tabla1[ANY],'2025'!$Z$2)-SUMIFS('Registre de reserves'!$U$2:$U$1178,'Registre de reserves'!$T$2:$T$1178,"RESERVA",'Registre de reserves'!$I$2:$I$1178,'2025'!$A19,'Registre de reserves'!$B$2:$B$1178,'2025'!H$2,Tabla1[ANY],'2025'!$Z$2) -> 0 | I19: =IF($H$13=0,0,H19/H$13) -> 0 | J19: =SUMIFS('Registre de reserves'!$P$2:$P$1178,'Registre de reserves'!$T$2:$T$1178,"NO",'Registre de reserves'!$I$2:$I$1178,'2025'!$A19,'Registre de reserves'!$B$2:$B$1178,'2025'!J$2,Tabla1[ANY],'2025'!$Z$2)+SUMIFS('Registre de reserves'!$P$2:$P$1178,'Registre de reserves'!$T$2:$T$1178,"RESERVA",'Registre de reserves'!$I$2:$I$1178,'2025'!$A19,'Registre de reserves'!$B$2:$B$1178,'2025'!J$2,Tabla1[ANY],'2025'!$Z$2)-SUMIFS('Registre de reserves'!$U$2:$U$1178,'Registre de reserves'!$T$2:$T$1178,"RESERVA",'Registre de reserves'!$I$2:$I$1178,'2025'!$A19,'Registre de reserves'!$B$2:$B$1178,'2025'!J$2,Tabla1[ANY],'2025'!$Z$2) -> 0 | K19: =IF($J$13=0,0,J19/J$13) -> 0 | L19: =SUMIFS('Registre de reserves'!$P$2:$P$1178,'Registre de reserves'!$T$2:$T$1178,"NO",'Registre de reserves'!$I$2:$I$1178,'2025'!$A19,'Registre de reserves'!$B$2:$B$1178,'2025'!L$2,Tabla1[ANY],'2025'!$Z$2)+SUMIFS('Registre de reserves'!$P$2:$P$1178,'Registre de reserves'!$T$2:$T$1178,"RESERVA",'Registre de reserves'!$I$2:$I$1178,'2025'!$A19,'Registre de reserves'!$B$2:$B$1178,'2025'!L$2,Tabla1[ANY],'2025'!$Z$2)-SUMIFS('Registre de reserves'!$U$2:$U$1178,'Registre de reserves'!$T$2:$T$1178,"RESERVA",'Registre de reserves'!$I$2:$I$1178,'2025'!$A19,'Registre de reserves'!$B$2:$B$1178,'2025'!L$2,Tabla1[ANY],'2025'!$Z$2) -> 550 | M19: =IF($L$13=0,0,L19/L$13) -> 0.4 | N19: =SUMIFS('Registre de reserves'!$P$2:$P$1178,'Registre de reserves'!$T$2:$T$1178,"NO",'Registre de reserves'!$I$2:$I$1178,'2025'!$A19,'Registre de reserves'!$B$2:$B$1178,'2025'!N$2,Tabla1[ANY],'2025'!$Z$2)+SUMIFS('Registre de reserves'!$P$2:$P$1178,'Registre de reserves'!$T$2:$T$1178,"RESERVA",'Registre de reserves'!$I$2:$I$1178,'2025'!$A19,'Registre de reserves'!$B$2:$B$1178,'2025'!N$2,Tabla1[ANY],'2025'!$Z$2)-SUMIFS('Registre de reserves'!$U$2:$U$1178,'Registre de reserves'!$T$2:$T$1178,"RESERVA",'Registre de reserves'!$I$2:$I$1178,'2025'!$A19,'Registre de reserves'!$B$2:$B$1178,'2025'!N$2,Tabla1[ANY],'2025'!$Z$2) -> 800 | O19: =IF($N$13=0,0,N19/N$13) -> 0.28218695 | P19: =SUMIFS('Registre de reserves'!$P$2:$P$1178,'Registre de reserves'!$T$2:$T$1178,"NO",'Registre de reserves'!$I$2:$I$1178,'2025'!$A19,'Registre de reserves'!$B$2:$B$1178,'2025'!P$2,Tabla1[ANY],'2025'!$Z$2)+SUMIFS('Registre de reserves'!$P$2:$P$1178,'Registre de reserves'!$T$2:$T$1178,"RESERVA",'Registre de reserves'!$I$2:$I$1178,'2025'!$A19,'Registre de reserves'!$B$2:$B$1178,'2025'!P$2,Tabla1[ANY],'2025'!$Z$2)-SUMIFS('Registre de reserves'!$U$2:$U$1178,'Registre de reserves'!$T$2:$T$1178,"RESERVA",'Registre de reserves'!$I$2:$I$1178,'2025'!$A19,'Registre de reserves'!$B$2:$B$1178,'2025'!P$2,Tabla1[ANY],'2025'!$Z$2) -> 0 | Q19: =IF($P$13=0,0,P19/P$13) -> 0 | R19: =SUMIFS('Registre de reserves'!$P$2:$P$1178,'Registre de reserves'!$T$2:$T$1178,"NO",'Registre de reserves'!$I$2:$I$1178,'2025'!$A19,'Registre de reserves'!$B$2:$B$1178,'2025'!R$2,Tabla1[ANY],'2025'!$Z$2)+SUMIFS('Registre de reserves'!$P$2:$P$1178,'Registre de reserves'!$T$2:$T$1178,"RESERVA",'Registre de reserves'!$I$2:$I$1178,'2025'!$A19,'Registre de reserves'!$B$2:$B$1178,'2025'!R$2,Tabla1[ANY],'2025'!$Z$2)-SUMIFS('Registre de reserves'!$U$2:$U$1178,'Registre de reserves'!$T$2:$T$1178,"RESERVA",'Registre de reserves'!$I$2:$I$1178,'2025'!$A19,'Registre de reserves'!$B$2:$B$1178,'2025'!R$2,Tabla1[ANY],'2025'!$Z$2) -> 0 | S19: =IF($R$13=0,0,R19/R$13) -> 0 | T19: =SUMIFS('Registre de reserves'!$P$2:$P$1178,'Registre de reserves'!$T$2:$T$1178,"NO",'Registre de reserves'!$I$2:$I$1178,'2025'!$A19,'Registre de reserves'!$B$2:$B$1178,'2025'!T$2,Tabla1[ANY],'2025'!$Z$2)+SUMIFS('Registre de reserves'!$P$2:$P$1178,'Registre de reserves'!$T$2:$T$1178,"RESERVA",'Registre de reserves'!$I$2:$I$1178,'2025'!$A19,'Registre de reserves'!$B$2:$B$1178,'2025'!T$2,Tabla1[ANY],'2025'!$Z$2)-SUMIFS('Registre de reserves'!$U$2:$U$1178,'Registre de reserves'!$T$2:$T$1178,"RESERVA",'Registre de reserves'!$I$2:$I$1178,'2025'!$A19,'Registre de reserves'!$B$2:$B$1178,'2025'!T$2,Tabla1[ANY],'2025'!$Z$2) -> 0 | U19: =IF($T$13=0,0,T19/T$13) -> 0 | V19: =SUMIFS('Registre de reserves'!$P$2:$P$1178,'Registre de reserves'!$T$2:$T$1178,"NO",'Registre de reserves'!$I$2:$I$1178,'2025'!$A19,'Registre de reserves'!$B$2:$B$1178,'2025'!V$2,Tabla1[ANY],'2025'!$Z$2)+SUMIFS('Registre de reserves'!$P$2:$P$1178,'Registre de reserves'!$T$2:$T$1178,"RESERVA",'Registre de reserves'!$I$2:$I$1178,'2025'!$A19,'Registre de reserves'!$B$2:$B$1178,'2025'!V$2,Tabla1[ANY],'2025'!$Z$2)-SUMIFS('Registre de reserves'!$U$2:$U$1178,'Registre de reserves'!$T$2:$T$1178,"RESERVA",'Registre de reserves'!$I$2:$I$1178,'2025'!$A19,'Registre de reserves'!$B$2:$B$1178,'2025'!V$2,Tabla1[ANY],'2025'!$Z$2) -> 0 | W19: =IF($V$13=0,0,V19/V$13) -> 0 | X19: =SUMIFS('Registre de reserves'!$P$2:$P$1178,'Registre de reserves'!$T$2:$T$1178,"NO",'Registre de reserves'!$I$2:$I$1178,'2025'!$A19,'Registre de reserves'!$B$2:$B$1178,'2025'!X$2,Tabla1[ANY],'2025'!$Z$2)+SUMIFS('Registre de reserves'!$P$2:$P$1178,'Registre de reserves'!$T$2:$T$1178,"RESERVA",'Registre de reserves'!$I$2:$I$1178,'2025'!$A19,'Registre de reserves'!$B$2:$B$1178,'2025'!X$2,Tabla1[ANY],'2025'!$Z$2)-SUMIFS('Registre de reserves'!$U$2:$U$1178,'Registre de reserves'!$T$2:$T$1178,"RESERVA",'Registre de reserves'!$I$2:$I$1178,'2025'!$A19,'Registre de reserves'!$B$2:$B$1178,'2025'!X$2,Tabla1[ANY],'2025'!$Z$2) -> 0 | Y19: =IF($X$13=0,0,X19/X$13) -> 0 | Z19: =B19+D19+F19+H19+J19+L19+N19+P19+R19+T19+V19+X19 -> 1350 | AA19: =IF($Z$13=0,0,Z19/Z$13) -> 0.28066528 | AB19: =Z19/$A$2 -> 225
A20: Tarda+Nit | B20: =SUMIFS('Registre de reserves'!$P$2:$P$1178,'Registre de reserves'!$T$2:$T$1178,"NO",'Registre de reserves'!$I$2:$I$1178,'2025'!$A20,'Registre de reserves'!$B$2:$B$1178,'2025'!B$2,Tabla1[ANY],'2025'!$Z$2)+SUMIFS('Registre de reserves'!$P$2:$P$1178,'Registre de reserves'!$T$2:$T$1178,"RESERVA",'Registre de reserves'!$I$2:$I$1178,'2025'!$A20,'Registre de reserves'!$B$2:$B$1178,'2025'!B$2,Tabla1[ANY],'2025'!$Z$2)-SUMIFS('Registre de reserves'!$U$2:$U$1178,'Registre de reserves'!$T$2:$T$1178,"RESERVA",'Registre de reserves'!$I$2:$I$1178,'2025'!$A20,'Registre de reserves'!$B$2:$B$1178,'2025'!B$2,Tabla1[ANY],'2025'!$Z$2) -> 0 | C20: =IF($B$13=0,0,B20/B$13) -> 0 | D20: =SUMIFS('Registre de reserves'!$P$2:$P$1178,'Registre de reserves'!$T$2:$T$1178,"NO",'Registre de reserves'!$I$2:$I$1178,'2025'!$A20,'Registre de reserves'!$B$2:$B$1178,'2025'!D$2,Tabla1[ANY],'2025'!$Z$2)+SUMIFS('Registre de reserves'!$P$2:$P$1178,'Registre de reserves'!$T$2:$T$1178,"RESERVA",'Registre de reserves'!$I$2:$I$1178,'2025'!$A20,'Registre de reserves'!$B$2:$B$1178,'2025'!D$2,Tabla1[ANY],'2025'!$Z$2)-SUMIFS('Registre de reserves'!$U$2:$U$1178,'Registre de reserves'!$T$2:$T$1178,"RESERVA",'Registre de reserves'!$I$2:$I$1178,'2025'!$A20,'Registre de reserves'!$B$2:$B$1178,'2025'!D$2,Tabla1[ANY],'2025'!$Z$2) -> 0 | E20: =IF($D$13=0,0,D20/D$13) -> 0 | F20: =SUMIFS('Registre de reserves'!$P$2:$P$1178,'Registre de reserves'!$T$2:$T$1178,"NO",'Registre de reserves'!$I$2:$I$1178,'2025'!$A20,'Registre de reserves'!$B$2:$B$1178,'2025'!F$2,Tabla1[ANY],'2025'!$Z$2)+SUMIFS('Registre de reserves'!$P$2:$P$1178,'Registre de reserves'!$T$2:$T$1178,"RESERVA",'Registre de reserves'!$I$2:$I$1178,'2025'!$A20,'Registre de reserves'!$B$2:$B$1178,'2025'!F$2,Tabla1[ANY],'2025'!$Z$2)-SUMIFS('Registre de reserves'!$U$2:$U$1178,'Registre de reserves'!$T$2:$T$1178,"RESERVA",'Registre de reserves'!$I$2:$I$1178,'2025'!$A20,'Registre de reserves'!$B$2:$B$1178,'2025'!F$2,Tabla1[ANY],'2025'!$Z$2) -> 0 | G20: =IF($F$13=0,0,F20/F$13) -> 0 | H20: =SUMIFS('Registre de reserves'!$P$2:$P$1178,'Registre de reserves'!$T$2:$T$1178,"NO",'Registre de reserves'!$I$2:$I$1178,'2025'!$A20,'Registre de reserves'!$B$2:$B$1178,'2025'!H$2,Tabla1[ANY],'2025'!$Z$2)+SUMIFS('Registre de reserves'!$P$2:$P$1178,'Registre de reserves'!$T$2:$T$1178,"RESERVA",'Registre de reserves'!$I$2:$I$1178,'2025'!$A20,'Registre de reserves'!$B$2:$B$1178,'2025'!H$2,Tabla1[ANY],'2025'!$Z$2)-SUMIFS('Registre de reserves'!$U$2:$U$1178,'Registre de reserves'!$T$2:$T$1178,"RESERVA",'Registre de reserves'!$I$2:$I$1178,'2025'!$A20,'Registre de reserves'!$B$2:$B$1178,'2025'!H$2,Tabla1[ANY],'2025'!$Z$2) -> 0 | I20: =IF($H$13=0,0,H20/H$13) -> 0 | J20: =SUMIFS('Registre de reserves'!$P$2:$P$1178,'Registre de reserves'!$T$2:$T$1178,"NO",'Registre de reserves'!$I$2:$I$1178,'2025'!$A20,'Registre de reserves'!$B$2:$B$1178,'2025'!J$2,Tabla1[ANY],'2025'!$Z$2)+SUMIFS('Registre de reserves'!$P$2:$P$1178,'Registre de reserves'!$T$2:$T$1178,"RESERVA",'Registre de reserves'!$I$2:$I$1178,'2025'!$A20,'Registre de reserves'!$B$2:$B$1178,'2025'!J$2,Tabla1[ANY],'2025'!$Z$2)-SUMIFS('Registre de reserves'!$U$2:$U$1178,'Registre de reserves'!$T$2:$T$1178,"RESERVA",'Registre de reserves'!$I$2:$I$1178,'2025'!$A20,'Registre de reserves'!$B$2:$B$1178,'2025'!J$2,Tabla1[ANY],'2025'!$Z$2) -> 0 | K20: =IF($J$13=0,0,J20/J$13) -> 0 | L20: =SUMIFS('Registre de reserves'!$P$2:$P$1178,'Registre de reserves'!$T$2:$T$1178,"NO",'Registre de reserves'!$I$2:$I$1178,'2025'!$A20,'Registre de reserves'!$B$2:$B$1178,'2025'!L$2,Tabla1[ANY],'2025'!$Z$2)+SUMIFS('Registre de reserves'!$P$2:$P$1178,'Registre de reserves'!$T$2:$T$1178,"RESERVA",'Registre de reserves'!$I$2:$I$1178,'2025'!$A20,'Registre de reserves'!$B$2:$B$1178,'2025'!L$2,Tabla1[ANY],'2025'!$Z$2)-SUMIFS('Registre de reserves'!$U$2:$U$1178,'Registre de reserves'!$T$2:$T$1178,"RESERVA",'Registre de reserves'!$I$2:$I$1178,'2025'!$A20,'Registre de reserves'!$B$2:$B$1178,'2025'!L$2,Tabla1[ANY],'2025'!$Z$2) -> 0 | M20: =IF($L$13=0,0,L20/L$13) -> 0 | N20: =SUMIFS('Registre de reserves'!$P$2:$P$1178,'Registre de reserves'!$T$2:$T$1178,"NO",'Registre de reserves'!$I$2:$I$1178,'2025'!$A20,'Registre de reserves'!$B$2:$B$1178,'2025'!N$2,Tabla1[ANY],'2025'!$Z$2)+SUMIFS('Registre de reserves'!$P$2:$P$1178,'Registre de reserves'!$T$2:$T$1178,"RESERVA",'Registre de reserves'!$I$2:$I$1178,'2025'!$A20,'Registre de reserves'!$B$2:$B$1178,'2025'!N$2,Tabla1[ANY],'2025'!$Z$2)-SUMIFS('Registre de reserves'!$U$2:$U$1178,'Registre de reserves'!$T$2:$T$1178,"RESERVA",'Registre de reserves'!$I$2:$I$1178,'2025'!$A20,'Registre de reserves'!$B$2:$B$1178,'2025'!N$2,Tabla1[ANY],'2025'!$Z$2) -> 620 | O20: =IF($N$13=0,0,N20/N$13) -> 0.21869489 | P20: =SUMIFS('Registre de reserves'!$P$2:$P$1178,'Registre de reserves'!$T$2:$T$1178,"NO",'Registre de reserves'!$I$2:$I$1178,'2025'!$A20,'Registre de reserves'!$B$2:$B$1178,'2025'!P$2,Tabla1[ANY],'2025'!$Z$2)+SUMIFS('Registre de reserves'!$P$2:$P$1178,'Registre de reserves'!$T$2:$T$1178,"RESERVA",'Registre de reserves'!$I$2:$I$1178,'2025'!$A20,'Registre de reserves'!$B$2:$B$1178,'2025'!P$2,Tabla1[ANY],'2025'!$Z$2)-SUMIFS('Registre de reserves'!$U$2:$U$1178,'Registre de reserves'!$T$2:$T$1178,"RESERVA",'Registre de reserves'!$I$2:$I$1178,'2025'!$A20,'Registre de reserves'!$B$2:$B$1178,'2025'!P$2,Tabla1[ANY],'2025'!$Z$2) -> 0 | Q20: =IF($P$13=0,0,P20/P$13) -> 0 | R20: =SUMIFS('Registre de reserves'!$P$2:$P$1178,'Registre de reserves'!$T$2:$T$1178,"NO",'Registre de reserves'!$I$2:$I$1178,'2025'!$A20,'Registre de reserves'!$B$2:$B$1178,'2025'!R$2,Tabla1[ANY],'2025'!$Z$2)+SUMIFS('Registre de reserves'!$P$2:$P$1178,'Registre de reserves'!$T$2:$T$1178,"RESERVA",'Registre de reserves'!$I$2:$I$1178,'2025'!$A20,'Registre de reserves'!$B$2:$B$1178,'2025'!R$2,Tabla1[ANY],'2025'!$Z$2)-SUMIFS('Registre de reserves'!$U$2:$U$1178,'Registre de reserves'!$T$2:$T$1178,"RESERVA",'Registre de reserves'!$I$2:$I$1178,'2025'!$A20,'Registre de reserves'!$B$2:$B$1178,'2025'!R$2,Tabla1[ANY],'2025'!$Z$2) -> 0 | S20: =IF($R$13=0,0,R20/R$13) -> 0 | T20: =SUMIFS('Registre de reserves'!$P$2:$P$1178,'Registre de reserves'!$T$2:$T$1178,"NO",'Registre de reserves'!$I$2:$I$1178,'2025'!$A20,'Registre de reserves'!$B$2:$B$1178,'2025'!T$2,Tabla1[ANY],'2025'!$Z$2)+SUMIFS('Registre de reserves'!$P$2:$P$1178,'Registre de reserves'!$T$2:$T$1178,"RESERVA",'Registre de reserves'!$I$2:$I$1178,'2025'!$A20,'Registre de reserves'!$B$2:$B$1178,'2025'!T$2,Tabla1[ANY],'2025'!$Z$2)-SUMIFS('Registre de reserves'!$U$2:$U$1178,'Registre de reserves'!$T$2:$T$1178,"RESERVA",'Registre de reserves'!$I$2:$I$1178,'2025'!$A20,'Registre de reserves'!$B$2:$B$1178,'2025'!T$2,Tabla1[ANY],'2025'!$Z$2) -> 0 | U20: =IF($T$13=0,0,T20/T$13) -> 0 | V20: =SUMIFS('Registre de reserves'!$P$2:$P$1178,'Registre de reserves'!$T$2:$T$1178,"NO",'Registre de reserves'!$I$2:$I$1178,'2025'!$A20,'Registre de reserves'!$B$2:$B$1178,'2025'!V$2,Tabla1[ANY],'2025'!$Z$2)+SUMIFS('Registre de reserves'!$P$2:$P$1178,'Registre de reserves'!$T$2:$T$1178,"RESERVA",'Registre de reserves'!$I$2:$I$1178,'2025'!$A20,'Registre de reserves'!$B$2:$B$1178,'2025'!V$2,Tabla1[ANY],'2025'!$Z$2)-SUMIFS('Registre de reserves'!$U$2:$U$1178,'Registre de reserves'!$T$2:$T$1178,"RESERVA",'Registre de reserves'!$I$2:$I$1178,'2025'!$A20,'Registre de reserves'!$B$2:$B$1178,'2025'!V$2,Tabla1[ANY],'2025'!$Z$2) -> 0 | W20: =IF($V$13=0,0,V20/V$13) -> 0 | X20: =SUMIFS('Registre de reserves'!$P$2:$P$1178,'Registre de reserves'!$T$2:$T$1178,"NO",'Registre de reserves'!$I$2:$I$1178,'2025'!$A20,'Registre de reserves'!$B$2:$B$1178,'2025'!X$2,Tabla1[ANY],'2025'!$Z$2)+SUMIFS('Registre de reserves'!$P$2:$P$1178,'Registre de reserves'!$T$2:$T$1178,"RESERVA",'Registre de reserves'!$I$2:$I$1178,'2025'!$A20,'Registre de reserves'!$B$2:$B$1178,'2025'!X$2,Tabla1[ANY],'2025'!$Z$2)-SUMIFS('Registre de reserves'!$U$2:$U$1178,'Registre de reserves'!$T$2:$T$1178,"RESERVA",'Registre de reserves'!$I$2:$I$1178,'2025'!$A20,'Registre de reserves'!$B$2:$B$1178,'2025'!X$2,Tabla1[ANY],'2025'!$Z$2) -> 600 | Y20: =IF($X$13=0,0,X20/X$13) -> 1 | Z20: =B20+D20+F20+H20+J20+L20+N20+P20+R20+T20+V20+X20 -> 1220 | AA20: =IF($Z$13=0,0,Z20/Z$13) -> 0.25363825 | AB20: =Z20/$A$2 -> 203.33333
A21: Especial | B21: =SUMIFS('Registre de reserves'!$P$2:$P$1178,'Registre de reserves'!$T$2:$T$1178,"NO",'Registre de reserves'!$I$2:$I$1178,'2025'!$A21,'Registre de reserves'!$B$2:$B$1178,'2025'!B$2,Tabla1[ANY],'2025'!$Z$2)+SUMIFS('Registre de reserves'!$P$2:$P$1178,'Registre de reserves'!$T$2:$T$1178,"RESERVA",'Registre de reserves'!$I$2:$I$1178,'2025'!$A21,'Registre de reserves'!$B$2:$B$1178,'2025'!B$2,Tabla1[ANY],'2025'!$Z$2)-SUMIFS('Registre de reserves'!$U$2:$U$1178,'Registre de reserves'!$T$2:$T$1178,"RESERVA",'Registre de reserves'!$I$2:$I$1178,'2025'!$A21,'Registre de reserves'!$B$2:$B$1178,'2025'!B$2,Tabla1[ANY],'2025'!$Z$2) -> 0 | C21: =IF($B$13=0,0,B21/B$13) -> 0 | D21: =SUMIFS('Registre de reserves'!$P$2:$P$1178,'Registre de reserves'!$T$2:$T$1178,"NO",'Registre de reserves'!$I$2:$I$1178,'2025'!$A21,'Registre de reserves'!$B$2:$B$1178,'2025'!D$2,Tabla1[ANY],'2025'!$Z$2)+SUMIFS('Registre de reserves'!$P$2:$P$1178,'Registre de reserves'!$T$2:$T$1178,"RESERVA",'Registre de reserves'!$I$2:$I$1178,'2025'!$A21,'Registre de reserves'!$B$2:$B$1178,'2025'!D$2,Tabla1[ANY],'2025'!$Z$2)-SUMIFS('Registre de reserves'!$U$2:$U$1178,'Registre de reserves'!$T$2:$T$1178,"RESERVA",'Registre de reserves'!$I$2:$I$1178,'2025'!$A21,'Registre de reserves'!$B$2:$B$1178,'2025'!D$2,Tabla1[ANY],'2025'!$Z$2) -> 0 | E21: =IF($D$13=0,0,D21/D$13) -> 0 | F21: =SUMIFS('Registre de reserves'!$P$2:$P$1178,'Registre de reserves'!$T$2:$T$1178,"NO",'Registre de reserves'!$I$2:$I$1178,'2025'!$A21,'Registre de reserves'!$B$2:$B$1178,'2025'!F$2,Tabla1[ANY],'2025'!$Z$2)+SUMIFS('Registre de reserves'!$P$2:$P$1178,'Registre de reserves'!$T$2:$T$1178,"RESERVA",'Registre de reserves'!$I$2:$I$1178,'2025'!$A21,'Registre de reserves'!$B$2:$B$1178,'2025'!F$2,Tabla1[ANY],'2025'!$Z$2)-SUMIFS('Registre de reserves'!$U$2:$U$1178,'Registre de reserves'!$T$2:$T$1178,"RESERVA",'Registre de reserves'!$I$2:$I$1178,'2025'!$A21,'Registre de reserves'!$B$2:$B$1178,'2025'!F$2,Tabla1[ANY],'2025'!$Z$2) -> 0 | G21: =IF($F$13=0,0,F21/F$13) -> 0 | H21: =SUMIFS('Registre de reserves'!$P$2:$P$1178,'Registre de reserves'!$T$2:$T$1178,"NO",'Registre de reserves'!$I$2:$I$1178,'2025'!$A21,'Registre de reserves'!$B$2:$B$1178,'2025'!H$2,Tabla1[ANY],'2025'!$Z$2)+SUMIFS('Registre de reserves'!$P$2:$P$1178,'Registre de reserves'!$T$2:$T$1178,"RESERVA",'Registre de reserves'!$I$2:$I$1178,'2025'!$A21,'Registre de reserves'!$B$2:$B$1178,'2025'!H$2,Tabla1[ANY],'2025'!$Z$2)-SUMIFS('Registre de reserves'!$U$2:$U$1178,'Registre de reserves'!$T$2:$T$1178,"RESERVA",'Registre de reserves'!$I$2:$I$1178,'2025'!$A21,'Registre de reserves'!$B$2:$B$1178,'2025'!H$2,Tabla1[ANY],'2025'!$Z$2) -> 0 | I21: =IF($H$13=0,0,H21/H$13) -> 0 | J21: =SUMIFS('Registre de reserves'!$P$2:$P$1178,'Registre de reserves'!$T$2:$T$1178,"NO",'Registre de reserves'!$I$2:$I$1178,'2025'!$A21,'Registre de reserves'!$B$2:$B$1178,'2025'!J$2,Tabla1[ANY],'2025'!$Z$2)+SUMIFS('Registre de reserves'!$P$2:$P$1178,'Registre de reserves'!$T$2:$T$1178,"RESERVA",'Registre de reserves'!$I$2:$I$1178,'2025'!$A21,'Registre de reserves'!$B$2:$B$1178,'2025'!J$2,Tabla1[ANY],'2025'!$Z$2)-SUMIFS('Registre de reserves'!$U$2:$U$1178,'Registre de reserves'!$T$2:$T$1178,"RESERVA",'Registre de reserves'!$I$2:$I$1178,'2025'!$A21,'Registre de reserves'!$B$2:$B$1178,'2025'!J$2,Tabla1[ANY],'2025'!$Z$2) -> 0 | K21: =IF($J$13=0,0,J21/J$13) -> 0 | L21: =SUMIFS('Registre de reserves'!$P$2:$P$1178,'Registre de reserves'!$T$2:$T$1178,"NO",'Registre de reserves'!$I$2:$I$1178,'2025'!$A21,'Registre de reserves'!$B$2:$B$1178,'2025'!L$2,Tabla1[ANY],'2025'!$Z$2)+SUMIFS('Registre de reserves'!$P$2:$P$1178,'Registre de reserves'!$T$2:$T$1178,"RESERVA",'Registre de reserves'!$I$2:$I$1178,'2025'!$A21,'Registre de reserves'!$B$2:$B$1178,'2025'!L$2,Tabla1[ANY],'2025'!$Z$2)-SUMIFS('Registre de reserves'!$U$2:$U$1178,'Registre de reserves'!$T$2:$T$1178,"RESERVA",'Registre de reserves'!$I$2:$I$1178,'2025'!$A21,'Registre de reserves'!$B$2:$B$1178,'2025'!L$2,Tabla1[ANY],'2025'!$Z$2) -> 0 | M21: =IF($L$13=0,0,L21/L$13) -> 0 | N21: =SUMIFS('Registre de reserves'!$P$2:$P$1178,'Registre de reserves'!$T$2:$T$1178,"NO",'Registre de reserves'!$I$2:$I$1178,'2025'!$A21,'Registre de reserves'!$B$2:$B$1178,'2025'!N$2,Tabla1[ANY],'2025'!$Z$2)+SUMIFS('Registre de reserves'!$P$2:$P$1178,'Registre de reserves'!$T$2:$T$1178,"RESERVA",'Registre de reserves'!$I$2:$I$1178,'2025'!$A21,'Registre de reserves'!$B$2:$B$1178,'2025'!N$2,Tabla1[ANY],'2025'!$Z$2)-SUMIFS('Registre de reserves'!$U$2:$U$1178,'Registre de reserves'!$T$2:$T$1178,"RESERVA",'Registre de reserves'!$I$2:$I$1178,'2025'!$A21,'Registre de reserves'!$B$2:$B$1178,'2025'!N$2,Tabla1[ANY],'2025'!$Z$2) -> 0 | O21: =IF($N$13=0,0,N21/N$13) -> 0 | P21: =SUMIFS('Registre de reserves'!$P$2:$P$1178,'Registre de reserves'!$T$2:$T$1178,"NO",'Registre de reserves'!$I$2:$I$1178,'2025'!$A21,'Registre de reserves'!$B$2:$B$1178,'2025'!P$2,Tabla1[ANY],'2025'!$Z$2)+SUMIFS('Registre de reserves'!$P$2:$P$1178,'Registre de reserves'!$T$2:$T$1178,"RESERVA",'Registre de reserves'!$I$2:$I$1178,'2025'!$A21,'Registre de reserves'!$B$2:$B$1178,'2025'!P$2,Tabla1[ANY],'2025'!$Z$2)-SUMIFS('Registre de reserves'!$U$2:$U$1178,'Registre de reserves'!$T$2:$T$1178,"RESERVA",'Registre de reserves'!$I$2:$I$1178,'2025'!$A21,'Registre de reserves'!$B$2:$B$1178,'2025'!P$2,Tabla1[ANY],'2025'!$Z$2) -> 0 | Q21: =IF($P$13=0,0,P21/P$13) -> 0 | R21: =SUMIFS('Registre de reserves'!$P$2:$P$1178,'Registre de reserves'!$T$2:$T$1178,"NO",'Registre de reserves'!$I$2:$I$1178,'2025'!$A21,'Registre de reserves'!$B$2:$B$1178,'2025'!R$2,Tabla1[ANY],'2025'!$Z$2)+SUMIFS('Registre de reserves'!$P$2:$P$1178,'Registre de reserves'!$T$2:$T$1178,"RESERVA",'Registre de reserves'!$I$2:$I$1178,'2025'!$A21,'Registre de reserves'!$B$2:$B$1178,'2025'!R$2,Tabla1[ANY],'2025'!$Z$2)-SUMIFS('Registre de reserves'!$U$2:$U$1178,'Registre de reserves'!$T$2:$T$1178,"RESERVA",'Registre de reserves'!$I$2:$I$1178,'2025'!$A21,'Registre de reserves'!$B$2:$B$1178,'2025'!R$2,Tabla1[ANY],'2025'!$Z$2) -> 0 | S21: =IF($R$13=0,0,R21/R$13) -> 0 | T21: =SUMIFS('Registre de reserves'!$P$2:$P$1178,'Registre de reserves'!$T$2:$T$1178,"NO",'Registre de reserves'!$I$2:$I$1178,'2025'!$A21,'Registre de reserves'!$B$2:$B$1178,'2025'!T$2,Tabla1[ANY],'2025'!$Z$2)+SUMIFS('Registre de reserves'!$P$2:$P$1178,'Registre de reserves'!$T$2:$T$1178,"RESERVA",'Registre de reserves'!$I$2:$I$1178,'2025'!$A21,'Registre de reserves'!$B$2:$B$1178,'2025'!T$2,Tabla1[ANY],'2025'!$Z$2)-SUMIFS('Registre de reserves'!$U$2:$U$1178,'Registre de reserves'!$T$2:$T$1178,"RESERVA",'Registre de reserves'!$I$2:$I$1178,'2025'!$A21,'Registre de reserves'!$B$2:$B$1178,'2025'!T$2,Tabla1[ANY],'2025'!$Z$2) -> 0 | U21: =IF($T$13=0,0,T21/T$13) -> 0 | V21: =SUMIFS('Registre de reserves'!$P$2:$P$1178,'Registre de reserves'!$T$2:$T$1178,"NO",'Registre de reserves'!$I$2:$I$1178,'2025'!$A21,'Registre de reserves'!$B$2:$B$1178,'2025'!V$2,Tabla1[ANY],'2025'!$Z$2)+SUMIFS('Registre de reserves'!$P$2:$P$1178,'Registre de reserves'!$T$2:$T$1178,"RESERVA",'Registre de reserves'!$I$2:$I$1178,'2025'!$A21,'Registre de reserves'!$B$2:$B$1178,'2025'!V$2,Tabla1[ANY],'2025'!$Z$2)-SUMIFS('Registre de reserves'!$U$2:$U$1178,'Registre de reserves'!$T$2:$T$1178,"RESERVA",'Registre de reserves'!$I$2:$I$1178,'2025'!$A21,'Registre de reserves'!$B$2:$B$1178,'2025'!V$2,Tabla1[ANY],'2025'!$Z$2) -> 0 | W21: =IF($V$13=0,0,V21/V$13) -> 0 | X21: =SUMIFS('Registre de reserves'!$P$2:$P$1178,'Registre de reserves'!$T$2:$T$1178,"NO",'Registre de reserves'!$I$2:$I$1178,'2025'!$A21,'Registre de reserves'!$B$2:$B$1178,'2025'!X$2,Tabla1[ANY],'2025'!$Z$2)+SUMIFS('Registre de reserves'!$P$2:$P$1178,'Registre de reserves'!$T$2:$T$1178,"RESERVA",'Registre de reserves'!$I$2:$I$1178,'2025'!$A21,'Registre de reserves'!$B$2:$B$1178,'2025'!X$2,Tabla1[ANY],'2025'!$Z$2)-SUMIFS('Registre de reserves'!$U$2:$U$1178,'Registre de reserves'!$T$2:$T$1178,"RESERVA",'Registre de reserves'!$I$2:$I$1178,'2025'!$A21,'Registre de reserves'!$B$2:$B$1178,'2025'!X$2,Tabla1[ANY],'2025'!$Z$2) -> 0 | Y21: =IF($X$13=0,0,X21/X$13) -> 0 | Z21: =B21+D21+F21+H21+J21+L21+N21+P21+R21+T21+V21+X21 -> 0 | AA21: =IF($Z$13=0,0,Z21/Z$13) -> 0 | AB21: =Z21/$A$2 -> 0
A22: Hores extres efectives | B22: =SUM(B23:B30) -> 300 | C22: =IF(B$3=0,0,B22/B$3) -> 0.061664954 | D22: =SUM(D23:D30) -> 80 | E22: =IF(D$3=0,0,D22/D$3) -> 0.021828104 | F22: =SUM(F23:F30) -> 0 | G22: =IF(F$3=0,0,F22/F$3) -> 0 | H22: =SUM(H23:H30) -> 180 | I22: =IF(H$3=0,0,H22/H$3) -> 0.055130168 | J22: =SUM(J23:J30) -> 90 | K22: =IF(J$3=0,0,J22/J$3) -> 0.023809524 | L22: =SUM(L23:L30) -> 60 | M22: =IF(L$3=0,0,L22/L$3) -> 0.01754386 | N22: =SUM(N23:N30) -> 0 | O22: =IF(N$3=0,0,N22/N$3) -> 0 | P22: =SUM(P23:P30) -> 0 | Q22: =IF(P$3=0,0,P22/P$3) -> 0 | R22: =SUM(R23:R30) -> 0 | S22: =IF(R$3=0,0,R22/R$3) -> 0 | T22: =SUM(T23:T30) -> 0 | U22: =IF(T$3=0,0,T22/T$3) -> 0 | V22: =SUM(V23:V30) -> 0 | W22: =IF(V$3=0,0,V22/V$3) -> 0 | X22: =SUM(X23:X30) -> 0 | Y22: =IF(X$3=0,0,X22/X$3) -> 0 | Z22: =SUM(Z23:Z30) -> 710 | AA22: =IF(Z$3=0,0,Z22/Z$3) -> 0.030909882 | AB22: =Z22/$A$2 -> 118.33333
A23: Mati | B23: =SUMIFS('Registre de reserves'!$R$2:$R$1178,'Registre de reserves'!$T$2:$T$1178,"SI",'Registre de reserves'!$I$2:$I$1178,'2025'!$A23,'Registre de reserves'!$B$2:$B$1178,'2025'!B$2,Tabla1[ANY],'2025'!$Z$2) -> 0 | C23: =IF(B$22=0,0,B23/B$22) -> 0 | D23: =SUMIFS('Registre de reserves'!$R$2:$R$1178,'Registre de reserves'!$T$2:$T$1178,"SI",'Registre de reserves'!$I$2:$I$1178,'2025'!$A23,'Registre de reserves'!$B$2:$B$1178,'2025'!D$2,Tabla1[ANY],'2025'!$Z$2) -> 20 | E23: =IF(D$22=0,0,D23/D$22) -> 0.25 | F23: =SUMIFS('Registre de reserves'!$R$2:$R$1178,'Registre de reserves'!$T$2:$T$1178,"SI",'Registre de reserves'!$I$2:$I$1178,'2025'!$A23,'Registre de reserves'!$B$2:$B$1178,'2025'!F$2,Tabla1[ANY],'2025'!$Z$2) -> 0 | G23: =IF(F$22=0,0,F23/F$22) -> 0 | H23: =SUMIFS('Registre de reserves'!$R$2:$R$1178,'Registre de reserves'!$T$2:$T$1178,"SI",'Registre de reserves'!$I$2:$I$1178,'2025'!$A23,'Registre de reserves'!$B$2:$B$1178,'2025'!H$2,Tabla1[ANY],'2025'!$Z$2) -> 0 | I23: =IF(H$22=0,0,H23/H$22) -> 0 | J23: =SUMIFS('Registre de reserves'!$R$2:$R$1178,'Registre de reserves'!$T$2:$T$1178,"SI",'Registre de reserves'!$I$2:$I$1178,'2025'!$A23,'Registre de reserves'!$B$2:$B$1178,'2025'!J$2,Tabla1[ANY],'2025'!$Z$2) -> 0 | K23: =IF(J$22=0,0,J23/J$22) -> 0 | L23: =SUMIFS('Registre de reserves'!$R$2:$R$1178,'Registre de reserves'!$T$2:$T$1178,"SI",'Registre de reserves'!$I$2:$I$1178,'2025'!$A23,'Registre de reserves'!$B$2:$B$1178,'2025'!L$2,Tabla1[ANY],'2025'!$Z$2) -> 0 | M23: =IF(L$22=0,0,L23/L$22) -> 0 | N23: =SUMIFS('Registre de reserves'!$R$2:$R$1178,'Registre de reserves'!$T$2:$T$1178,"SI",'Registre de reserves'!$I$2:$I$1178,'2025'!$A23,'Registre de reserves'!$B$2:$B$1178,'2025'!N$2,Tabla1[ANY],'2025'!$Z$2) -> 0 | O23: =IF(N$22=0,0,N23/N$22) -> 0 | P23: =SUMIFS('Registre de reserves'!$R$2:$R$1178,'Registre de reserves'!$T$2:$T$1178,"SI",'Registre de reserves'!$I$2:$I$1178,'2025'!$A23,'Registre de reserves'!$B$2:$B$1178,'2025'!P$2,Tabla1[ANY],'2025'!$Z$2) -> 0 | Q23: =IF(P$22=0,0,P23/P$22) -> 0 | R23: =SUMIFS('Registre de reserves'!$R$2:$R$1178,'Registre de reserves'!$T$2:$T$1178,"SI",'Registre de reserves'!$I$2:$I$1178,'2025'!$A23,'Registre de reserves'!$B$2:$B$1178,'2025'!R$2,Tabla1[ANY],'2025'!$Z$2) -> 0 | S23: =IF(R$22=0,0,R23/R$22) -> 0 | T23: =SUMIFS('Registre de reserves'!$R$2:$R$1178,'Registre de reserves'!$T$2:$T$1178,"SI",'Registre de reserves'!$I$2:$I$1178,'2025'!$A23,'Registre de reserves'!$B$2:$B$1178,'2025'!T$2,Tabla1[ANY],'2025'!$Z$2) -> 0 | U23: =IF(T$22=0,0,T23/T$22) -> 0 | V23: =SUMIFS('Registre de reserves'!$R$2:$R$1178,'Registre de reserves'!$T$2:$T$1178,"SI",'Registre de reserves'!$I$2:$I$1178,'2025'!$A23,'Registre de reserves'!$B$2:$B$1178,'2025'!V$2,Tabla1[ANY],'2025'!$Z$2) -> 0 | W23: =IF(V$22=0,0,V23/V$22) -> 0 | X23: =SUMIFS('Registre de reserves'!$R$2:$R$1178,'Registre de reserves'!$T$2:$T$1178,"SI",'Registre de reserves'!$I$2:$I$1178,'2025'!$A23,'Registre de reserves'!$B$2:$B$1178,'2025'!X$2,Tabla1[ANY],'2025'!$Z$2) -> 0 | Y23: =IF(X$22=0,0,X23/X$22) -> 0 | Z23: =B23+D23+F23+H23+J23+L23+N23+P23+R23+T23+V23+X23 -> 20 | AA23: =IF(Z$22=0,0,Z23/Z$22) -> 0.028169014 | AB23: =Z23/$A$2 -> 3.3333333
A24: Tarda | B24: =SUMIFS('Registre de reserves'!$R$2:$R$1178,'Registre de reserves'!$T$2:$T$1178,"SI",'Registre de reserves'!$I$2:$I$1178,'2025'!$A24,'Registre de reserves'!$B$2:$B$1178,'2025'!B$2,Tabla1[ANY],'2025'!$Z$2) -> 0 | C24: =IF(B$22=0,0,B24/B$22) -> 0 | D24: =SUMIFS('Registre de reserves'!$R$2:$R$1178,'Registre de reserves'!$T$2:$T$1178,"SI",'Registre de reserves'!$I$2:$I$1178,'2025'!$A24,'Registre de reserves'!$B$2:$B$1178,'2025'!D$2,Tabla1[ANY],'2025'!$Z$2) -> 0 | E24: =IF(D$22=0,0,D24/D$22) -> 0 | F24: =SUMIFS('Registre de reserves'!$R$2:$R$1178,'Registre de reserves'!$T$2:$T$1178,"SI",'Registre de reserves'!$I$2:$I$1178,'2025'!$A24,'Registre de reserves'!$B$2:$B$1178,'2025'!F$2,Tabla1[ANY],'2025'!$Z$2) -> 0 | G24: =IF(F$22=0,0,F24/F$22) -> 0 | H24: =SUMIFS('Registre de reserves'!$R$2:$R$1178,'Registre de reserves'!$T$2:$T$1178,"SI",'Registre de reserves'!$I$2:$I$1178,'2025'!$A24,'Registre de reserves'!$B$2:$B$1178,'2025'!H$2,Tabla1[ANY],'2025'!$Z$2) -> 0 | I24: =IF(H$22=0,0,H24/H$22) -> 0 | J24: =SUMIFS('Registre de reserves'!$R$2:$R$1178,'Registre de reserves'!$T$2:$T$1178,"SI",'Registre de reserves'!$I$2:$I$1178,'2025'!$A24,'Registre de reserves'!$B$2:$B$1178,'2025'!J$2,Tabla1[ANY],'2025'!$Z$2) -> 30 | K24: =IF(J$22=0,0,J24/J$22) -> 0.33333333 | L24: =SUMIFS('Registre de reserves'!$R$2:$R$1178,'Registre de reserves'!$T$2:$T$1178,"SI",'Registre de reserves'!$I$2:$I$1178,'2025'!$A24,'Registre de reserves'!$B$2:$B$1178,'2025'!L$2,Tabla1[ANY],'2025'!$Z$2) -> 0 | M24: =IF(L$22=0,0,L24/L$22) -> 0 | N24: =SUMIFS('Registre de reserves'!$R$2:$R$1178,'Registre de reserves'!$T$2:$T$1178,"SI",'Registre de reserves'!$I$2:$I$1178,'2025'!$A24,'Registre de reserves'!$B$2:$B$1178,'2025'!N$2,Tabla1[ANY],'2025'!$Z$2) -> 0 | O24: =IF(N$22=0,0,N24/N$22) -> 0 | P24: =SUMIFS('Registre de reserves'!$R$2:$R$1178,'Registre de reserves'!$T$2:$T$1178,"SI",'Registre de reserves'!$I$2:$I$1178,'2025'!$A24,'Registre de reserves'!$B$2:$B$1178,'2025'!P$2,Tabla1[ANY],'2025'!$Z$2) -> 0 | Q24: =IF(P$22=0,0,P24/P$22) -> 0 | R24: =SUMIFS('Registre de reserves'!$R$2:$R$1178,'Registre de reserves'!$T$2:$T$1178,"SI",'Registre de reserves'!$I$2:$I$1178,'2025'!$A24,'Registre de reserves'!$B$2:$B$1178,'2025'!R$2,Tabla1[ANY],'2025'!$Z$2) -> 0 | S24: =IF(R$22=0,0,R24/R$22) -> 0 | T24: =SUMIFS('Registre de reserves'!$R$2:$R$1178,'Registre de reserves'!$T$2:$T$1178,"SI",'Registre de reserves'!$I$2:$I$1178,'2025'!$A24,'Registre de reserves'!$B$2:$B$1178,'2025'!T$2,Tabla1[ANY],'2025'!$Z$2) -> 0 | U24: =IF(T$22=0,0,T24/T$22) -> 0 | V24: =SUMIFS('Registre de reserves'!$R$2:$R$1178,'Registre de reserves'!$T$2:$T$1178,"SI",'Registre de reserves'!$I$2:$I$1178,'2025'!$A24,'Registre de reserves'!$B$2:$B$1178,'2025'!V$2,Tabla1[ANY],'2025'!$Z$2) -> 0 | W24: =IF(V$22=0,0,V24/V$22) -> 0 | X24: =SUMIFS('Registre de reserves'!$R$2:$R$1178,'Registre de reserves'!$T$2:$T$1178,"SI",'Registre de reserves'!$I$2:$I$1178,'2025'!$A24,'Registre de reserves'!$B$2:$B$1178,'2025'!X$2,Tabla1[ANY],'2025'!$Z$2) -> 0 | Y24: =IF(X$22=0,0,X24/X$22) -> 0 | Z24: =B24+D24+F24+H24+J24+L24+N24+P24+R24+T24+V24+X24 -> 30 | AA24: =IF(Z$22=0,0,Z24/Z$22) -> 0.042253521 | AB24: =Z24/$A$2 -> 5
A25: Dia sencer | B25: =SUMIFS('Registre de reserves'!$R$2:$R$1178,'Registre de reserves'!$T$2:$T$1178,"SI",'Registre de reserves'!$I$2:$I$1178,'2025'!$A25,'Registre de reserves'!$B$2:$B$1178,'2025'!B$2,Tabla1[ANY],'2025'!$Z$2) -> 60 | C25: =IF(B$22=0,0,B25/B$22) -> 0.2 | D25: =SUMIFS('Registre de reserves'!$R$2:$R$1178,'Registre de reserves'!$T$2:$T$1178,"SI",'Registre de reserves'!$I$2:$I$1178,'2025'!$A25,'Registre de reserves'!$B$2:$B$1178,'2025'!D$2,Tabla1[ANY],'2025'!$Z$2) -> 0 | E25: =IF(D$22=0,0,D25/D$22) -> 0 | F25: =SUMIFS('Registre de reserves'!$R$2:$R$1178,'Registre de reserves'!$T$2:$T$1178,"SI",'Registre de reserves'!$I$2:$I$1178,'2025'!$A25,'Registre de reserves'!$B$2:$B$1178,'2025'!F$2,Tabla1[ANY],'2025'!$Z$2) -> 0 | G25: =IF(F$22=0,0,F25/F$22) -> 0 | H25: =SUMIFS('Registre de reserves'!$R$2:$R$1178,'Registre de reserves'!$T$2:$T$1178,"SI",'Registre de reserves'!$I$2:$I$1178,'2025'!$A25,'Registre de reserves'!$B$2:$B$1178,'2025'!H$2,Tabla1[ANY],'2025'!$Z$2) -> 0 | I25: =IF(H$22=0,0,H25/H$22) -> 0 | J25: =SUMIFS('Registre de reserves'!$R$2:$R$1178,'Registre de reserves'!$T$2:$T$1178,"SI",'Registre de reserves'!$I$2:$I$1178,'2025'!$A25,'Registre de reserves'!$B$2:$B$1178,'2025'!J$2,Tabla1[ANY],'2025'!$Z$2) -> 0 | K25: =IF(J$22=0,0,J25/J$22) -> 0 | L25: =SUMIFS('Registre de reserves'!$R$2:$R$1178,'Registre de reserves'!$T$2:$T$1178,"SI",'Registre de reserves'!$I$2:$I$1178,'2025'!$A25,'Registre de reserves'!$B$2:$B$1178,'2025'!L$2,Tabla1[ANY],'2025'!$Z$2) -> 0 | M25: =IF(L$22=0,0,L25/L$22) -> 0 | N25: =SUMIFS('Registre de reserves'!$R$2:$R$1178,'Registre de reserves'!$T$2:$T$1178,"SI",'Registre de reserves'!$I$2:$I$1178,'2025'!$A25,'Registre de reserves'!$B$2:$B$1178,'2025'!N$2,Tabla1[ANY],'2025'!$Z$2) -> 0 | O25: =IF(N$22=0,0,N25/N$22) -> 0 | P25: =SUMIFS('Registre de reserves'!$R$2:$R$1178,'Registre de reserves'!$T$2:$T$1178,"SI",'Registre de reserves'!$I$2:$I$1178,'2025'!$A25,'Registre de reserves'!$B$2:$B$1178,'2025'!P$2,Tabla1[ANY],'2025'!$Z$2) -> 0 | Q25: =IF(P$22=0,0,P25/P$22) -> 0 | R25: =SUMIFS('Registre de reserves'!$R$2:$R$1178,'Registre de reserves'!$T$2:$T$1178,"SI",'Registre de reserves'!$I$2:$I$1178,'2025'!$A25,'Registre de reserves'!$B$2:$B$1178,'2025'!R$2,Tabla1[ANY],'2025'!$Z$2) -> 0 | S25: =IF(R$22=0,0,R25/R$22) -> 0 | T25: =SUMIFS('Registre de reserves'!$R$2:$R$1178,'Registre de reserves'!$T$2:$T$1178,"SI",'Registre de reserves'!$I$2:$I$1178,'2025'!$A25,'Registre de reserves'!$B$2:$B$1178,'2025'!T$2,Tabla1[ANY],'2025'!$Z$2) -> 0 | U25: =IF(T$22=0,0,T25/T$22) -> 0 | V25: =SUMIFS('Registre de reserves'!$R$2:$R$1178,'Registre de reserves'!$T$2:$T$1178,"SI",'Registre de reserves'!$I$2:$I$1178,'2025'!$A25,'Registre de reserves'!$B$2:$B$1178,'2025'!V$2,Tabla1[ANY],'2025'!$Z$2) -> 0 | W25: =IF(V$22=0,0,V25/V$22) -> 0 | X25: =SUMIFS('Registre de reserves'!$R$2:$R$1178,'Registre de reserves'!$T$2:$T$1178,"SI",'Registre de reserves'!$I$2:$I$1178,'2025'!$A25,'Registre de reserves'!$B$2:$B$1178,'2025'!X$2,Tabla1[ANY],'2025'!$Z$2) -> 0 | Y25: =IF(X$22=0,0,X25/X$22) -> 0 | Z25: =B25+D25+F25+H25+J25+L25+N25+P25+R25+T25+V25+X25 -> 60 | AA25: =IF(Z$22=0,0,Z25/Z$22) -> 0.084507042 | AB25: =Z25/$A$2 -> 10
A26: Dinar | B26: =SUMIFS('Registre de reserves'!$R$2:$R$1178,'Registre de reserves'!$T$2:$T$1178,"SI",'Registre de reserves'!$I$2:$I$1178,'2025'!$A26,'Registre de reserves'!$B$2:$B$1178,'2025'!B$2,Tabla1[ANY],'2025'!$Z$2) -> 0 | C26: =IF(B$22=0,0,B26/B$22) -> 0 | D26: =SUMIFS('Registre de reserves'!$R$2:$R$1178,'Registre de reserves'!$T$2:$T$1178,"SI",'Registre de reserves'!$I$2:$I$1178,'2025'!$A26,'Registre de reserves'!$B$2:$B$1178,'2025'!D$2,Tabla1[ANY],'2025'!$Z$2) -> 0 | E26: =IF(D$22=0,0,D26/D$22) -> 0 | F26: =SUMIFS('Registre de reserves'!$R$2:$R$1178,'Registre de reserves'!$T$2:$T$1178,"SI",'Registre de reserves'!$I$2:$I$1178,'2025'!$A26,'Registre de reserves'!$B$2:$B$1178,'2025'!F$2,Tabla1[ANY],'2025'!$Z$2) -> 0 | G26: =IF(F$22=0,0,F26/F$22) -> 0 | H26: =SUMIFS('Registre de reserves'!$R$2:$R$1178,'Registre de reserves'!$T$2:$T$1178,"SI",'Registre de reserves'!$I$2:$I$1178,'2025'!$A26,'Registre de reserves'!$B$2:$B$1178,'2025'!H$2,Tabla1[ANY],'2025'!$Z$2) -> 0 | I26: =IF(H$22=0,0,H26/H$22) -> 0 | J26: =SUMIFS('Registre de reserves'!$R$2:$R$1178,'Registre de reserves'!$T$2:$T$1178,"SI",'Registre de reserves'!$I$2:$I$1178,'2025'!$A26,'Registre de reserves'!$B$2:$B$1178,'2025'!J$2,Tabla1[ANY],'2025'!$Z$2) -> 0 | K26: =IF(J$22=0,0,J26/J$22) -> 0 | L26: =SUMIFS('Registre de reserves'!$R$2:$R$1178,'Registre de reserves'!$T$2:$T$1178,"SI",'Registre de reserves'!$I$2:$I$1178,'2025'!$A26,'Registre de reserves'!$B$2:$B$1178,'2025'!L$2,Tabla1[ANY],'2025'!$Z$2) -> 0 | M26: =IF(L$22=0,0,L26/L$22) -> 0 | N26: =SUMIFS('Registre de reserves'!$R$2:$R$1178,'Registre de reserves'!$T$2:$T$1178,"SI",'Registre de reserves'!$I$2:$I$1178,'2025'!$A26,'Registre de reserves'!$B$2:$B$1178,'2025'!N$2,Tabla1[ANY],'2025'!$Z$2) -> 0 | O26: =IF(N$22=0,0,N26/N$22) -> 0 | P26: =SUMIFS('Registre de reserves'!$R$2:$R$1178,'Registre de reserves'!$T$2:$T$1178,"SI",'Registre de reserves'!$I$2:$I$1178,'2025'!$A26,'Registre de reserves'!$B$2:$B$1178,'2025'!P$2,Tabla1[ANY],'2025'!$Z$2) -> 0 | Q26: =IF(P$22=0,0,P26/P$22) -> 0 | R26: =SUMIFS('Registre de reserves'!$R$2:$R$1178,'Registre de reserves'!$T$2:$T$1178,"SI",'Registre de reserves'!$I$2:$I$1178,'2025'!$A26,'Registre de reserves'!$B$2:$B$1178,'2025'!R$2,Tabla1[ANY],'2025'!$Z$2) -> 0 | S26: =IF(R$22=0,0,R26/R$22) -> 0 | T26: =SUMIFS('Registre de reserves'!$R$2:$R$1178,'Registre de reserves'!$T$2:$T$1178,"SI",'Registre de reserves'!$I$2:$I$1178,'2025'!$A26,'Registre de reserves'!$B$2:$B$1178,'2025'!T$2,Tabla1[ANY],'2025'!$Z$2) -> 0 | U26: =IF(T$22=0,0,T26/T$22) -> 0 | V26: =SUMIFS('Registre de reserves'!$R$2:$R$1178,'Registre de reserves'!$T$2:$T$1178,"SI",'Registre de reserves'!$I$2:$I$1178,'2025'!$A26,'Registre de reserves'!$B$2:$B$1178,'2025'!V$2,Tabla1[ANY],'2025'!$Z$2) -> 0 | W26: =IF(V$22=0,0,V26/V$22) -> 0 | X26: =SUMIFS('Registre de reserves'!$R$2:$R$1178,'Registre de reserves'!$T$2:$T$1178,"SI",'Registre de reserves'!$I$2:$I$1178,'2025'!$A26,'Registre de reserves'!$B$2:$B$1178,'2025'!X$2,Tabla1[ANY],'2025'!$Z$2) -> 0 | Y26: =IF(X$22=0,0,X26/X$22) -> 0 | Z26: =B26+D26+F26+H26+J26+L26+N26+P26+R26+T26+V26+X26 -> 0 | AA26: =IF(Z$22=0,0,Z26/Z$22) -> 0 | AB26: =Z26/$A$2 -> 0
A27: Sopar | B27: =SUMIFS('Registre de reserves'!$R$2:$R$1178,'Registre de reserves'!$T$2:$T$1178,"SI",'Registre de reserves'!$I$2:$I$1178,'2025'!$A27,'Registre de reserves'!$B$2:$B$1178,'2025'!B$2,Tabla1[ANY],'2025'!$Z$2) -> 0 | C27: =IF(B$22=0,0,B27/B$22) -> 0 | D27: =SUMIFS('Registre de reserves'!$R$2:$R$1178,'Registre de reserves'!$T$2:$T$1178,"SI",'Registre de reserves'!$I$2:$I$1178,'2025'!$A27,'Registre de reserves'!$B$2:$B$1178,'2025'!D$2,Tabla1[ANY],'2025'!$Z$2) -> 0 | E27: =IF(D$22=0,0,D27/D$22) -> 0 | F27: =SUMIFS('Registre de reserves'!$R$2:$R$1178,'Registre de reserves'!$T$2:$T$1178,"SI",'Registre de reserves'!$I$2:$I$1178,'2025'!$A27,'Registre de reserves'!$B$2:$B$1178,'2025'!F$2,Tabla1[ANY],'2025'!$Z$2) -> 0 | G27: =IF(F$22=0,0,F27/F$22) -> 0 | H27: =SUMIFS('Registre de reserves'!$R$2:$R$1178,'Registre de reserves'!$T$2:$T$1178,"SI",'Registre de reserves'!$I$2:$I$1178,'2025'!$A27,'Registre de reserves'!$B$2:$B$1178,'2025'!H$2,Tabla1[ANY],'2025'!$Z$2) -> 0 | I27: =IF(H$22=0,0,H27/H$22) -> 0 | J27: =SUMIFS('Registre de reserves'!$R$2:$R$1178,'Registre de reserves'!$T$2:$T$1178,"SI",'Registre de reserves'!$I$2:$I$1178,'2025'!$A27,'Registre de reserves'!$B$2:$B$1178,'2025'!J$2,Tabla1[ANY],'2025'!$Z$2) -> 0 | K27: =IF(J$22=0,0,J27/J$22) -> 0 | L27: =SUMIFS('Registre de reserves'!$R$2:$R$1178,'Registre de reserves'!$T$2:$T$1178,"SI",'Registre de reserves'!$I$2:$I$1178,'2025'!$A27,'Registre de reserves'!$B$2:$B$1178,'2025'!L$2,Tabla1[ANY],'2025'!$Z$2) -> 0 | M27: =IF(L$22=0,0,L27/L$22) -> 0 | N27: =SUMIFS('Registre de reserves'!$R$2:$R$1178,'Registre de reserves'!$T$2:$T$1178,"SI",'Registre de reserves'!$I$2:$I$1178,'2025'!$A27,'Registre de reserves'!$B$2:$B$1178,'2025'!N$2,Tabla1[ANY],'2025'!$Z$2) -> 0 | O27: =IF(N$22=0,0,N27/N$22) -> 0 | P27: =SUMIFS('Registre de reserves'!$R$2:$R$1178,'Registre de reserves'!$T$2:$T$1178,"SI",'Registre de reserves'!$I$2:$I$1178,'2025'!$A27,'Registre de reserves'!$B$2:$B$1178,'2025'!P$2,Tabla1[ANY],'2025'!$Z$2) -> 0 | Q27: =IF(P$22=0,0,P27/P$22) -> 0 | R27: =SUMIFS('Registre de reserves'!$R$2:$R$1178,'Registre de reserves'!$T$2:$T$1178,"SI",'Registre de reserves'!$I$2:$I$1178,'2025'!$A27,'Registre de reserves'!$B$2:$B$1178,'2025'!R$2,Tabla1[ANY],'2025'!$Z$2) -> 0 | S27: =IF(R$22=0,0,R27/R$22) -> 0 | T27: =SUMIFS('Registre de reserves'!$R$2:$R$1178,'Registre de reserves'!$T$2:$T$1178,"SI",'Registre de reserves'!$I$2:$I$1178,'2025'!$A27,'Registre de reserves'!$B$2:$B$1178,'2025'!T$2,Tabla1[ANY],'2025'!$Z$2) -> 0 | U27: =IF(T$22=0,0,T27/T$22) -> 0 | V27: =SUMIFS('Registre de reserves'!$R$2:$R$1178,'Registre de reserves'!$T$2:$T$1178,"SI",'Registre de reserves'!$I$2:$I$1178,'2025'!$A27,'Registre de reserves'!$B$2:$B$1178,'2025'!V$2,Tabla1[ANY],'2025'!$Z$2) -> 0 | W27: =IF(V$22=0,0,V27/V$22) -> 0 | X27: =SUMIFS('Registre de reserves'!$R$2:$R$1178,'Registre de reserves'!$T$2:$T$1178,"SI",'Registre de reserves'!$I$2:$I$1178,'2025'!$A27,'Registre de reserves'!$B$2:$B$1178,'2025'!X$2,Tabla1[ANY],'2025'!$Z$2) -> 0 | Y27: =IF(X$22=0,0,X27/X$22) -> 0 | Z27: =B27+D27+F27+H27+J27+L27+N27+P27+R27+T27+V27+X27 -> 0 | AA27: =IF(Z$22=0,0,Z27/Z$22) -> 0 | AB27: =Z27/$A$2 -> 0
A28: Nit | B28: =SUMIFS('Registre de reserves'!$R$2:$R$1178,'Registre de reserves'!$T$2:$T$1178,"SI",'Registre de reserves'!$I$2:$I$1178,'2025'!$A28,'Registre de reserves'!$B$2:$B$1178,'2025'!B$2,Tabla1[ANY],'2025'!$Z$2) -> 240 | C28: =IF(B$22=0,0,B28/B$22) -> 0.8 | D28: =SUMIFS('Registre de reserves'!$R$2:$R$1178,'Registre de reserves'!$T$2:$T$1178,"SI",'Registre de reserves'!$I$2:$I$1178,'2025'!$A28,'Registre de reserves'!$B$2:$B$1178,'2025'!D$2,Tabla1[ANY],'2025'!$Z$2) -> 60 | E28: =IF(D$22=0,0,D28/D$22) -> 0.75 | F28: =SUMIFS('Registre de reserves'!$R$2:$R$1178,'Registre de reserves'!$T$2:$T$1178,"SI",'Registre de reserves'!$I$2:$I$1178,'2025'!$A28,'Registre de reserves'!$B$2:$B$1178,'2025'!F$2,Tabla1[ANY],'2025'!$Z$2) -> 0 | G28: =IF(F$22=0,0,F28/F$22) -> 0 | H28: =SUMIFS('Registre de reserves'!$R$2:$R$1178,'Registre de reserves'!$T$2:$T$1178,"SI",'Registre de reserves'!$I$2:$I$1178,'2025'!$A28,'Registre de reserves'!$B$2:$B$1178,'2025'!H$2,Tabla1[ANY],'2025'!$Z$2) -> 180 | I28: =IF(H$22=0,0,H28/H$22) -> 1 | J28: =SUMIFS('Registre de reserves'!$R$2:$R$1178,'Registre de reserves'!$T$2:$T$1178,"SI",'Registre de reserves'!$I$2:$I$1178,'2025'!$A28,'Registre de reserves'!$B$2:$B$1178,'2025'!J$2,Tabla1[ANY],'2025'!$Z$2) -> 60 | K28: =IF(J$22=0,0,J28/J$22) -> 0.66666667 | L28: =SUMIFS('Registre de reserves'!$R$2:$R$1178,'Registre de reserves'!$T$2:$T$1178,"SI",'Registre de reserves'!$I$2:$I$1178,'2025'!$A28,'Registre de reserves'!$B$2:$B$1178,'2025'!L$2,Tabla1[ANY],'2025'!$Z$2) -> 0 | M28: =IF(L$22=0,0,L28/L$22) -> 0 | N28: =SUMIFS('Registre de reserves'!$R$2:$R$1178,'Registre de reserves'!$T$2:$T$1178,"SI",'Registre de reserves'!$I$2:$I$1178,'2025'!$A28,'Registre de reserves'!$B$2:$B$1178,'2025'!N$2,Tabla1[ANY],'2025'!$Z$2) -> 0 | O28: =IF(N$22=0,0,N28/N$22) -> 0 | P28: =SUMIFS('Registre de reserves'!$R$2:$R$1178,'Registre de reserves'!$T$2:$T$1178,"SI",'Registre de reserves'!$I$2:$I$1178,'2025'!$A28,'Registre de reserves'!$B$2:$B$1178,'2025'!P$2,Tabla1[ANY],'2025'!$Z$2) -> 0 | Q28: =IF(P$22=0,0,P28/P$22) -> 0 | R28: =SUMIFS('Registre de reserves'!$R$2:$R$1178,'Registre de reserves'!$T$2:$T$1178,"SI",'Registre de reserves'!$I$2:$I$1178,'2025'!$A28,'Registre de reserves'!$B$2:$B$1178,'2025'!R$2,Tabla1[ANY],'2025'!$Z$2) -> 0 | S28: =IF(R$22=0,0,R28/R$22) -> 0 | T28: =SUMIFS('Registre de reserves'!$R$2:$R$1178,'Registre de reserves'!$T$2:$T$1178,"SI",'Registre de reserves'!$I$2:$I$1178,'2025'!$A28,'Registre de reserves'!$B$2:$B$1178,'2025'!T$2,Tabla1[ANY],'2025'!$Z$2) -> 0 | U28: =IF(T$22=0,0,T28/T$22) -> 0 | V28: =SUMIFS('Registre de reserves'!$R$2:$R$1178,'Registre de reserves'!$T$2:$T$1178,"SI",'Registre de reserves'!$I$2:$I$1178,'2025'!$A28,'Registre de reserves'!$B$2:$B$1178,'2025'!V$2,Tabla1[ANY],'2025'!$Z$2) -> 0 | W28: =IF(V$22=0,0,V28/V$22) -> 0 | X28: =SUMIFS('Registre de reserves'!$R$2:$R$1178,'Registre de reserves'!$T$2:$T$1178,"SI",'Registre de reserves'!$I$2:$I$1178,'2025'!$A28,'Registre de reserves'!$B$2:$B$1178,'2025'!X$2,Tabla1[ANY],'2025'!$Z$2) -> 0 | Y28: =IF(X$22=0,0,X28/X$22) -> 0 | Z28: =B28+D28+F28+H28+J28+L28+N28+P28+R28+T28+V28+X28 -> 540 | AA28: =IF(Z$22=0,0,Z28/Z$22) -> 0.76056338 | AB28: =Z28/$A$2 -> 90
A29: Tarda+Nit | B29: =SUMIFS('Registre de reserves'!$R$2:$R$1178,'Registre de reserves'!$T$2:$T$1178,"SI",'Registre de reserves'!$I$2:$I$1178,'2025'!$A29,'Registre de reserves'!$B$2:$B$1178,'2025'!B$2,Tabla1[ANY],'2025'!$Z$2) -> 0 | C29: =IF(B$22=0,0,B29/B$22) -> 0 | D29: =SUMIFS('Registre de reserves'!$R$2:$R$1178,'Registre de reserves'!$T$2:$T$1178,"SI",'Registre de reserves'!$I$2:$I$1178,'2025'!$A29,'Registre de reserves'!$B$2:$B$1178,'2025'!D$2,Tabla1[ANY],'2025'!$Z$2) -> 0 | E29: =IF(D$22=0,0,D29/D$22) -> 0 | F29: =SUMIFS('Registre de reserves'!$R$2:$R$1178,'Registre de reserves'!$T$2:$T$1178,"SI",'Registre de reserves'!$I$2:$I$1178,'2025'!$A29,'Registre de reserves'!$B$2:$B$1178,'2025'!F$2,Tabla1[ANY],'2025'!$Z$2) -> 0 | G29: =IF(F$22=0,0,F29/F$22) -> 0 | H29: =SUMIFS('Registre de reserves'!$R$2:$R$1178,'Registre de reserves'!$T$2:$T$1178,"SI",'Registre de reserves'!$I$2:$I$1178,'2025'!$A29,'Registre de reserves'!$B$2:$B$1178,'2025'!H$2,Tabla1[ANY],'2025'!$Z$2) -> 0 | I29: =IF(H$22=0,0,H29/H$22) -> 0 | J29: =SUMIFS('Registre de reserves'!$R$2:$R$1178,'Registre de reserves'!$T$2:$T$1178,"SI",'Registre de reserves'!$I$2:$I$1178,'2025'!$A29,'Registre de reserves'!$B$2:$B$1178,'2025'!J$2,Tabla1[ANY],'2025'!$Z$2) -> 0 | K29: =IF(J$22=0,0,J29/J$22) -> 0 | L29: =SUMIFS('Registre de reserves'!$R$2:$R$1178,'Registre de reserves'!$T$2:$T$1178,"SI",'Registre de reserves'!$I$2:$I$1178,'2025'!$A29,'Registre de reserves'!$B$2:$B$1178,'2025'!L$2,Tabla1[ANY],'2025'!$Z$2) -> 60 | M29: =IF(L$22=0,0,L29/L$22) -> 1 | N29: =SUMIFS('Registre de reserves'!$R$2:$R$1178,'Registre de reserves'!$T$2:$T$1178,"SI",'Registre de reserves'!$I$2:$I$1178,'2025'!$A29,'Registre de reserves'!$B$2:$B$1178,'2025'!N$2,Tabla1[ANY],'2025'!$Z$2) -> 0 | O29: =IF(N$22=0,0,N29/N$22) -> 0 | P29: =SUMIFS('Registre de reserves'!$R$2:$R$1178,'Registre de reserves'!$T$2:$T$1178,"SI",'Registre de reserves'!$I$2:$I$1178,'2025'!$A29,'Registre de reserves'!$B$2:$B$1178,'2025'!P$2,Tabla1[ANY],'2025'!$Z$2) -> 0 | Q29: =IF(P$22=0,0,P29/P$22) -> 0 | R29: =SUMIFS('Registre de reserves'!$R$2:$R$1178,'Registre de reserves'!$T$2:$T$1178,"SI",'Registre de reserves'!$I$2:$I$1178,'2025'!$A29,'Registre de reserves'!$B$2:$B$1178,'2025'!R$2,Tabla1[ANY],'2025'!$Z$2) -> 0 | S29: =IF(R$22=0,0,R29/R$22) -> 0 | T29: =SUMIFS('Registre de reserves'!$R$2:$R$1178,'Registre de reserves'!$T$2:$T$1178,"SI",'Registre de reserves'!$I$2:$I$1178,'2025'!$A29,'Registre de reserves'!$B$2:$B$1178,'2025'!T$2,Tabla1[ANY],'2025'!$Z$2) -> 0 | U29: =IF(T$22=0,0,T29/T$22) -> 0 | V29: =SUMIFS('Registre de reserves'!$R$2:$R$1178,'Registre de reserves'!$T$2:$T$1178,"SI",'Registre de reserves'!$I$2:$I$1178,'2025'!$A29,'Registre de reserves'!$B$2:$B$1178,'2025'!V$2,Tabla1[ANY],'2025'!$Z$2) -> 0 | W29: =IF(V$22=0,0,V29/V$22) -> 0 | X29: =SUMIFS('Registre de reserves'!$R$2:$R$1178,'Registre de reserves'!$T$2:$T$1178,"SI",'Registre de reserves'!$I$2:$I$1178,'2025'!$A29,'Registre de reserves'!$B$2:$B$1178,'2025'!X$2,Tabla1[ANY],'2025'!$Z$2) -> 0 | Y29: =IF(X$22=0,0,X29/X$22) -> 0 | Z29: =B29+D29+F29+H29+J29+L29+N29+P29+R29+T29+V29+X29 -> 60 | AA29: =IF(Z$22=0,0,Z29/Z$22) -> 0.084507042 | AB29: =Z29/$A$2 -> 10
